Workbook

Sheet Cover
B4: NASDAQ: TSLA
B6: TESLA, INC.
B7: FINANCIAL MODEL & VALUATION
B10: Integrated Financial Model | FY2021A – FY2030E
B11: DCF | Trading Comparables | Precedent Transactions
B13: MODEL PROFILE
B14: PREPARED BY | D14: Yash Andhrutkar
B15: MODEL PERIOD | D15: FY2021A – FY2030E (5 historical years, 5 forecast years)
B16: CURRENCY & UNITS | D16: USD millions, except per-share and operating data
B17: HISTORICAL SOURCE | D17: Tesla, Inc. SEC filings, FY2021–FY2025
B18: MARKET DATA | D18: 3 September 2026 close
B19: LAST UPDATED | D19: 46272
B21: NAVIGATION
B22: → Model Summary | D22: KPIs, revenue mix, margins, FCFF, football field, scenario strip
B23: → Assumptions | D23: Every driver, its rationale and the Bear/Base/Bull grids
B24: → Scenario Analysis | D24: Bear, Base and Bull built in parallel from one model
B25: → Valuation | D25: DCF, WACC × TGR sensitivity, exit-multiple and beta cross-checks
B26: → Reverse DCF | D26: What the market price would require
B27: → Sources & Notes | D27: Every external input, with its source
B30: Academic / portfolio financial model. Historical figures are taken from Tesla, Inc. SEC filings; FY2026E–FY2030E figures are the author's own forecasts. Trading comparables are priced at the 3 September 2026 close. This workbook is not investment advice and no recommendation is made to any person to buy or sell any security.

Sheet Model Summary
B1: TESLA, INC. · MODEL SUMMARY | M1: ="NASDAQ: TSLA | FY2021A–FY2030E | SELECTED CASE: "&UPPER(CHOOSE(Assumptions!$L$2,"Bear","Base","Bull")) -> NASDAQ: TSLA | FY2021A–FY2030E | SELECTED CASE: BASE
B3: Integrated three-statement model · driver-based forecast · DCF and trading-comparables valuation · all figures link live to the model
B6: FY2030E REVENUE | G6: FY2030E EBIT MARGIN | L6: DCF IMPLIED VALUE / SHARE | Q6: WACC
B7: =IS!P8 -> 161408.21 | G7: =IS!P26 -> 0.1274056 | L7: =Valuation!K56 -> 32.569468 | Q7: =Valuation!F17 -> 0.12380656
B8: ="FY2025A–FY2030E CAGR "&TEXT((IS!P8/IS!K8)^(1/5)-1,"0.0%") -> FY2025A–FY2030E CAGR 11.2% | G8: ="from "&TEXT(IS!K26,"0.0%")&" in FY2025A" -> from 4.6% in FY2025A | L8: ="Sensitivity "&TEXT(Valuation!E84,"$0.00")&" – "&TEXT(Valuation!I84,"$0.00") -> Sensitivity $26.18 – $45.82 | Q8: ="CAPM · beta "&TEXT(Assumptions!G59,"0.00")&" · TGR "&TEXT(Valuation!F18,"0.0%") -> CAPM · beta 1.85 · TGR 3.8%
B10: CURRENT MARKET PRICE | G10: COMPARABLE COS. BASE VALUE | L10: FY2025A–FY2030E REVENUE CAGR | Q10: TERMINAL GROWTH RATE
B11: =Valuation!G87 -> 376.37 | G11: =Valuation!G85 -> 36.78365 | L11: =(IS!P8/IS!K8)^(1/5)-1 -> 0.11224055 | Q11: =Valuation!F18 -> 0.038
B12: "3 September 2026 close" | G12: ="Range "&TEXT(Valuation!E85,"$0.00")&" – "&TEXT(Valuation!I85,"$0.00") -> Range $30.27 – $51.77 | L12: ="$"&TEXT(IS!K8,"#,##0")&"M → $"&TEXT(IS!P8,"#,##0")&"M" -> $94,827M → $161,408M | Q12: ="Terminal value = "&TEXT(Valuation!K47,"0%")&" of enterprise value" -> Terminal value = 78% of enterprise value
L46: ="Football field: market-price bar runs off the plot area — the axis is capped at $60 so the "&"DCF and comparable ranges keep full resolution. Market price = "&TEXT(Valuation!G87,"$0.00")&"." -> Football field: market-price bar runs off the plot area — the axis is capped at $60 so the DCF and comparable ranges keep full resolution. Market price = $376.37.
B47: VALUATION SUMMARY — IMPLIED SHARE PRICE | L47: MODEL INTEGRITY & KEY OUTPUTS
B48: Method | G48: Low | H48: Base | I48: High | J48: vs. market | L48: Balance sheet check, FY2021A–FY2030E | R48: ='Model Checks'!E6 -> PASS
B49: Discounted Cash Flow | G49: =Valuation!E84 -> 26.184574 | H49: =Valuation!G84 -> 32.569468 | I49: =Valuation!I84 -> 45.82243 | J49: =Valuation!G84/Valuation!$G$87-1 -> -0.91346423 | L49: Cash check, FY2021A–FY2030E | R49: ='Model Checks'!E7 -> PASS
B50: Comparable Companies | G50: =Valuation!E85 -> 30.271642 | H50: =Valuation!G85 -> 36.78365 | I50: =Valuation!I85 -> 51.770477 | J50: =Valuation!G85/Valuation!$G$87-1 -> -0.90226732 | L50: WACC > terminal growth | R50: ='Model Checks'!E11 -> PASS
B51: Current Market Price | G51: – | H51: =Valuation!G87 -> 376.37 | I51: – | J51: – | L51: All model checks (see Model Checks sheet) | R51: ='Model Checks'!E18 -> PASS
B53: SCENARIO VALUATION — ONE INTEGRATED MODEL, THREE CASES
B54: Case | E54: FY30E revenue | G54: FY30E EBIT margin | H54: FY30E FCFF | I54: Enterprise value | J54: Equity value | L54: DCF $/share | M54: vs. market | N54: Scenario character
B55: Bear | E55: ='Scenario Analysis'!G6 -> 113105.54 | G55: ='Scenario Analysis'!G11 -> 0.060189657 | H55: ='Scenario Analysis'!G13 -> 2369.8931 | I55: ='Scenario Analysis'!G14 -> 16863.276 | J55: ='Scenario Analysis'!G15 -> 51818.276 | L55: ='Scenario Analysis'!G16 -> 13.118551 | M55: ='Scenario Analysis'!G17 -> -0.96514454 | N55: Slower deliveries, sustained pricing pressure, weaker margin recovery, higher capex
B56: Base | E56: ='Scenario Analysis'!I6 -> 161408.21 | G56: ='Scenario Analysis'!I11 -> 0.1274056 | H56: ='Scenario Analysis'!I13 -> 10815 | I56: ='Scenario Analysis'!I14 -> 93694.398 | J56: ='Scenario Analysis'!I15 -> 128649.4 | L56: ='Scenario Analysis'!I16 -> 32.569468 | M56: ='Scenario Analysis'!I17 -> -0.91346423 | N56: Current fundamental forecast
B57: Bull | E57: ='Scenario Analysis'!K6 -> 206513.16 | G57: ='Scenario Analysis'!K11 -> 0.17008755 | H57: ='Scenario Analysis'!K13 -> 20083.529 | I57: ='Scenario Analysis'!K14 -> 176169.41 | J57: ='Scenario Analysis'!K15 -> 211124.41 | L57: ='Scenario Analysis'!K16 -> 53.449218 | M57: ='Scenario Analysis'!K17 -> -0.85798757 | N57: Stronger volume and mix, faster Energy scaling, full operating leverage
B59: ="Selected case: "&UPPER(CHOOSE(Assumptions!$L$2,"Bear","Base","Bull"))&". Modelled fundamentals imply "&TEXT(Valuation!K56,"$0.00")&" per share on the DCF and "&TEXT(Valuation!G85,"$0.00")&" on trading comparables, against a market price of "&TEXT(Valuation!G87,"$0.00")&". Across Bear to Bull the DCF spans "&TEXT('Scenario Analysis'!G16,"$0.00")&" to "&TEXT('Scenario Analysis'!K16,"$0.00")&", so the gap to the market price is not a scenario question. The Reverse DCF sheet shows what the market price would require: roughly "&TEXT('Reverse DCF'!F61,"0.0")&"x the Base Case FY2030E free cash flow." -> Selected case: BASE. Modelled fundamentals imply $32.57 per share on the DCF and $36.78 on trading comparables, against a market price of $376.37. Across Bear to Bull the DCF spans $13.12 to $53.45, so the gap to the market price is not a scenario question. The Reverse DCF sheet shows what the market price would require: roughly 15.7x the Base Case FY2030E free cash flow.
B61: Every figure and chart on this sheet is linked live to the model. Chart sources — revenue mix: IS!G5:P7 · margins: 'Ratio Analysis'!I40:R47 · FCFF: Valuation!L28:P28 · football field: Valuation!C91:F93. Scenario strip: 'Scenario Analysis'!G6:K17.

Sheet Assumptions
A1: TESLA, INC. | E1: ◄ Cover | G1: ASSUMPTIONS | AA1: HELPER COLUMN — full text of every forecast rationale, kept here so the wording stays auditable and searchable. The user-facing version is displayed in the callout boxes beside each assumption block. Column is hidden by default.
A2: USD millions except per-share and operating data · Blue = input · Black = same-sheet formula · Green = cross-sheet link · Shaded = scenario-driven | K2: SCENARIO ▸ | L2: 2 | M2: =CHOOSE($L$2,"Bear","Base","Bull") -> Base | N2: =CHOOSE($L$2,"case — downside operating environment","case — current fundamental forecast","case — strong but defensible execution") -> case — current fundamental forecast
E3: Unit | G3: FY21A | H3: FY22A | I3: FY23A | J3: FY24A | K3: FY25A | L3: FY26E | M3: FY27E | N3: FY28E | O3: FY29E | P3: FY30E
Q4: FORECAST RATIONALE (FY2026E – FY2030E)
A5: AUTOMOTIVE | AA5: AUTOMOTIVE | Vehicle deliveries — recovery from 1.64m in FY2025A to 2.54m by FY2030E, a 9.2% CAGR (+6%, +10%, +12%, +10%, +8%). Growth is rebuilt gradually rather than extrapolated from the FY2021–FY2023 ramp. ASP per delivery — (3.0%), (2.0%), then +1.0%, +1.0%, +2.0%. Pricing stays under competitive pressure near term before stabilising, so the forecast never relies on unit growth alone. Regulatory credits — declining 30%, 20%, 10%, 5%, 5% as other OEMs meet emissions rules from their own fleets — treated as a wasting revenue stream, not a perpetual one. Automotive gross margin — 19.0% rising to 23.0%: a partial recovery from the depressed FY2025A level on scale and manufacturing cost, deliberately held below the FY2022 peak.
C6: Vehicle Deliveries (context) | E6: units | G6: ='Revenue Build-up'!G5 -> 936172 | H6: ='Revenue Build-up'!H5 -> 1313851 | I6: ='Revenue Build-up'!I5 -> 1808581 | J6: ='Revenue Build-up'!J5 -> 1789226 | K6: ='Revenue Build-up'!K5 -> 1636129 | L6: ='Revenue Build-up'!L5 -> 1734296.7 | M6: ='Revenue Build-up'!M5 -> 1907726.4 | N6: ='Revenue Build-up'!N5 -> 2136653.6 | ... P6: ='Revenue Build-up'!P5 -> 2538344.5
C7: Delivery Growth % | H7: ='Revenue Build-up'!H5/'Revenue Build-up'!G5-1 -> 0.40342907 | I7: ='Revenue Build-up'!I5/'Revenue Build-up'!H5-1 -> 0.37654955 | J7: ='Revenue Build-up'!J5/'Revenue Build-up'!I5-1 -> -0.01070176 | K7: ='Revenue Build-up'!K5/'Revenue Build-up'!J5-1 -> -0.085566049 | L7: =CHOOSE($L$2,L68,L69,L70) -> 0.06 | M7: =CHOOSE($L$2,M68,M69,M70) -> 0.1 | N7: =CHOOSE($L$2,N68,N69,N70) -> 0.12 | O7: =CHOOSE($L$2,O68,O69,O70) -> 0.1 | P7: =CHOOSE($L$2,P68,P69,P70) -> 0.08
C9: Automotive Revenue per Delivery (context) | E9: $/unit | G9: ='Revenue Build-up'!G6 -> 48887.384 | H9: ='Revenue Build-up'!H6 -> 53039.5 | I9: ='Revenue Build-up'!I6 -> 44581.36 | J9: ='Revenue Build-up'!J6 -> 41530.248 | K9: ='Revenue Build-up'!K6 -> 41276.085 | L9: ='Revenue Build-up'!L6 -> 40037.803 | M9: ='Revenue Build-up'!M6 -> 39237.047 | N9: ='Revenue Build-up'!N6 -> 39629.417 | ... P9: ='Revenue Build-up'!P6 -> 40826.225
C10: ASP Growth % | H10: ='Revenue Build-up'!H6/'Revenue Build-up'!G6-1 -> 0.084932259 | I10: ='Revenue Build-up'!I6/'Revenue Build-up'!H6-1 -> -0.1594687 | J10: ='Revenue Build-up'!J6/'Revenue Build-up'!I6-1 -> -0.068439173 | K10: ='Revenue Build-up'!K6/'Revenue Build-up'!J6-1 -> -0.0061199508 | L10: =CHOOSE($L$2,L71,L72,L73) -> -0.03 | M10: =CHOOSE($L$2,M71,M72,M73) -> -0.02 | N10: =CHOOSE($L$2,N71,N72,N73) -> 0.01 | O10: =CHOOSE($L$2,O71,O72,O73) -> 0.01 | P10: =CHOOSE($L$2,P71,P72,P73) -> 0.02
C11: Automotive Regulatory Credits (context) | E11: $M | G11: ='Revenue Build-up'!G8 -> 1465 | H11: ='Revenue Build-up'!H8 -> 1776 | I11: ='Revenue Build-up'!I8 -> 1790 | J11: ='Revenue Build-up'!J8 -> 2763 | K11: ='Revenue Build-up'!K8 -> 1993 | L11: ='Revenue Build-up'!L8 -> 1395.1 | M11: ='Revenue Build-up'!M8 -> 1116.08 | N11: ='Revenue Build-up'!N8 -> 1004.472 | ... P11: ='Revenue Build-up'!P8 -> 906.53598
C12: Regulatory Credit Revenue Growth % | H12: ='Revenue Build-up'!H8/'Revenue Build-up'!G8-1 -> 0.21228669 | I12: ='Revenue Build-up'!I8/'Revenue Build-up'!H8-1 -> 0.0078828829 | J12: ='Revenue Build-up'!J8/'Revenue Build-up'!I8-1 -> 0.54357542 | K12: ='Revenue Build-up'!K8/'Revenue Build-up'!J8-1 -> -0.27868259 | L12: =CHOOSE($L$2,L74,L75,L76) -> -0.3 | M12: =CHOOSE($L$2,M74,M75,M76) -> -0.2 | N12: =CHOOSE($L$2,N74,N75,N76) -> -0.1 | O12: =CHOOSE($L$2,O74,O75,O76) -> -0.05 | P12: =CHOOSE($L$2,P74,P75,P76) -> -0.05
C14: Automotive Gross Margin % | G14: ='Cost Build-up'!G6 -> 0.29300051 | H14: ='Cost Build-up'!H6 -> 0.2848227 | I14: ='Cost Build-up'!I6 -> 0.19449399 | J14: ='Cost Build-up'!J6 -> 0.18420916 | K14: ='Cost Build-up'!K6 -> 0.1777896 | L14: =CHOOSE($L$2,L77,L78,L79) -> 0.19 | M14: =CHOOSE($L$2,M77,M78,M79) -> 0.2 | N14: =CHOOSE($L$2,N77,N78,N79) -> 0.21 | O14: =CHOOSE($L$2,O77,O78,O79) -> 0.22 | P14: =CHOOSE($L$2,P77,P78,P79) -> 0.23
A16: ENERGY GENERATION & STORAGE | AA16: ENERGY GENERATION & STORAGE | Revenue growth — 30% in FY2026E decelerating to 15% by FY2030E ($12,771M → $33,794M). The fastest-growing modelled segment; deceleration reflects a larger base, not weaker demand. Gross margin — 30.0% rising to 32.0% as deployments scale and mix shifts toward grid-scale storage.
C17: Energy Revenue Growth % | H17: ='Revenue Build-up'!H12/'Revenue Build-up'!G12-1 -> 0.40157763 | I17: ='Revenue Build-up'!I12/'Revenue Build-up'!H12-1 -> 0.54387311 | J17: ='Revenue Build-up'!J12/'Revenue Build-up'!I12-1 -> 0.67125104 | K17: ='Revenue Build-up'!K12/'Revenue Build-up'!J12-1 -> 0.26621059 | L17: =CHOOSE($L$2,L80,L81,L82) -> 0.3 | M17: =CHOOSE($L$2,M80,M81,M82) -> 0.25 | N17: =CHOOSE($L$2,N80,N81,N82) -> 0.2 | O17: =CHOOSE($L$2,O80,O81,O82) -> 0.18 | P17: =CHOOSE($L$2,P80,P81,P82) -> 0.15
C18: Energy Gross Margin % | G18: ='Cost Build-up'!G11 -> -0.046253137 | H18: ='Cost Build-up'!H11 -> 0.073676132 | I18: ='Cost Build-up'!I11 -> 0.18906379 | J18: ='Cost Build-up'!J11 -> 0.26174896 | K18: ='Cost Build-up'!K11 -> 0.29770574 | L18: =CHOOSE($L$2,L83,L84,L85) -> 0.3 | M18: =CHOOSE($L$2,M83,M84,M85) -> 0.31 | N18: =CHOOSE($L$2,N83,N84,N85) -> 0.32 | O18: =CHOOSE($L$2,O83,O84,O85) -> 0.32 | P18: =CHOOSE($L$2,P83,P84,P85) -> 0.32
A20: SERVICES & OTHER | AA20: SERVICES & OTHER | Revenue growth — 15% decelerating to 11%, tied to the growing installed vehicle base — after-sales, used vehicles, charging and insurance. Gross margin — 12.0% rising to 15.0% on maturing service economics; kept well below the other segments because the mix stays weighted to lower-margin activity.
C21: Services & Other Revenue Growth % | H21: ='Revenue Build-up'!H15/'Revenue Build-up'!G15-1 -> 0.60205155 | I21: ='Revenue Build-up'!I15/'Revenue Build-up'!H15-1 -> 0.36578559 | J21: ='Revenue Build-up'!J15/'Revenue Build-up'!I15-1 -> 0.26625796 | K21: ='Revenue Build-up'!K15/'Revenue Build-up'!J15-1 -> 0.18948168 | L21: =CHOOSE($L$2,L86,L87,L88) -> 0.15 | M21: =CHOOSE($L$2,M86,M87,M88) -> 0.14 | N21: =CHOOSE($L$2,N86,N87,N88) -> 0.13 | O21: =CHOOSE($L$2,O86,O87,O88) -> 0.12 | P21: =CHOOSE($L$2,P86,P87,P88) -> 0.11
C22: Services Gross Margin % | G22: ='Cost Build-up'!G16 -> -0.027354024 | H22: ='Cost Build-up'!H16 -> 0.034641274 | I22: ='Cost Build-up'!I16 -> 0.058781103 | J22: ='Cost Build-up'!J16 -> 0.058192519 | K22: ='Cost Build-up'!K16 -> 0.074301676 | L22: =CHOOSE($L$2,L89,L90,L91) -> 0.12 | M22: =CHOOSE($L$2,M89,M90,M91) -> 0.13 | N22: =CHOOSE($L$2,N89,N90,N91) -> 0.14 | O22: =CHOOSE($L$2,O89,O90,O91) -> 0.15 | P22: =CHOOSE($L$2,P89,P90,P91) -> 0.15
A24: OPERATING COSTS | AA24: OPERATING EXPENSES | R&D — 7.0% of revenue falling to 6.0%. Absolute spend still rises every year — the ratio falls because revenue grows faster, giving leverage without assuming a cut in investment. SG&A — 6.0% of revenue falling to 5.0% on the same logic. Restructuring is set to nil, being non-recurring.
C25: R&D as % of Total Revenue | G25: ='Cost Build-up'!G24/'Revenue Build-up'!G18 -> 0.04817643 | H25: ='Cost Build-up'!H24/'Revenue Build-up'!H18 -> 0.037747661 | I25: ='Cost Build-up'!I24/'Revenue Build-up'!I18 -> 0.041013506 | J25: ='Cost Build-up'!J24/'Revenue Build-up'!J18 -> 0.046473539 | K25: ='Cost Build-up'!K24/'Revenue Build-up'!K18 -> 0.067607327 | L25: =CHOOSE($L$2,L92,L93,L94) -> 0.07 | M25: =CHOOSE($L$2,M92,M93,M94) -> 0.07 | N25: =CHOOSE($L$2,N92,N93,N94) -> 0.065 | O25: =CHOOSE($L$2,O92,O93,O94) -> 0.06 | P25: =CHOOSE($L$2,P92,P93,P94) -> 0.06
C26: SG&A as % of Total Revenue | G26: ='Cost Build-up'!G26/'Revenue Build-up'!G18 -> 0.08392323 | H26: ='Cost Build-up'!H26/'Revenue Build-up'!H18 -> 0.048439763 | I26: ='Cost Build-up'!I26/'Revenue Build-up'!I18 -> 0.049600612 | J26: ='Cost Build-up'!J26/'Revenue Build-up'!J18 -> 0.052717781 | K26: ='Cost Build-up'!K26/'Revenue Build-up'!K18 -> 0.061522562 | L26: =CHOOSE($L$2,L95,L96,L97) -> 0.06 | M26: =CHOOSE($L$2,M95,M96,M97) -> 0.058 | N26: =CHOOSE($L$2,N95,N96,N97) -> 0.055 | O26: =CHOOSE($L$2,O95,O96,O97) -> 0.053 | P26: =CHOOSE($L$2,P95,P96,P97) -> 0.05
A28: WORKING CAPITAL & BALANCE SHEET DRIVERS | AA28: WORKING CAPITAL | Receivable, inventory and payable days — 18 → 17, 55 → 48 and 62 → 60 respectively: modest efficiency gains consistent with a maturing manufacturing base, not an aggressive release of working capital. Other current assets and accrued liabilities — 38% → 42% and 13% → 12% of revenue, both held close to their historical relationship to the top line. Deferred revenue — held at 3.5% of revenue for the current and non-current portions alike, in line with FY2023–FY2025 actuals. Why ratios, not plugs — each item is driven off revenue or COGS, so the balance sheet and cash flow statement respond consistently whenever the revenue build changes.
C29: Accounts Receivable (Days of Revenue) | G29: =BS!G6/IS!G8*365 -> 12.972986 | H29: =BS!H6/IS!H8*365 -> 13.226781 | I29: =BS!I6/IS!I8*365 -> 13.23117 | J29: =BS!J6/IS!J8*365 -> 16.507012 | K29: =BS!K6/IS!K8*365 -> 17.613549 | L29: 18 | M29: 18 | N29: 17 | O29: 17 | P29: 17
C30: Inventory (Days of COGS) | G30: =BS!G7/IS!G14*365 -> 52.249173 | H30: =BS!H7/IS!H14*365 -> 77.319128 | I30: =BS!I7/IS!I14*365 -> 62.865648 | J30: =BS!J7/IS!J14*365 -> 54.663572 | K30: =BS!K7/IS!K14*365 -> 58.187385 | L30: 55 | M30: 53 | N30: 50 | O30: 48 | P30: 48
C31: Accounts Payable (Days of COGS) | G31: =BS!G17/IS!G14*365 -> 90.984534 | H31: =BS!H17/IS!H14*365 -> 91.868782 | I31: =BS!I17/IS!I14*365 -> 66.579639 | J31: =BS!J17/IS!J14*365 -> 56.742398 | K31: =BS!K17/IS!K14*365 -> 62.784339 | L31: 62 | M31: 62 | N31: 60 | O31: 60 | P31: 60
C32: Other Current Assets (% of Revenue) | G32: =BS!G8/'Revenue Build-up'!G18 -> 0.03444624 | H32: =BS!H8/'Revenue Build-up'!H18 -> 0.10892195 | I32: =BS!I8/'Revenue Build-up'!I18 -> 0.16620338 | J32: =BS!J8/'Revenue Build-up'!J18 -> 0.26395742 | K32: =BS!K8/'Revenue Build-up'!K18 -> 0.37079102 | L32: 0.38 | M32: 0.39 | N32: 0.4 | O32: 0.41 | P32: 0.42
C33: Accrued Liabilities & Other (% of Revenue) | G33: =BS!G18/'Revenue Build-up'!G18 -> 0.12344165 | H33: =BS!H18/'Revenue Build-up'!H18 -> 0.10072181 | I33: =BS!I18/'Revenue Build-up'!I18 -> 0.093827824 | J33: =BS!J18/'Revenue Build-up'!J18 -> 0.10976559 | K33: =BS!K18/'Revenue Build-up'!K18 -> 0.14003396 | L33: 0.13 | M33: 0.13 | N33: 0.125 | O33: 0.125 | P33: 0.12
C34: Deferred Revenue - Current (% of Revenue) | G34: =BS!G19/'Revenue Build-up'!G18 -> 0.026884417 | H34: =BS!H19/'Revenue Build-up'!H18 -> 0.021445582 | I34: =BS!I19/'Revenue Build-up'!I18 -> 0.029595032 | J34: =BS!J19/'Revenue Build-up'!J18 -> 0.032429112 | K34: =BS!K19/'Revenue Build-up'!K18 -> 0.03610786 | L34: 0.035 | M34: 0.035 | N34: 0.035 | O34: 0.035 | P34: 0.035
C35: Operating Lease ROU Assets (% of Revenue) | G35: =BS!G12/'Revenue Build-up'!G18 -> 0.037456106 | H35: =BS!H12/'Revenue Build-up'!H18 -> 0.031462522 | I35: =BS!I12/'Revenue Build-up'!I18 -> 0.043193866 | J35: =BS!J12/'Revenue Build-up'!J18 -> 0.052820145 | K35: =BS!K12/'Revenue Build-up'!K18 -> 0.063557847 | L35: 0.06 | M35: 0.06 | N35: 0.06 | O35: 0.06 | P35: 0.06
C36: Deferred Revenue - Non-Current (% of Revenue) | G36: =BS!G24/'Revenue Build-up'!G18 -> 0.038124965 | H36: =BS!H24/'Revenue Build-up'!H18 -> 0.034420957 | I36: =BS!I24/'Revenue Build-up'!I18 -> 0.033594081 | J36: =BS!J24/'Revenue Build-up'!J18 -> 0.033954345 | K36: =BS!K24/'Revenue Build-up'!K18 -> 0.038290782 | L36: 0.035 | M36: 0.035 | N36: 0.035 | O36: 0.035 | P36: 0.035
C37: Other Non-Current Assets (% of Revenue) | G37: =BS!G13/'Revenue Build-up'!G18 -> 0.26254575 | H37: =BS!H13/'Revenue Build-up'!H18 -> 0.18794039 | I37: =BS!I13/'Revenue Build-up'!I18 -> 0.23867194 | J37: =BS!J13/'Revenue Build-up'!J18 -> 0.232511 | K37: =BS!K13/'Revenue Build-up'!K18 -> 0.23721092 | L37: 0.22 | M37: 0.21 | N37: 0.2 | O37: 0.2 | P37: 0.19
C38: Other Non-Current Liabilities (% of Revenue) | G38: =BS!G25/'Revenue Build-up'!G18 -> 0.076435725 | H38: =BS!H25/'Revenue Build-up'!H18 -> 0.070450026 | I38: =BS!I25/'Revenue Build-up'!I18 -> 0.086749403 | J38: =BS!J25/'Revenue Build-up'!J18 -> 0.10807657 | K38: =BS!K25/'Revenue Build-up'!K18 -> 0.13561538 | L38: 0.13 | M38: 0.125 | N38: 0.12 | O38: 0.12 | P38: 0.115
A40: CAPITAL EXPENDITURE & DEPRECIATION | AA40: CAPEX & DEPRECIATION | CapEx — 10.0% of revenue falling to 8.0% — absolute capital expenditure still rises to $12,913M by FY2030E while the intensity of the current expansion phase moderates. Depreciation — 16.5% of opening net PP&E falling to 15.0%, applied through the asset schedule so PP&E rolls forward on capex less depreciation.
C41: CapEx as % of Total Revenue | G41: ='Asset Schedule'!G6/'Revenue Build-up'!G18 -> 0.12043179 | H41: ='Asset Schedule'!H6/'Revenue Build-up'!H18 -> 0.087869191 | I41: ='Asset Schedule'!I6/'Revenue Build-up'!I18 -> 0.091957467 | J41: ='Asset Schedule'!J6/'Revenue Build-up'!J18 -> 0.11610196 | K41: ='Asset Schedule'!K6/'Revenue Build-up'!K18 -> 0.089921647 | L41: =CHOOSE($L$2,L98,L99,L100) -> 0.1 | M41: =CHOOSE($L$2,M98,M99,M100) -> 0.095 | N41: =CHOOSE($L$2,N98,N99,N100) -> 0.09 | O41: =CHOOSE($L$2,O98,O99,O100) -> 0.085 | P41: =CHOOSE($L$2,P98,P99,P100) -> 0.08
C42: Depreciation Rate (% of Opening Net PP&E) | G42: ='Asset Schedule'!G11 -> 0.22836746 | H42: ='Asset Schedule'!H11 -> 0.19842194 | I42: ='Asset Schedule'!I11 -> 0.19819093 | J42: ='Asset Schedule'!J11 -> 0.18058873 | K42: ='Asset Schedule'!K11 -> 0.17155933 | L42: 0.165 | M42: 0.16 | N42: 0.155 | O42: 0.15 | P42: 0.15
A44: LOANS & OTHER INCOME | AA44: FINANCING, TAX & EQUITY | Debt — held flat at the FY2025A closing balance with no net new borrowing; interest expense at 5.0% on the average balance. Return on cash — 4.5% falling to 4.0%, applied to the prior-year cash balance so the model stays free of circular references. Tax — normalised at 24.0%, replacing the distorted FY2023 actual (a one-off valuation-allowance release). Equity — stock-based compensation and net issuance at 4.0% of revenue falling to 3.5%; no dividends are assumed.
C45: Effective Interest Rate on Debt | G45: ='Loans & Other Income'!G11/'Loans & Other Income'!G5 -> 0.031741958 | H45: ='Loans & Other Income'!H11/'Loans & Other Income'!H5 -> 0.027948493 | I45: ='Loans & Other Income'!I11/'Loans & Other Income'!I5 -> 0.050338819 | J45: ='Loans & Other Income'!J11/'Loans & Other Income'!J5 -> 0.066921606 | K45: ='Loans & Other Income'!K11/'Loans & Other Income'!K5 -> 0.041154268 | L45: 0.05 | M45: 0.05 | N45: 0.05 | O45: 0.05 | P45: 0.05
C46: Return Rate on Cash & Investments | G46: ='Loans & Other Income'!G16/'Loans & Other Income'!G14 -> 0.003030303 | H46: ='Loans & Other Income'!H16/'Loans & Other Income'!H14 -> 0.017558899 | I46: ='Loans & Other Income'!I16/'Loans & Other Income'!I14 -> 0.065296622 | J46: ='Loans & Other Income'!J16/'Loans & Other Income'!J14 -> 0.096444048 | K46: ='Loans & Other Income'!K16/'Loans & Other Income'!K14 -> 0.10290334 | L46: 0.045 | M46: 0.045 | N46: 0.045 | O46: 0.04 | P46: 0.04
A48: TAX
C49: Effective / Normalized Tax Rate | G49: ='Tax Schedule'!G7 -> 0.11020022 | H49: ='Tax Schedule'!H7 -> 0.082513303 | I49: ='Tax Schedule'!I7 -> -0.50145393 | J49: ='Tax Schedule'!J7 -> 0.20433815 | K49: ='Tax Schedule'!K7 -> 0.2696097 | L49: 0.24 | M49: 0.24 | N49: 0.24 | O49: 0.24 | P49: 0.24
A51: EQUITY
C52: Stock-Based Comp & Net Equity Issuance (% of Revenue) | G52: ='Equity Schedule'!G6/'Revenue Build-up'!G18 -> 0.047284618 | H52: ='Equity Schedule'!H6/'Revenue Build-up'!H18 -> 0.029142422 | I52: ='Equity Schedule'!I6/'Revenue Build-up'!I18 -> 0.028055346 | J52: ='Equity Schedule'!J6/'Revenue Build-up'!J18 -> 0.035612652 | K52: ='Equity Schedule'!K6/'Revenue Build-up'!K18 -> 0.046389741 | L52: 0.04 | M52: 0.04 | N52: 0.038 | O52: 0.038 | P52: 0.035
C53: Dividend Payout | G53: 0 | H53: 0 | I53: 0 | J53: 0 | K53: 0 | L53: 0 | M53: 0 | N53: 0 | O53: 0 | P53: 0
A55: VALUATION ASSUMPTIONS | AA55: VALUATION INPUTS | WACC — built from CAPM — risk-free 4.77%, levered beta 1.84, equity risk premium 5.0%, pre-tax cost of debt 5.0% at the normalised 24% tax rate, weighted at market values. Terminal growth — 3.0%, at long-run nominal economic growth. No premium is embedded for autonomy, AI or robotics optionality, which the model does not value as separate cash-flow streams.
C56: Current Share Price (valuation-date close) | E56: $/share | G56: 376.37
C57: Common Shares Outstanding (Current) | E57: millions | G57: 3950
C58: Risk-Free Rate (10-Yr US Treasury) | G58: 0.0477
C59: Beta (Levered) | G59: 1.85
C60: Equity Risk Premium | G60: 0.0414
C61: Pre-Tax Cost of Debt | G61: 0.05
C62: Terminal Growth Rate | G62: 0.038
C63: Valuation Date (market data as of) | E63: date | G63: 46268
A65: SCENARIO ASSUMPTIONS — BEAR / BASE / BULL
A66: The eleven drivers below are the value-relevant operating assumptions. The active case is set by the selector in the header row and is highlighted. Working capital, depreciation, financing, tax, equity and valuation inputs are common to all three cases — the framework tests operating performance, not the financing build.
E67: Case | L67: =L3 -> FY26E | M67: =M3 -> FY27E | N67: =N3 -> FY28E | O67: =O3 -> FY29E | P67: =P3 -> FY30E
C68: Vehicle Delivery Growth % | E68: Bear | L68: 0 | M68: 0.03 | N68: 0.05 | O68: 0.05 | P68: 0.04
E69: Base | L69: 0.06 | M69: 0.1 | N69: 0.12 | O69: 0.1 | P69: 0.08
E70: Bull | L70: 0.1 | M70: 0.15 | N70: 0.17 | O70: 0.14 | P70: 0.12
C71: Automotive ASP Growth % | E71: Bear | L71: -0.06 | M71: -0.04 | N71: -0.02 | O71: 0 | P71: 0
E72: Base | L72: -0.03 | M72: -0.02 | N72: 0.01 | O72: 0.01 | P72: 0.02
E73: Bull | L73: -0.01 | M73: 0 | N73: 0.02 | O73: 0.02 | P73: 0.03
C74: Regulatory Credit Revenue Growth % | E74: Bear | L74: -0.4 | M74: -0.35 | N74: -0.25 | O74: -0.2 | P74: -0.2
E75: Base | L75: -0.3 | M75: -0.2 | N75: -0.1 | O75: -0.05 | P75: -0.05
E76: Bull | L76: -0.25 | M76: -0.15 | N76: -0.05 | O76: 0 | P76: 0
C77: Automotive Gross Margin % | E77: Bear | L77: 0.165 | M77: 0.17 | N77: 0.175 | O77: 0.18 | P77: 0.185
E78: Base | L78: 0.19 | M78: 0.2 | N78: 0.21 | O78: 0.22 | P78: 0.23
E79: Bull | L79: 0.21 | M79: 0.23 | N79: 0.245 | O79: 0.255 | P79: 0.26
C80: Energy Revenue Growth % | E80: Bear | L80: 0.2 | M80: 0.15 | N80: 0.12 | O80: 0.1 | P80: 0.08
E81: Base | L81: 0.3 | M81: 0.25 | N81: 0.2 | O81: 0.18 | P81: 0.15
E82: Bull | L82: 0.38 | M82: 0.32 | N82: 0.27 | O82: 0.23 | P82: 0.2
C83: Energy Gross Margin % | E83: Bear | L83: 0.26 | M83: 0.26 | N83: 0.27 | O83: 0.27 | P83: 0.27
E84: Base | L84: 0.3 | M84: 0.31 | N84: 0.32 | O84: 0.32 | P84: 0.32
E85: Bull | L85: 0.32 | M85: 0.33 | N85: 0.34 | O85: 0.35 | P85: 0.35
C86: Services & Other Revenue Growth % | E86: Bear | L86: 0.1 | M86: 0.09 | N86: 0.08 | O86: 0.08 | P86: 0.07
E87: Base | L87: 0.15 | M87: 0.14 | N87: 0.13 | O87: 0.12 | P87: 0.11
E88: Bull | L88: 0.18 | M88: 0.17 | N88: 0.16 | O88: 0.15 | P88: 0.14
C89: Services Gross Margin % | E89: Bear | L89: 0.09 | M89: 0.095 | N89: 0.1 | O89: 0.105 | P89: 0.11
E90: Base | L90: 0.12 | M90: 0.13 | N90: 0.14 | O90: 0.15 | P90: 0.15
E91: Bull | L91: 0.14 | M91: 0.155 | N91: 0.17 | O91: 0.18 | P91: 0.19
C92: R&D as % of Total Revenue | E92: Bear | L92: 0.075 | M92: 0.075 | N92: 0.075 | O92: 0.072 | P92: 0.07
E93: Base | L93: 0.07 | M93: 0.07 | N93: 0.065 | O93: 0.06 | P93: 0.06
E94: Bull | L94: 0.067 | M94: 0.064 | N94: 0.06 | O94: 0.057 | P94: 0.055
C95: SG&A as % of Total Revenue | E95: Bear | L95: 0.065 | M95: 0.064 | N95: 0.063 | O95: 0.062 | P95: 0.06
E96: Base | L96: 0.06 | M96: 0.058 | N96: 0.055 | O96: 0.053 | P96: 0.05
E97: Bull | L97: 0.056 | M97: 0.053 | N97: 0.05 | O97: 0.047 | P97: 0.045
C98: CapEx as % of Total Revenue | E98: Bear | L98: 0.11 | M98: 0.105 | N98: 0.1 | O98: 0.095 | P98: 0.09
E99: Base | L99: 0.1 | M99: 0.095 | N99: 0.09 | O99: 0.085 | P99: 0.08
E100: Bull | L100: 0.095 | M100: 0.09 | N100: 0.085 | O100: 0.08 | P100: 0.075
A102: Not scenario-tested (common to all cases): receivable / inventory / payable days, other current and non-current asset and liability ratios, deferred revenue, depreciation rate, debt and interest, tax rate, share count, and every valuation input. Varying them would confound operating performance with financing and balance-sheet policy.

Sheet Revenue Build-up
A1: TESLA, INC. | E1: ◄ Cover | G1: REVENUE BUILD-UP
A2: USD millions except per-share and operating data
E3: Unit | G3: FY21A | H3: FY22A | I3: FY23A | J3: FY24A | K3: FY25A | L3: FY26E | M3: FY27E | N3: FY28E | O3: FY29E | P3: FY30E
A4: AUTOMOTIVE
C5: Vehicle Deliveries | E5: units | G5: 936172 | H5: 1313851 | I5: 1808581 | J5: 1789226 | K5: 1636129 | L5: =K5*(1+Assumptions!L7) -> 1734296.7 | M5: =L5*(1+Assumptions!M7) -> 1907726.4 | N5: =M5*(1+Assumptions!N7) -> 2136653.6 | O5: =N5*(1+Assumptions!O7) -> 2350318.9 | P5: =O5*(1+Assumptions!P7) -> 2538344.5
C6: Implied Automotive Revenue per Delivery | E6: $/unit | G6: 48887.384 | H6: 53039.5 | I6: 44581.36 | J6: 41530.248 | K6: 41276.085 | L6: =K6*(1+Assumptions!L10) -> 40037.803 | M6: =L6*(1+Assumptions!M10) -> 39237.047 | N6: =M6*(1+Assumptions!N10) -> 39629.417 | O6: =N6*(1+Assumptions!O10) -> 40025.711 | P6: =O6*(1+Assumptions!P10) -> 40826.225
C7: Automotive Sales & Leasing Revenue | E7: $M | G7: =G5*G6/1000000 -> 45767 | H7: =H5*H6/1000000 -> 69686 | I7: =I5*I6/1000000 -> 80629 | J7: =J5*J6/1000000 -> 74307 | K7: =K5*K6/1000000 -> 67533 | L7: =L5*L6/1000000 -> 69437.431 | M7: =M5*M6/1000000 -> 74853.55 | N7: =N5*N6/1000000 -> 84674.336 | ... P7: =P5*P6/1000000 -> 103631.02
C8: [+] Automotive Regulatory Credits | E8: $M | G8: 1465 | H8: 1776 | I8: 1790 | J8: 2763 | K8: 1993 | L8: =K8*(1+Assumptions!L12) -> 1395.1 | M8: =L8*(1+Assumptions!M12) -> 1116.08 | N8: =M8*(1+Assumptions!N12) -> 1004.472 | O8: =N8*(1+Assumptions!O12) -> 954.2484 | P8: =O8*(1+Assumptions!P12) -> 906.53598
C9: Total Automotive Revenue | G9: =SUM(G7:G8) -> 47232 | H9: =SUM(H7:H8) -> 71462 | I9: =SUM(I7:I8) -> 82419 | J9: =SUM(J7:J8) -> 77070 | K9: =SUM(K7:K8) -> 69526 | L9: =SUM(L7:L8) -> 70832.531 | M9: =SUM(M7:M8) -> 75969.63 | N9: =SUM(N7:N8) -> 85678.808 | ... P9: =SUM(P7:P8) -> 104537.56
A11: ENERGY GENERATION & STORAGE
C12: Energy Generation & Storage Revenue | E12: $M | G12: 2789 | H12: 3909 | I12: 6035 | J12: 10086 | K12: 12771 | L12: =K12*(1+Assumptions!L17) -> 16602.3 | M12: =L12*(1+Assumptions!M17) -> 20752.875 | N12: =M12*(1+Assumptions!N17) -> 24903.45 | O12: =N12*(1+Assumptions!O17) -> 29386.071 | P12: =O12*(1+Assumptions!P17) -> 33793.982
A14: SERVICES & OTHER
C15: Services & Other Revenue | E15: $M | G15: 3802 | H15: 6091 | I15: 8319 | J15: 10534 | K15: 12530 | L15: =K15*(1+Assumptions!L21) -> 14409.5 | M15: =L15*(1+Assumptions!M21) -> 16426.83 | N15: =M15*(1+Assumptions!N21) -> 18562.318 | O15: =N15*(1+Assumptions!O21) -> 20789.796 | P15: =O15*(1+Assumptions!P21) -> 23076.674
A17: TOTAL REVENUE
C18: TOTAL REVENUE | E18: $M | G18: =G9+G12+G15 -> 53823 | H18: =H9+H12+H15 -> 81462 | I18: =I9+I12+I15 -> 96773 | J18: =J9+J12+J15 -> 97690 | K18: =K9+K12+K15 -> 94827 | L18: =L9+L12+L15 -> 101844.33 | M18: =M9+M12+M15 -> 113149.34 | N18: =N9+N12+N15 -> 129144.58 | ... P18: =P9+P12+P15 -> 161408.21
C19: YoY Growth % | H19: =H18/G18-1 -> 0.51351653 | I19: =I18/H18-1 -> 0.18795267 | J19: =J18/I18-1 -> 0.0094757835 | K19: =K18/J18-1 -> -0.029306992 | L19: =L18/K18-1 -> 0.074001398 | M19: =M18/L18-1 -> 0.11100279 | N19: =N18/M18-1 -> 0.14136398 | O19: =O18/N18-1 -> 0.12434689 | P19: =P18/O18-1 -> 0.11160154
A21: ENERGY OPERATING CROSS-CHECK — STORAGE DEPLOYMENTS (CONTEXT, NOT A FORECAST DRIVER)
C22: Energy Storage Deployed | E22: GWh | G22: 3.99 | H22: 6.5 | I22: 14.7 | J22: 31.4 | K22: 46.7
C23: Implied Energy Revenue per GWh Deployed | E23: $M/GWh | G23: =G12/G22 -> 698.99749 | H23: =H12/H22 -> 601.38462 | I23: =I12/I22 -> 410.54422 | J23: =J12/J22 -> 321.21019 | K23: =K12/K22 -> 273.46895
C24: Implied Deployments at Forecast Revenue — $/GWh held flat | E24: GWh | L24: =L12/$K$23 -> 60.71 | M24: =M12/$K$23 -> 75.8875 | N24: =N12/$K$23 -> 91.065 | O24: =O12/$K$23 -> 107.4567 | P24: =P12/$K$23 -> 123.5752
C25: Implied Deployments at Forecast Revenue — $/GWh falling 10% p.a. | E25: GWh | L25: =L12/($K$23*0.9^1) -> 67.455556 | M25: =M12/($K$23*0.9^2) -> 93.688272 | N25: =N12/($K$23*0.9^3) -> 124.9177 | O25: =O12/($K$23*0.9^4) -> 163.78098 | P25: =P12/($K$23*0.9^5) -> 209.27569
A26: Deployments are Tesla's disclosed annual energy-storage figures (FY2021A–FY2025A). Revenue per GWh is a blended segment metric — the Energy segment also contains solar — and it has fallen every year, so it is used here as a plausibility cross-check on the revenue forecast, not as a forecast driver. Rows 24–25 show the deployment volumes the Base Case revenue implies under two $/GWh paths; both are a multiple of FY2025A, which is the growth the Energy assumption embeds. Tesla does not disclose a stable storage-only price or mix, so no revenue-per-GWh forecast is built. Sources: see Sources & Notes.

Sheet Cost Build-up
A1: TESLA, INC. | E1: ◄ Cover | G1: COST BUILD-UP
A2: USD millions except per-share and operating data
E3: Unit | G3: FY21A | H3: FY22A | I3: FY23A | J3: FY24A | K3: FY25A | L3: FY26E | M3: FY27E | N3: FY28E | O3: FY29E | P3: FY30E
A4: AUTOMOTIVE
C5: Automotive Revenue | E5: $M | G5: ='Revenue Build-up'!G9 -> 47232 | H5: ='Revenue Build-up'!H9 -> 71462 | I5: ='Revenue Build-up'!I9 -> 82419 | J5: ='Revenue Build-up'!J9 -> 77070 | K5: ='Revenue Build-up'!K9 -> 69526 | L5: ='Revenue Build-up'!L9 -> 70832.531 | M5: ='Revenue Build-up'!M9 -> 75969.63 | N5: ='Revenue Build-up'!N9 -> 85678.808 | ... P5: ='Revenue Build-up'!P9 -> 104537.56
C6: Automotive Gross Margin % | G6: =1-G7/G5 -> 0.29300051 | H6: =1-H7/H5 -> 0.2848227 | I6: =1-I7/I5 -> 0.19449399 | J6: =1-J7/J5 -> 0.18420916 | K6: =1-K7/K5 -> 0.1777896 | L6: =Assumptions!L14 -> 0.19 | M6: =Assumptions!M14 -> 0.2 | N6: =Assumptions!N14 -> 0.21 | O6: =Assumptions!O14 -> 0.22 | P6: =Assumptions!P14 -> 0.23
C7: Automotive Cost of Revenue | E7: $M | G7: 33393 | H7: 51108 | I7: 66389 | J7: 62873 | K7: 57165 | L7: =L5*(1-L6) -> 57374.35 | M7: =M5*(1-M6) -> 60775.704 | N7: =N5*(1-N6) -> 67686.258 | O7: =O5*(1-O6) -> 74121.4 | P7: =P5*(1-P6) -> 80493.92
A9: ENERGY GENERATION & STORAGE
C10: Energy Revenue | E10: $M | G10: ='Revenue Build-up'!G12 -> 2789 | H10: ='Revenue Build-up'!H12 -> 3909 | I10: ='Revenue Build-up'!I12 -> 6035 | J10: ='Revenue Build-up'!J12 -> 10086 | K10: ='Revenue Build-up'!K12 -> 12771 | L10: ='Revenue Build-up'!L12 -> 16602.3 | M10: ='Revenue Build-up'!M12 -> 20752.875 | N10: ='Revenue Build-up'!N12 -> 24903.45 | ... P10: ='Revenue Build-up'!P12 -> 33793.982
C11: Energy Gross Margin % | G11: =1-G12/G10 -> -0.046253137 | H11: =1-H12/H10 -> 0.073676132 | I11: =1-I12/I10 -> 0.18906379 | J11: =1-J12/J10 -> 0.26174896 | K11: =1-K12/K10 -> 0.29770574 | L11: =Assumptions!L18 -> 0.3 | M11: =Assumptions!M18 -> 0.31 | N11: =Assumptions!N18 -> 0.32 | O11: =Assumptions!O18 -> 0.32 | P11: =Assumptions!P18 -> 0.32
C12: Energy Cost of Revenue | E12: $M | G12: 2918 | H12: 3621 | I12: 4894 | J12: 7446 | K12: 8969 | L12: =L10*(1-L11) -> 11621.61 | M12: =M10*(1-M11) -> 14319.484 | N12: =N10*(1-N11) -> 16934.346 | O12: =O10*(1-O11) -> 19982.528 | P12: =P10*(1-P11) -> 22979.908
A14: SERVICES & OTHER
C15: Services & Other Revenue | E15: $M | G15: ='Revenue Build-up'!G15 -> 3802 | H15: ='Revenue Build-up'!H15 -> 6091 | I15: ='Revenue Build-up'!I15 -> 8319 | J15: ='Revenue Build-up'!J15 -> 10534 | K15: ='Revenue Build-up'!K15 -> 12530 | L15: ='Revenue Build-up'!L15 -> 14409.5 | M15: ='Revenue Build-up'!M15 -> 16426.83 | N15: ='Revenue Build-up'!N15 -> 18562.318 | ... P15: ='Revenue Build-up'!P15 -> 23076.674
C16: Services Gross Margin % | G16: =1-G17/G15 -> -0.027354024 | H16: =1-H17/H15 -> 0.034641274 | I16: =1-I17/I15 -> 0.058781103 | J16: =1-J17/J15 -> 0.058192519 | K16: =1-K17/K15 -> 0.074301676 | L16: =Assumptions!L22 -> 0.12 | M16: =Assumptions!M22 -> 0.13 | N16: =Assumptions!N22 -> 0.14 | O16: =Assumptions!O22 -> 0.15 | P16: =Assumptions!P22 -> 0.15
C17: Services Cost of Revenue | E17: $M | G17: 3906 | H17: 5880 | I17: 7830 | J17: 9921 | K17: 11599 | L17: =L15*(1-L16) -> 12680.36 | M17: =M15*(1-M16) -> 14291.342 | N17: =N15*(1-N16) -> 15963.593 | O17: =O15*(1-O16) -> 17671.327 | P17: =P15*(1-P16) -> 19615.173
A19: TOTAL COST OF REVENUE
C20: TOTAL COST OF REVENUE | E20: $M | G20: =G7+G12+G17 -> 40217 | H20: =H7+H12+H17 -> 60609 | I20: =I7+I12+I17 -> 79113 | J20: =J7+J12+J17 -> 80240 | K20: =K7+K12+K17 -> 77733 | L20: =L7+L12+L17 -> 81676.32 | M20: =M7+M12+M17 -> 89386.53 | N20: =N7+N12+N17 -> 100584.2 | ... P20: =P7+P12+P17 -> 123089
A22: OPERATING EXPENSES
C23: R&D as % of Total Revenue | G23: =Assumptions!G25 -> 0.04817643 | H23: =Assumptions!H25 -> 0.037747661 | I23: =Assumptions!I25 -> 0.041013506 | J23: =Assumptions!J25 -> 0.046473539 | K23: =Assumptions!K25 -> 0.067607327 | L23: =Assumptions!L25 -> 0.07 | M23: =Assumptions!M25 -> 0.07 | N23: =Assumptions!N25 -> 0.065 | ... P23: =Assumptions!P25 -> 0.06
C24: Research & Development | E24: $M | G24: 2593 | H24: 3075 | I24: 3969 | J24: 4540 | K24: 6411 | L24: ='Revenue Build-up'!L18*L23 -> 7129.1031 | M24: ='Revenue Build-up'!M18*M23 -> 7920.4535 | N24: ='Revenue Build-up'!N18*N23 -> 8394.3974 | O24: ='Revenue Build-up'!O18*O23 -> 8712.1982 | P24: ='Revenue Build-up'!P18*P23 -> 9684.4929
C25: SG&A as % of Total Revenue | G25: =Assumptions!G26 -> 0.08392323 | H25: =Assumptions!H26 -> 0.048439763 | I25: =Assumptions!I26 -> 0.049600612 | J25: =Assumptions!J26 -> 0.052717781 | K25: =Assumptions!K26 -> 0.061522562 | L25: =Assumptions!L26 -> 0.06 | M25: =Assumptions!M26 -> 0.058 | N25: =Assumptions!N26 -> 0.055 | ... P25: =Assumptions!P26 -> 0.05
C26: Selling, General & Administrative | E26: $M | G26: 4517 | H26: 3946 | I26: 4800 | J26: 5150 | K26: 5834 | L26: ='Revenue Build-up'!L18*L25 -> 6110.6598 | M26: ='Revenue Build-up'!M18*M25 -> 6562.6614 | N26: ='Revenue Build-up'!N18*N25 -> 7102.9517 | O26: ='Revenue Build-up'!O18*O25 -> 7695.775 | P26: ='Revenue Build-up'!P18*P25 -> 8070.4107
C27: Restructuring & Other | E27: $M | G27: -27 | H27: 176 | I27: 0 | J27: 684 | K27: 494 | L27: 0 | M27: 0 | N27: 0 | O27: 0 | P27: 0
C29: Total Operating Expenses | E29: $M | G29: =SUM(G24,G26,G27) -> 7083 | H29: =SUM(H24,H26,H27) -> 7197 | I29: =SUM(I24,I26,I27) -> 8769 | J29: =SUM(J24,J26,J27) -> 10374 | K29: =SUM(K24,K26,K27) -> 12739 | L29: =SUM(L24,L26,L27) -> 13239.763 | M29: =SUM(M24,M26,M27) -> 14483.115 | N29: =SUM(N24,N26,N27) -> 15497.349 | ... P29: =SUM(P24,P26,P27) -> 17754.904

Sheet IS
A1: TESLA, INC. | E1: ◄ Cover | G1: INCOME STATEMENT
A2: USD millions except per-share and operating data
E3: Unit | G3: FY21A | H3: FY22A | I3: FY23A | J3: FY24A | K3: FY25A | L3: FY26E | M3: FY27E | N3: FY28E | O3: FY29E | P3: FY30E
A4: REVENUE
C5: Automotive Revenue | E5: $M | G5: ='Revenue Build-up'!G9 -> 47232 | H5: ='Revenue Build-up'!H9 -> 71462 | I5: ='Revenue Build-up'!I9 -> 82419 | J5: ='Revenue Build-up'!J9 -> 77070 | K5: ='Revenue Build-up'!K9 -> 69526 | L5: ='Revenue Build-up'!L9 -> 70832.531 | M5: ='Revenue Build-up'!M9 -> 75969.63 | N5: ='Revenue Build-up'!N9 -> 85678.808 | ... P5: ='Revenue Build-up'!P9 -> 104537.56
C6: Energy Generation & Storage Revenue | E6: $M | G6: ='Revenue Build-up'!G12 -> 2789 | H6: ='Revenue Build-up'!H12 -> 3909 | I6: ='Revenue Build-up'!I12 -> 6035 | J6: ='Revenue Build-up'!J12 -> 10086 | K6: ='Revenue Build-up'!K12 -> 12771 | L6: ='Revenue Build-up'!L12 -> 16602.3 | M6: ='Revenue Build-up'!M12 -> 20752.875 | N6: ='Revenue Build-up'!N12 -> 24903.45 | ... P6: ='Revenue Build-up'!P12 -> 33793.982
C7: Services & Other Revenue | E7: $M | G7: ='Revenue Build-up'!G15 -> 3802 | H7: ='Revenue Build-up'!H15 -> 6091 | I7: ='Revenue Build-up'!I15 -> 8319 | J7: ='Revenue Build-up'!J15 -> 10534 | K7: ='Revenue Build-up'!K15 -> 12530 | L7: ='Revenue Build-up'!L15 -> 14409.5 | M7: ='Revenue Build-up'!M15 -> 16426.83 | N7: ='Revenue Build-up'!N15 -> 18562.318 | ... P7: ='Revenue Build-up'!P15 -> 23076.674
C8: TOTAL REVENUE | E8: $M | G8: =SUM(G5:G7) -> 53823 | H8: =SUM(H5:H7) -> 81462 | I8: =SUM(I5:I7) -> 96773 | J8: =SUM(J5:J7) -> 97690 | K8: =SUM(K5:K7) -> 94827 | L8: =SUM(L5:L7) -> 101844.33 | M8: =SUM(M5:M7) -> 113149.34 | N8: =SUM(N5:N7) -> 129144.58 | ... P8: =SUM(P5:P7) -> 161408.21
A10: COST OF REVENUE
C11: Automotive Cost of Revenue | E11: $M | G11: ='Cost Build-up'!G7 -> 33393 | H11: ='Cost Build-up'!H7 -> 51108 | I11: ='Cost Build-up'!I7 -> 66389 | J11: ='Cost Build-up'!J7 -> 62873 | K11: ='Cost Build-up'!K7 -> 57165 | L11: ='Cost Build-up'!L7 -> 57374.35 | M11: ='Cost Build-up'!M7 -> 60775.704 | N11: ='Cost Build-up'!N7 -> 67686.258 | ... P11: ='Cost Build-up'!P7 -> 80493.92
C12: Energy Cost of Revenue | E12: $M | G12: ='Cost Build-up'!G12 -> 2918 | H12: ='Cost Build-up'!H12 -> 3621 | I12: ='Cost Build-up'!I12 -> 4894 | J12: ='Cost Build-up'!J12 -> 7446 | K12: ='Cost Build-up'!K12 -> 8969 | L12: ='Cost Build-up'!L12 -> 11621.61 | M12: ='Cost Build-up'!M12 -> 14319.484 | N12: ='Cost Build-up'!N12 -> 16934.346 | ... P12: ='Cost Build-up'!P12 -> 22979.908
C13: Services Cost of Revenue | E13: $M | G13: ='Cost Build-up'!G17 -> 3906 | H13: ='Cost Build-up'!H17 -> 5880 | I13: ='Cost Build-up'!I17 -> 7830 | J13: ='Cost Build-up'!J17 -> 9921 | K13: ='Cost Build-up'!K17 -> 11599 | L13: ='Cost Build-up'!L17 -> 12680.36 | M13: ='Cost Build-up'!M17 -> 14291.342 | N13: ='Cost Build-up'!N17 -> 15963.593 | ... P13: ='Cost Build-up'!P17 -> 19615.173
C14: Total Cost of Revenue | E14: $M | G14: =SUM(G11:G13) -> 40217 | H14: =SUM(H11:H13) -> 60609 | I14: =SUM(I11:I13) -> 79113 | J14: =SUM(J11:J13) -> 80240 | K14: =SUM(K11:K13) -> 77733 | L14: =SUM(L11:L13) -> 81676.32 | M14: =SUM(M11:M13) -> 89386.53 | N14: =SUM(N11:N13) -> 100584.2 | ... P14: =SUM(P11:P13) -> 123089
C16: GROSS PROFIT | E16: $M | G16: =G8-G14 -> 13606 | H16: =H8-H14 -> 20853 | I16: =I8-I14 -> 17660 | J16: =J8-J14 -> 17450 | K16: =K8-K14 -> 17094 | L16: =L8-L14 -> 20168.011 | M16: =M8-M14 -> 23762.805 | N16: =N8-N14 -> 28560.378 | ... P16: =P8-P14 -> 38319.214
C17: Gross Margin % | G17: =G16/G8 -> 0.25279156 | H17: =H16/H8 -> 0.25598439 | I17: =I16/I8 -> 0.18248892 | J17: =J16/J8 -> 0.17862627 | K17: =K16/K8 -> 0.18026511 | L17: =L16/L8 -> 0.19802782 | M17: =M16/M8 -> 0.21001277 | N17: =N16/N8 -> 0.22115043 | ... P17: =P16/P8 -> 0.2374056
A19: OPERATING EXPENSES
C20: Research & Development | E20: $M | G20: ='Cost Build-up'!G24 -> 2593 | H20: ='Cost Build-up'!H24 -> 3075 | I20: ='Cost Build-up'!I24 -> 3969 | J20: ='Cost Build-up'!J24 -> 4540 | K20: ='Cost Build-up'!K24 -> 6411 | L20: ='Cost Build-up'!L24 -> 7129.1031 | M20: ='Cost Build-up'!M24 -> 7920.4535 | N20: ='Cost Build-up'!N24 -> 8394.3974 | ... P20: ='Cost Build-up'!P24 -> 9684.4929
C21: Selling, General & Administrative | E21: $M | G21: ='Cost Build-up'!G26 -> 4517 | H21: ='Cost Build-up'!H26 -> 3946 | I21: ='Cost Build-up'!I26 -> 4800 | J21: ='Cost Build-up'!J26 -> 5150 | K21: ='Cost Build-up'!K26 -> 5834 | L21: ='Cost Build-up'!L26 -> 6110.6598 | M21: ='Cost Build-up'!M26 -> 6562.6614 | N21: ='Cost Build-up'!N26 -> 7102.9517 | ... P21: ='Cost Build-up'!P26 -> 8070.4107
C22: Restructuring & Other | E22: $M | G22: ='Cost Build-up'!G27 -> -27 | H22: ='Cost Build-up'!H27 -> 176 | I22: ='Cost Build-up'!I27 -> 0 | J22: ='Cost Build-up'!J27 -> 684 | K22: ='Cost Build-up'!K27 -> 494 | L22: ='Cost Build-up'!L27 -> 0 | M22: ='Cost Build-up'!M27 -> 0 | N22: ='Cost Build-up'!N27 -> 0 | ... P22: ='Cost Build-up'!P27 -> 0
C23: Total Operating Expenses | E23: $M | G23: =SUM(G20:G22) -> 7083 | H23: =SUM(H20:H22) -> 7197 | I23: =SUM(I20:I22) -> 8769 | J23: =SUM(J20:J22) -> 10374 | K23: =SUM(K20:K22) -> 12739 | L23: =SUM(L20:L22) -> 13239.763 | M23: =SUM(M20:M22) -> 14483.115 | N23: =SUM(N20:N22) -> 15497.349 | ... P23: =SUM(P20:P22) -> 17754.904
C25: EBIT (Operating Income) | E25: $M | G25: =G16-G23 -> 6523 | H25: =H16-H23 -> 13656 | I25: =I16-I23 -> 8891 | J25: =J16-J23 -> 7076 | K25: =K16-K23 -> 4355 | L25: =L16-L23 -> 6928.2478 | M25: =M16-M23 -> 9279.6903 | N25: =N16-N23 -> 13063.029 | ... P25: =P16-P23 -> 20564.31
C26: EBIT Margin % | G26: =G25/G8 -> 0.12119354 | H26: =H25/H8 -> 0.16763644 | I26: =I25/I8 -> 0.0918748 | J26: =J25/J8 -> 0.072433207 | K26: =K25/K8 -> 0.045925738 | L26: =L25/L8 -> 0.06802782 | M26: =M25/M8 -> 0.082012769 | N26: =N25/N8 -> 0.10115043 | ... P26: =P25/P8 -> 0.1274056
C28: [+] Depreciation & Amortization | E28: $M | G28: ='Asset Schedule'!G7 -> 2911 | H28: ='Asset Schedule'!H7 -> 3747 | I28: ='Asset Schedule'!I7 -> 4667 | J28: ='Asset Schedule'!J7 -> 5368 | K28: ='Asset Schedule'!K7 -> 6148 | L28: ='Asset Schedule'!L7 -> 6706.095 | M28: ='Asset Schedule'!M7 -> 7059.4141 | N28: ='Asset Schedule'!N7 -> 7410.7222 | ... P28: ='Asset Schedule'!P7 -> 8484.3257
C29: EBITDA | E29: $M | G29: =G25+G28 -> 9434 | H29: =H25+H28 -> 17403 | I29: =I25+I28 -> 13558 | J29: =J25+J28 -> 12444 | K29: =K25+K28 -> 10503 | L29: =L25+L28 -> 13634.343 | M29: =M25+M28 -> 16339.104 | N29: =N25+N28 -> 20473.751 | ... P29: =P25+P28 -> 29048.636
C30: EBITDA Margin % | G30: =G29/G8 -> 0.17527823 | H30: =H29/H8 -> 0.21363335 | I30: =I29/I8 -> 0.14010106 | J30: =J29/J8 -> 0.12738254 | K30: =K29/K8 -> 0.11075959 | L30: =L29/L8 -> 0.13387434 | M30: =M29/M8 -> 0.14440301 | N30: =N29/N8 -> 0.15853357 | ... P30: =P29/P8 -> 0.17997
A32: NON-OPERATING ITEMS
C33: [+] Interest Income | E33: $M | G33: ='Loans & Other Income'!G16 -> 56 | H33: ='Loans & Other Income'!H16 -> 297 | I33: ='Loans & Other Income'!I16 -> 1066 | J33: ='Loans & Other Income'!J16 -> 1569 | K33: ='Loans & Other Income'!K16 -> 1680 | L33: ='Loans & Other Income'!L16 -> 743.085 | M33: ='Loans & Other Income'!M16 -> 883.82997 | N33: ='Loans & Other Income'!N16 -> 1064.9972 | ... P33: ='Loans & Other Income'!P16 -> 1435.2462
C34: [-] Interest Expense | E34: $M | G34: ='Loans & Other Income'!G11 -> 371 | H34: ='Loans & Other Income'!H11 -> 191 | I34: ='Loans & Other Income'!I11 -> 156 | J34: ='Loans & Other Income'!J11 -> 350 | K34: ='Loans & Other Income'!K11 -> 338 | L34: ='Loans & Other Income'!L11 -> 418.8 | M34: ='Loans & Other Income'!M11 -> 418.8 | N34: ='Loans & Other Income'!N11 -> 418.8 | ... P34: ='Loans & Other Income'!P11 -> 418.8
C35: [+/-] Other Income (Expense), net | E35: $M | G35: 135 | H35: -43 | I35: 172 | J35: 695 | K35: -419 | L35: 0 | M35: 0 | N35: 0 | O35: 0 | P35: 0
C37: PBT (Income Before Taxes) | E37: $M | G37: =G25+G33-G34+G35 -> 6343 | H37: =H25+H33-H34+H35 -> 13719 | I37: =I25+I33-I34+I35 -> 9973 | J37: =J25+J33-J34+J35 -> 8990 | K37: =K25+K33-K34+K35 -> 5278 | L37: =L25+L33-L34+L35 -> 7252.5328 | M37: =M25+M33-M34+M35 -> 9744.7203 | N37: =N25+N33-N34+N35 -> 13709.226 | ... P37: =P25+P33-P34+P35 -> 21580.756
C38: PBT Margin % | G38: =G37/G8 -> 0.11784925 | H38: =H37/H8 -> 0.16840981 | I38: =I37/I8 -> 0.1030556 | J38: =J37/J8 -> 0.092025796 | K38: =K37/K8 -> 0.055659253 | L38: =L37/L8 -> 0.071211945 | M38: =M37/M8 -> 0.086122647 | N38: =N37/N8 -> 0.1061541 | ... P38: =P37/P8 -> 0.13370296
C40: [-] Income Tax Expense | E40: $M | G40: ='Tax Schedule'!G6 -> 699 | H40: ='Tax Schedule'!H6 -> 1132 | I40: ='Tax Schedule'!I6 -> -5001 | J40: ='Tax Schedule'!J6 -> 1837 | K40: ='Tax Schedule'!K6 -> 1423 | L40: ='Tax Schedule'!L6 -> 1740.6079 | M40: ='Tax Schedule'!M6 -> 2338.7329 | N40: ='Tax Schedule'!N6 -> 3290.2143 | ... P40: ='Tax Schedule'!P6 -> 5179.3815
C41: Effective Tax Rate % | G41: =G40/G37 -> 0.11020022 | H41: =H40/H37 -> 0.082513303 | I41: =I40/I37 -> -0.50145393 | J41: =J40/J37 -> 0.20433815 | K41: =K40/K37 -> 0.2696097 | L41: =L40/L37 -> 0.24 | M41: =M40/M37 -> 0.24 | N41: =N40/N37 -> 0.24 | ... P41: =P40/P37 -> 0.24
C43: NET INCOME | E43: $M | G43: =G37-G40 -> 5644 | H43: =H37-H40 -> 12587 | I43: =I37-I40 -> 14974 | J43: =J37-J40 -> 7153 | K43: =K37-K40 -> 3855 | L43: =L37-L40 -> 5511.925 | M43: =M37-M40 -> 7405.9874 | N43: =N37-N40 -> 10419.012 | ... P43: =P37-P40 -> 16401.375
C44: Net Margin % | G44: =G43/G8 -> 0.10486223 | H44: =H43/H8 -> 0.15451376 | I44: =I43/I8 -> 0.15473324 | J44: =J43/J8 -> 0.073221415 | K44: =K43/K8 -> 0.040652979 | L44: =L43/L8 -> 0.054121078 | M44: =M43/M8 -> 0.065453212 | N44: =N43/N8 -> 0.080677116 | ... P44: =P43/P8 -> 0.10161425
C45: [-] Net Income Attributable to Noncontrolling Interests | G45: 125 | H45: 31 | I45: -23 | J45: 62 | K45: 61 | L45: 0 | M45: 0 | N45: 0 | O45: 0 | P45: 0
C46: NET INCOME ATTRIBUTABLE TO COMMON STOCKHOLDERS | G46: =G43-G45 -> 5519 | H46: =H43-H45 -> 12556 | I46: =I43-I45 -> 14997 | J46: =J43-J45 -> 7091 | K46: =K43-K45 -> 3794 | L46: =L43-L45 -> 5511.925 | M46: =M43-M45 -> 7405.9874 | N46: =N43-N45 -> 10419.012 | ... P46: =P43-P45 -> 16401.375
C47: Diluted Weighted-Average Shares Outstanding | E47: millions | G47: ='Equity Schedule'!G12 -> 3386 | H47: ='Equity Schedule'!H12 -> 3475 | I47: ='Equity Schedule'!I12 -> 3485 | J47: ='Equity Schedule'!J12 -> 3498 | K47: ='Equity Schedule'!K12 -> 3528 | L47: ='Equity Schedule'!L12 -> 3950 | M47: ='Equity Schedule'!M12 -> 3950 | N47: ='Equity Schedule'!N12 -> 3950 | ... P47: ='Equity Schedule'!P12 -> 3950
C48: Diluted EPS | E48: $/share | G48: =G46/G47 -> 1.6299468 | H48: =H46/H47 -> 3.6132374 | I48: =I46/I47 -> 4.3032999 | J48: =J46/J47 -> 2.0271584 | K48: =K46/K47 -> 1.0753968 | L48: =L46/L47 -> 1.395424 | M48: =M46/M47 -> 1.8749335 | N48: =N46/N47 -> 2.6377246 | ... P48: =P46/P47 -> 4.1522468

Sheet BS
A1: TESLA, INC. | E1: ◄ Cover | G1: BALANCE SHEET
A2: USD millions except per-share and operating data
E3: Unit | G3: FY21A | H3: FY22A | I3: FY23A | J3: FY24A | K3: FY25A | L3: FY26E | M3: FY27E | N3: FY28E | O3: FY29E | P3: FY30E
A4: ASSETS
C5: Cash and Cash Equivalents | E5: $M | G5: 17576 | H5: 16253 | I5: 16398 | J5: 16139 | K5: 16513 | L5: =Cashflow!L32 -> 19640.666 | M5: =Cashflow!M32 -> 23666.605 | N5: =Cashflow!N32 -> 28247.664 | O5: =Cashflow!O32 -> 35881.154 | P5: =Cashflow!P32 -> 45753.868
C6: [+] Accounts Receivable | E6: $M | G6: 1913 | H6: 2952 | I6: 3508 | J6: 4418 | K6: 4576 | L6: =IS!L8/365*Assumptions!L29 -> 5022.4601 | M6: =IS!M8/365*Assumptions!M29 -> 5579.9672 | N6: =IS!N8/365*Assumptions!N29 -> 6014.9528 | O6: =IS!O8/365*Assumptions!O29 -> 6762.8936 | P6: =IS!P8/365*Assumptions!P29 -> 7517.6429
C7: [+] Inventory | E7: $M | G7: 5757 | H7: 12839 | I7: 13626 | J7: 12017 | K7: 12392 | L7: =IS!L14/365*Assumptions!L30 -> 12307.391 | M7: =IS!M14/365*Assumptions!M30 -> 12979.414 | N7: =IS!N14/365*Assumptions!N30 -> 13778.657 | O7: =IS!O14/365*Assumptions!O30 -> 14699.212 | P7: =IS!P14/365*Assumptions!P30 -> 16187.047
C8: Short-Term Investments & Other Current Assets | E8: $M | G8: 1854 | H8: 8873 | I8: 16084 | J8: 25786 | K8: 35161 | L8: ='Revenue Build-up'!L18*Assumptions!L32 -> 38700.846 | M8: ='Revenue Build-up'!M18*Assumptions!M32 -> 44128.241 | N8: ='Revenue Build-up'!N18*Assumptions!N32 -> 51657.83 | O8: ='Revenue Build-up'!O18*Assumptions!O32 -> 59533.354 | P8: ='Revenue Build-up'!P18*Assumptions!P32 -> 67791.45
C9: Total Current Assets | E9: $M | G9: =SUM(G5:G8) -> 27100 | H9: =SUM(H5:H8) -> 40917 | I9: =SUM(I5:I8) -> 49616 | J9: =SUM(J5:J8) -> 58360 | K9: =SUM(K5:K8) -> 68642 | L9: =SUM(L5:L8) -> 75671.362 | M9: =SUM(M5:M8) -> 86354.227 | N9: =SUM(N5:N8) -> 99699.105 | ... P9: =SUM(P5:P8) -> 137250.01
C11: Net PP&E | E11: $M | G11: ='Asset Schedule'!G9 -> 18884 | H11: ='Asset Schedule'!H9 -> 23548 | I11: ='Asset Schedule'!I9 -> 29725 | J11: ='Asset Schedule'!J9 -> 35836 | K11: ='Asset Schedule'!K9 -> 40643 | L11: ='Asset Schedule'!L9 -> 44121.338 | M11: ='Asset Schedule'!M9 -> 47811.111 | N11: ='Asset Schedule'!N9 -> 52023.4 | ... P11: ='Asset Schedule'!P9 -> 60990.503
C12: [+] Operating Lease ROU Assets | E12: $M | G12: 2016 | H12: 2563 | I12: 4180 | J12: 5160 | K12: 6027 | L12: ='Revenue Build-up'!L18*Assumptions!L35 -> 6110.6598 | M12: ='Revenue Build-up'!M18*Assumptions!M35 -> 6788.9601 | N12: ='Revenue Build-up'!N18*Assumptions!N35 -> 7748.6746 | O12: ='Revenue Build-up'!O18*Assumptions!O35 -> 8712.1982 | P12: ='Revenue Build-up'!P18*Assumptions!P35 -> 9684.4929
C13: [+] Other Non-Current Assets | E13: $M | G13: 14131 | H13: 15310 | I13: 23097 | J13: 22714 | K13: 22494 | L13: ='Revenue Build-up'!L18*Assumptions!L37 -> 22405.753 | M13: ='Revenue Build-up'!M18*Assumptions!M37 -> 23761.36 | N13: ='Revenue Build-up'!N18*Assumptions!N37 -> 25828.915 | O13: ='Revenue Build-up'!O18*Assumptions!O37 -> 29040.661 | P13: ='Revenue Build-up'!P18*Assumptions!P37 -> 30667.561
C14: TOTAL ASSETS | E14: $M | G14: =G9+SUM(G11:G13) -> 62131 | H14: =H9+SUM(H11:H13) -> 82338 | I14: =I9+SUM(I11:I13) -> 106618 | J14: =J9+SUM(J11:J13) -> 122070 | K14: =K9+SUM(K11:K13) -> 137806 | L14: =L9+SUM(L11:L13) -> 148309.11 | M14: =M9+SUM(M11:M13) -> 164715.66 | N14: =N9+SUM(N11:N13) -> 185300.09 | ... P14: =P9+SUM(P11:P13) -> 238592.56
A16: LIABILITIES
C17: Accounts Payable | E17: $M | G17: 10025 | H17: 15255 | I17: 14431 | J17: 12474 | K17: 13371 | L17: =IS!L14/365*Assumptions!L31 -> 13873.786 | M17: =IS!M14/365*Assumptions!M31 -> 15183.465 | N17: =IS!N14/365*Assumptions!N31 -> 16534.389 | O17: =IS!O14/365*Assumptions!O31 -> 18374.014 | P17: =IS!P14/365*Assumptions!P31 -> 20233.808
C18: [+] Accrued Liabilities & Other | E18: $M | G18: 6644 | H18: 8205 | I18: 9080 | J18: 10723 | K18: 13279 | L18: ='Revenue Build-up'!L18*Assumptions!L33 -> 13239.763 | M18: ='Revenue Build-up'!M18*Assumptions!M33 -> 14709.414 | N18: ='Revenue Build-up'!N18*Assumptions!N33 -> 16143.072 | O18: ='Revenue Build-up'!O18*Assumptions!O33 -> 18150.413 | P18: ='Revenue Build-up'!P18*Assumptions!P33 -> 19368.986
C19: [+] Deferred Revenue (Current) | E19: $M | G19: 1447 | H19: 1747 | I19: 2864 | J19: 3168 | K19: 3424 | L19: ='Revenue Build-up'!L18*Assumptions!L34 -> 3564.5516 | M19: ='Revenue Build-up'!M18*Assumptions!M34 -> 3960.2267 | N19: ='Revenue Build-up'!N18*Assumptions!N34 -> 4520.0602 | O19: ='Revenue Build-up'!O18*Assumptions!O34 -> 5082.1156 | P19: ='Revenue Build-up'!P18*Assumptions!P34 -> 5649.2875
C20: [+] Current Portion of Debt | E20: $M | G20: 1589 | H20: 1502 | I20: 2373 | J20: 2456 | K20: 1640 | L20: =K20 -> 1640 | M20: =L20 -> 1640 | N20: =M20 -> 1640 | O20: =N20 -> 1640 | P20: =O20 -> 1640
C21: Total Current Liabilities | E21: $M | G21: =SUM(G17:G20) -> 19705 | H21: =SUM(H17:H20) -> 26709 | I21: =SUM(I17:I20) -> 28748 | J21: =SUM(J17:J20) -> 28821 | K21: =SUM(K17:K20) -> 31714 | L21: =SUM(L17:L20) -> 32318.1 | M21: =SUM(M17:M20) -> 35493.106 | N21: =SUM(N17:N20) -> 38837.521 | ... P21: =SUM(P17:P20) -> 46892.082
C23: Long-Term Debt | E23: $M | G23: 5245 | H23: 1597 | I23: 2857 | J23: 5757 | K23: 6736 | L23: ='Loans & Other Income'!L8-L20 -> 6736 | M23: ='Loans & Other Income'!M8-M20 -> 6736 | N23: ='Loans & Other Income'!N8-N20 -> 6736 | O23: ='Loans & Other Income'!O8-O20 -> 6736 | P23: ='Loans & Other Income'!P8-P20 -> 6736
C24: [+] Deferred Revenue (Non-Current) | E24: $M | G24: 2052 | H24: 2804 | I24: 3251 | J24: 3317 | K24: 3631 | L24: ='Revenue Build-up'!L18*Assumptions!L36 -> 3564.5516 | M24: ='Revenue Build-up'!M18*Assumptions!M36 -> 3960.2267 | N24: ='Revenue Build-up'!N18*Assumptions!N36 -> 4520.0602 | O24: ='Revenue Build-up'!O18*Assumptions!O36 -> 5082.1156 | P24: ='Revenue Build-up'!P18*Assumptions!P36 -> 5649.2875
C25: [+] Other Non-Current Liabilities | E25: $M | G25: 4114 | H25: 5739 | I25: 8395 | J25: 10558 | K25: 12860 | L25: ='Revenue Build-up'!L18*Assumptions!L38 -> 13239.763 | M25: ='Revenue Build-up'!M18*Assumptions!M38 -> 14143.667 | N25: ='Revenue Build-up'!N18*Assumptions!N38 -> 15497.349 | O25: ='Revenue Build-up'!O18*Assumptions!O38 -> 17424.396 | P25: ='Revenue Build-up'!P18*Assumptions!P38 -> 18561.945
C26: TOTAL LIABILITIES | E26: $M | G26: =G21+SUM(G23:G25) -> 31116 | H26: =H21+SUM(H23:H25) -> 36849 | I26: =I21+SUM(I23:I25) -> 43251 | J26: =J21+SUM(J23:J25) -> 48453 | K26: =K21+SUM(K23:K25) -> 54941 | L26: =L21+SUM(L23:L25) -> 55858.415 | M26: =M21+SUM(M23:M25) -> 60332.999 | N26: =N21+SUM(N23:N25) -> 65590.93 | ... P26: =P21+SUM(P23:P25) -> 77839.314
A28: STOCKHOLDERS' EQUITY
C29: Common Stock & Additional Paid-in Capital | E29: $M | G29: 29806 | H29: 32180 | I29: 34895 | J29: 38374 | K29: 42773 | L29: =K29+'Equity Schedule'!L6 -> 46846.773 | M29: =L29+'Equity Schedule'!M6 -> 51372.747 | N29: =M29+'Equity Schedule'!N6 -> 56280.241 | O29: =N29+'Equity Schedule'!O6 -> 61797.966 | P29: =O29+'Equity Schedule'!P6 -> 67447.254
C30: [+] Accumulated Other Comprehensive Income | E30: $M | G30: 54 | H30: -361 | I30: -143 | J30: -670 | K30: 361 | L30: =K30 -> 361 | M30: =L30 -> 361 | N30: =M30 -> 361 | O30: =N30 -> 361 | P30: =O30 -> 361
C31: [+] Retained Earnings | E31: $M | G31: 329 | H31: 12885 | I31: 27882 | J31: 35209 | K31: 39003 | L31: =K31+IS!L43 -> 44514.925 | M31: =L31+IS!M43 -> 51920.912 | N31: =M31+IS!N43 -> 62339.924 | O31: =N31+IS!O43 -> 75815.622 | P31: =O31+IS!P43 -> 92216.997
C32: [+] Noncontrolling Interests | E32: $M | G32: 826 | H32: 785 | I32: 733 | J32: 704 | K32: 728 | L32: =K32 -> 728 | M32: =L32 -> 728 | N32: =M32 -> 728 | O32: =N32 -> 728 | P32: =O32 -> 728
C33: TOTAL EQUITY | E33: $M | G33: =SUM(G29:G32) -> 31015 | H33: =SUM(H29:H32) -> 45489 | I33: =SUM(I29:I32) -> 63367 | J33: =SUM(J29:J32) -> 73617 | K33: =SUM(K29:K32) -> 82865 | L33: =SUM(L29:L32) -> 92450.698 | M33: =SUM(M29:M32) -> 104382.66 | N33: =SUM(N29:N32) -> 119709.16 | ... P33: =SUM(P29:P32) -> 160753.25
C35: TOTAL LIABILITIES & EQUITY | E35: $M | G35: =G26+G33 -> 62131 | H35: =H26+H33 -> 82338 | I35: =I26+I33 -> 106618 | J35: =J26+J33 -> 122070 | K35: =K26+K33 -> 137806 | L35: =L26+L33 -> 148309.11 | M35: =M26+M33 -> 164715.66 | N35: =N26+N33 -> 185300.09 | ... P35: =P26+P33 -> 238592.56
C36: Balance Check (Assets − Liabilities & Equity) | G36: =G14-G35 -> 0 | H36: =H14-H35 -> 0 | I36: =I14-I35 -> 0 | J36: =J14-J35 -> 0 | K36: =K14-K35 -> 0 | L36: =L14-L35 -> 0 | M36: =M14-M35 -> 0 | N36: =N14-N35 -> 0 | ... P36: =P14-P35 -> 0
C37: Balance Check Status | G37: =IF(ABS(G36)<0.5,"PASS","FAIL") -> PASS | H37: =IF(ABS(H36)<0.5,"PASS","FAIL") -> PASS | I37: =IF(ABS(I36)<0.5,"PASS","FAIL") -> PASS | J37: =IF(ABS(J36)<0.5,"PASS","FAIL") -> PASS | K37: =IF(ABS(K36)<0.5,"PASS","FAIL") -> PASS | L37: =IF(ABS(L36)<0.5,"PASS","FAIL") -> PASS | M37: =IF(ABS(M36)<0.5,"PASS","FAIL") -> PASS | N37: =IF(ABS(N36)<0.5,"PASS","FAIL") -> PASS | ... P37: =IF(ABS(P36)<0.5,"PASS","FAIL") -> PASS

Sheet Asset Schedule
A1: TESLA, INC. | E1: ◄ Cover | G1: ASSET SCHEDULE
A2: USD millions except per-share and operating data
E3: Unit | G3: FY21A | H3: FY22A | I3: FY23A | J3: FY24A | K3: FY25A | L3: FY26E | M3: FY27E | N3: FY28E | O3: FY29E | P3: FY30E
A4: PROPERTY, PLANT & EQUIPMENT (NET)
C5: Opening Net PP&E | E5: $M | G5: 12747 | H5: =G9 -> 18884 | I5: =H9 -> 23548 | J5: =I9 -> 29725 | K5: =J9 -> 35836 | L5: =K9 -> 40643 | M5: =L9 -> 44121.338 | N5: =M9 -> 47811.111 | O5: =N9 -> 52023.4 | P5: =O9 -> 56562.171
C6: [+] Capital Expenditure | E6: $M | G6: 6482 | H6: 7158 | I6: 8899 | J6: 11342 | K6: 8527 | L6: ='Revenue Build-up'!L18*Assumptions!L41 -> 10184.433 | M6: ='Revenue Build-up'!M18*Assumptions!M41 -> 10749.187 | N6: ='Revenue Build-up'!N18*Assumptions!N41 -> 11623.012 | O6: ='Revenue Build-up'!O18*Assumptions!O41 -> 12342.281 | P6: ='Revenue Build-up'!P18*Assumptions!P41 -> 12912.657
C7: [-] Depreciation & Amortization | E7: $M | G7: 2911 | H7: 3747 | I7: 4667 | J7: 5368 | K7: 6148 | L7: =L5*Assumptions!L42 -> 6706.095 | M7: =M5*Assumptions!M42 -> 7059.4141 | N7: =N5*Assumptions!N42 -> 7410.7222 | O7: =O5*Assumptions!O42 -> 7803.5101 | P7: =P5*Assumptions!P42 -> 8484.3257
C8: [+/-] Other Adjustments, net (hist. only) | E8: $M | G8: =18884-G5-G6+G7 -> 2566 | H8: =23548-H5-H6+H7 -> 1253 | I8: =29725-I5-I6+I7 -> 1945 | J8: =35836-J5-J6+J7 -> 137 | K8: =40643-K5-K6+K7 -> 2428 | L8: 0 | M8: 0 | N8: 0 | O8: 0 | P8: 0
C9: Closing Net PP&E | E9: $M | G9: =G5+G6-G7+G8 -> 18884 | H9: =H5+H6-H7+H8 -> 23548 | I9: =I5+I6-I7+I8 -> 29725 | J9: =J5+J6-J7+J8 -> 35836 | K9: =K5+K6-K7+K8 -> 40643 | L9: =L5+L6-L7+L8 -> 44121.338 | M9: =M5+M6-M7+M8 -> 47811.111 | N9: =N5+N6-N7+N8 -> 52023.4 | ... P9: =P5+P6-P7+P8 -> 60990.503
C11: Depreciation Rate (% of Opening Net PP&E) | G11: =G7/G5 -> 0.22836746 | H11: =H7/H5 -> 0.19842194 | I11: =I7/I5 -> 0.19819093 | J11: =J7/J5 -> 0.18058873 | K11: =K7/K5 -> 0.17155933 | L11: =L7/L5 -> 0.165 | M11: =M7/M5 -> 0.16 | N11: =N7/N5 -> 0.155 | ... P11: =P7/P5 -> 0.15

Sheet Loans & Other Income
A1: TESLA, INC. | E1: ◄ Cover | G1: LOANS & OTHER INCOME
A2: USD millions except per-share and operating data
E3: Unit | G3: FY21A | H3: FY22A | I3: FY23A | J3: FY24A | K3: FY25A | L3: FY26E | M3: FY27E | N3: FY28E | O3: FY29E | P3: FY30E
A4: DEBT SCHEDULE
C5: Opening Total Debt (Current + Long-Term) | E5: $M | G5: 11688 | H5: =G8 -> 6834 | I5: =H8 -> 3099 | J5: =I8 -> 5230 | K5: =J8 -> 8213 | L5: =K8 -> 8376 | M5: =L8 -> 8376 | N5: =M8 -> 8376 | O5: =N8 -> 8376 | P5: =O8 -> 8376
C6: [+/-] Net Borrowings / (Repayments) | E6: $M | G6: -5284 | H6: -3364 | I6: 2580 | J6: 3244 | K6: 40 | L6: 0 | M6: 0 | N6: 0 | O6: 0 | P6: 0
C8: Closing Total Debt | E8: $M | G8: 6834 | H8: 3099 | I8: 5230 | J8: 8213 | K8: 8376 | L8: =L5+L6 -> 8376 | M8: =M5+M6 -> 8376 | N8: =N5+N6 -> 8376 | O8: =O5+O6 -> 8376 | P8: =P5+P6 -> 8376
C10: Effective Interest Rate on Debt | G10: =Assumptions!G45 -> 0.031741958 | H10: =Assumptions!H45 -> 0.027948493 | I10: =Assumptions!I45 -> 0.050338819 | J10: =Assumptions!J45 -> 0.066921606 | K10: =Assumptions!K45 -> 0.041154268 | L10: =Assumptions!L45 -> 0.05 | M10: =Assumptions!M45 -> 0.05 | N10: =Assumptions!N45 -> 0.05 | ... P10: =Assumptions!P45 -> 0.05
C11: Interest Expense | E11: $M | G11: 371 | H11: 191 | I11: 156 | J11: 350 | K11: 338 | L11: =AVERAGE(K8,L8)*L10 -> 418.8 | M11: =AVERAGE(L8,M8)*M10 -> 418.8 | N11: =AVERAGE(M8,N8)*N10 -> 418.8 | O11: =AVERAGE(N8,O8)*O10 -> 418.8 | P11: =AVERAGE(O8,P8)*P10 -> 418.8
A13: OTHER INCOME (RETURN ON CASH & INVESTMENTS)
C14: Cash & Short-Term Investments (interest-income basis) | E14: $M | G14: =AVERAGE(19384,BS!G5) -> 18480 | H14: =AVERAGE(BS!G5,BS!H5) -> 16914.5 | I14: =AVERAGE(BS!H5,BS!I5) -> 16325.5 | J14: =AVERAGE(BS!I5,BS!J5) -> 16268.5 | K14: =AVERAGE(BS!J5,BS!K5) -> 16326 | L14: =BS!K5 -> 16513 | M14: =BS!L5 -> 19640.666 | N14: =BS!M5 -> 23666.605 | O14: =BS!N5 -> 28247.664 | P14: =BS!O5 -> 35881.154
C15: Return Rate on Cash & Investments | G15: =Assumptions!G46 -> 0.003030303 | H15: =Assumptions!H46 -> 0.017558899 | I15: =Assumptions!I46 -> 0.065296622 | J15: =Assumptions!J46 -> 0.096444048 | K15: =Assumptions!K46 -> 0.10290334 | L15: =Assumptions!L46 -> 0.045 | M15: =Assumptions!M46 -> 0.045 | N15: =Assumptions!N46 -> 0.045 | ... P15: =Assumptions!P46 -> 0.04
C16: Interest Income | E16: $M | G16: 56 | H16: 297 | I16: 1066 | J16: 1569 | K16: 1680 | L16: =L14*L15 -> 743.085 | M16: =M14*M15 -> 883.82997 | N16: =N14*N15 -> 1064.9972 | O16: =O14*O15 -> 1129.9066 | P16: =P14*P15 -> 1435.2462

Sheet Tax Schedule
A1: TESLA, INC. | E1: ◄ Cover | G1: TAX SCHEDULE
A2: USD millions except per-share and operating data
E3: Unit | G3: FY21A | H3: FY22A | I3: FY23A | J3: FY24A | K3: FY25A | L3: FY26E | M3: FY27E | N3: FY28E | O3: FY29E | P3: FY30E
C4: PBT (Income Before Taxes) | E4: $M | G4: =IS!G37 -> 6343 | H4: =IS!H37 -> 13719 | I4: =IS!I37 -> 9973 | J4: =IS!J37 -> 8990 | K4: =IS!K37 -> 5278 | L4: =IS!L37 -> 7252.5328 | M4: =IS!M37 -> 9744.7203 | N4: =IS!N37 -> 13709.226 | ... P4: =IS!P37 -> 21580.756
C5: Effective / Normalized Tax Rate | G5: =G6/G4 -> 0.11020022 | H5: =H6/H4 -> 0.082513303 | I5: =I6/I4 -> -0.50145393 | J5: =J6/J4 -> 0.20433815 | K5: =K6/K4 -> 0.2696097 | L5: =Assumptions!L49 -> 0.24 | M5: =Assumptions!M49 -> 0.24 | N5: =Assumptions!N49 -> 0.24 | O5: =Assumptions!O49 -> 0.24 | P5: =Assumptions!P49 -> 0.24
C6: Income Tax Expense | E6: $M | G6: 699 | H6: 1132 | I6: -5001 | J6: 1837 | K6: 1423 | L6: =L4*L5 -> 1740.6079 | M6: =M4*M5 -> 2338.7329 | N6: =N4*N5 -> 3290.2143 | O6: =O4*O5 -> 4255.4835 | P6: =P4*P5 -> 5179.3815
C7: Implied Effective Tax Rate % | G7: =G6/G4 -> 0.11020022 | H7: =H6/H4 -> 0.082513303 | I7: =I6/I4 -> -0.50145393 | J7: =J6/J4 -> 0.20433815 | K7: =K6/K4 -> 0.2696097 | L7: =L6/L4 -> 0.24 | M7: =M6/M4 -> 0.24 | N7: =N6/N4 -> 0.24 | ... P7: =P6/P4 -> 0.24

Sheet Equity Schedule
A1: TESLA, INC. | E1: ◄ Cover | G1: EQUITY SCHEDULE
A2: USD millions except per-share and operating data
E3: Unit | G3: FY21A | H3: FY22A | I3: FY23A | J3: FY24A | K3: FY25A | L3: FY26E | M3: FY27E | N3: FY28E | O3: FY29E | P3: FY30E
C4: Opening Total Equity | E4: $M | G4: 23730 | H4: =G9 -> 30931 | I4: =H9 -> 45436 | J4: =I9 -> 63291 | K4: =J9 -> 73367 | L4: =K9 -> 82676 | M4: =L9 -> 92261.698 | N4: =M9 -> 104193.66 | O4: =N9 -> 119520.16 | P4: =O9 -> 138513.59
C5: [+] Net Income | E5: $M | G5: =IS!G43 -> 5644 | H5: =IS!H43 -> 12587 | I5: =IS!I43 -> 14974 | J5: =IS!J43 -> 7153 | K5: =IS!K43 -> 3855 | L5: =IS!L43 -> 5511.925 | M5: =IS!M43 -> 7405.9874 | N5: =IS!N43 -> 10419.012 | ... P5: =IS!P43 -> 16401.375
C6: [+] Stock-Based Comp & Net Equity Issuance | E6: $M | G6: =BS!G29-27261 -> 2545 | H6: =BS!H29-BS!G29 -> 2374 | I6: =BS!I29-BS!H29 -> 2715 | J6: =BS!J29-BS!I29 -> 3479 | K6: =BS!K29-BS!J29 -> 4399 | L6: ='Revenue Build-up'!L18*Assumptions!L52 -> 4073.7732 | M6: ='Revenue Build-up'!M18*Assumptions!M52 -> 4525.9734 | N6: ='Revenue Build-up'!N18*Assumptions!N52 -> 4907.4939 | O6: ='Revenue Build-up'!O18*Assumptions!O52 -> 5517.7255 | P6: ='Revenue Build-up'!P18*Assumptions!P52 -> 5649.2875
C7: [-] Dividends Paid | E7: $M | G7: 0 | H7: 0 | I7: 0 | J7: 0 | K7: 0 | L7: 0 | M7: 0 | N7: 0 | O7: 0 | P7: 0
C8: [+/-] Other Comprehensive Income & Adjustments | E8: $M | G8: =(BS!G30-363)+(BS!G32-1505) -> -988 | H8: =(BS!H30-BS!G30)+(BS!H32-BS!G32) -> -456 | I8: =(BS!I30-BS!H30)+(BS!I32-BS!H32) -> 166 | J8: =(BS!J30-BS!I30)+(BS!J32-BS!I32) -> -556 | K8: =(BS!K30-BS!J30)+(BS!K32-BS!J32) -> 1055 | L8: 0 | M8: 0 | N8: 0 | O8: 0 | P8: 0
C9: Closing Total Equity | E9: $M | G9: =G4+G5+G6-G7+G8 -> 30931 | H9: =H4+H5+H6-H7+H8 -> 45436 | I9: =I4+I5+I6-I7+I8 -> 63291 | J9: =J4+J5+J6-J7+J8 -> 73367 | K9: =K4+K5+K6-K7+K8 -> 82676 | L9: =L4+L5+L6-L7+L8 -> 92261.698 | M9: =M4+M5+M6-M7+M8 -> 104193.66 | N9: =N4+N5+N6-N7+N8 -> 119520.16 | ... P9: =P4+P5+P6-P7+P8 -> 160564.25
A11: SHARES OUTSTANDING
C12: Diluted Weighted-Average Shares Outstanding | E12: millions | G12: 3386 | H12: 3475 | I12: 3485 | J12: 3498 | K12: 3528 | L12: =Assumptions!$G$57 -> 3950 | M12: =Assumptions!$G$57 -> 3950 | N12: =Assumptions!$G$57 -> 3950 | O12: =Assumptions!$G$57 -> 3950 | P12: =Assumptions!$G$57 -> 3950

Sheet Cashflow
A1: TESLA, INC. | E1: ◄ Cover | G1: CASH FLOW STATEMENT
A2: USD millions except per-share and operating data
E3: Unit | G3: FY21A | H3: FY22A | I3: FY23A | J3: FY24A | K3: FY25A | L3: FY26E | M3: FY27E | N3: FY28E | O3: FY29E | P3: FY30E
A4: CASH FLOW FROM OPERATING ACTIVITIES
C5: Net Income | E5: $M | G5: =IS!G43 -> 5644 | H5: =IS!H43 -> 12587 | I5: =IS!I43 -> 14974 | J5: =IS!J43 -> 7153 | K5: =IS!K43 -> 3855 | L5: =IS!L43 -> 5511.925 | M5: =IS!M43 -> 7405.9874 | N5: =IS!N43 -> 10419.012 | ... P5: =IS!P43 -> 16401.375
C6: [+] Depreciation & Amortization | E6: $M | G6: ='Asset Schedule'!G7 -> 2911 | H6: ='Asset Schedule'!H7 -> 3747 | I6: ='Asset Schedule'!I7 -> 4667 | J6: ='Asset Schedule'!J7 -> 5368 | K6: ='Asset Schedule'!K7 -> 6148 | L6: ='Asset Schedule'!L7 -> 6706.095 | M6: ='Asset Schedule'!M7 -> 7059.4141 | N6: ='Asset Schedule'!N7 -> 7410.7222 | ... P6: ='Asset Schedule'!P7 -> 8484.3257
C7: [+] Stock-Based Compensation (non-cash, incl. in Equity) | E7: $M | G7: 2121 | H7: 1560 | I7: 1812 | J7: 1999 | K7: 2825 | L7: ='Equity Schedule'!L6 -> 4073.7732 | M7: ='Equity Schedule'!M6 -> 4525.9734 | N7: ='Equity Schedule'!N6 -> 4907.4939 | O7: ='Equity Schedule'!O6 -> 5517.7255 | P7: ='Equity Schedule'!P6 -> 5649.2875
C8: [+/-] Change in Deferred Revenue (Curr + Non-Curr) | E8: $M | G8: 979 | H8: 1286 | I8: 1532 | J8: 502 | K8: 363 | L8: =(BS!L19-BS!K19)+(BS!L24-BS!K24) -> 74.103142 | M8: =(BS!M19-BS!L19)+(BS!M24-BS!L24) -> 791.35032 | N8: =(BS!N19-BS!M19)+(BS!N24-BS!M24) -> 1119.6668 | O8: =(BS!O19-BS!N19)+(BS!O24-BS!N24) -> 1124.1109 | P8: =(BS!P19-BS!O19)+(BS!P24-BS!O24) -> 1134.3438
C9: Change in Working Capital:
C10: [-] Increase in Accounts Receivable | E10: $M | G10: -130 | H10: -1124 | I10: -586 | J10: -1083 | K10: -261 | L10: =-(BS!L6-BS!K6) -> -446.46014 | M10: =-(BS!M6-BS!L6) -> -557.50708 | N10: =-(BS!N6-BS!M6) -> -434.98563 | O10: =-(BS!O6-BS!N6) -> -747.9407 | P10: =-(BS!P6-BS!O6) -> -754.74931
C11: [-] Increase in Inventory & Operating Lease Vehicles | E11: $M | G11: -3823 | H11: -8035 | I11: -3147 | J11: 347 | K11: -655 | L11: =-(BS!L7-BS!K7) -> 84.609347 | M11: =-(BS!M7-BS!L7) -> -672.02329 | N11: =-(BS!N7-BS!M7) -> -799.24327 | O11: =-(BS!O7-BS!N7) -> -920.55436 | P11: =-(BS!P7-BS!O7) -> -1487.8351
C12: [-] Increase in Other Current Assets | E12: $M | G12: -271 | H12: -1417 | I12: -2652 | J12: -3273 | K12: -3181 | L12: =-(BS!L8-BS!K8) -> -3539.8456 | M12: =-(BS!M8-BS!L8) -> -5427.3951 | N12: =-(BS!N8-BS!M8) -> -7529.5896 | O12: =-(BS!O8-BS!N8) -> -7875.5238 | P12: =-(BS!P8-BS!O8) -> -8258.0959
C13: [+/-] Change in Accounts Payable & Accrued Liabilities | E13: $M | G13: 4578 | H13: 6029 | I13: 2605 | J13: 3588 | K13: 4376 | L13: =(BS!L17-BS!K17)+(BS!L18-BS!K18) -> 463.5488 | M13: =(BS!M17-BS!L17)+(BS!M18-BS!L18) -> 2779.3301 | N13: =(BS!N17-BS!M17)+(BS!N18-BS!M18) -> 2784.5817 | O13: =(BS!O17-BS!N17)+(BS!O18-BS!N18) -> 3846.9667 | P13: =(BS!P17-BS!O17)+(BS!P18-BS!O18) -> 3078.3667
C14: [+/-] Other Non-Cash Operating Adjustments, net | E14: $M | G14: 303 | H14: 738 | I14: -5949 | J14: 322 | K14: 1277 | L14: 0 | M14: 0 | N14: 0 | O14: 0 | P14: 0
C15: [+] Increase in Other Non-Current Assets/Liab, net | E15: $M | G15: -815 | H15: -647 | I15: 0 | J15: 0 | K15: 0 | L15: =(BS!L25-BS!K25)-(BS!L13-BS!K13)-(BS!L12-BS!K12) -> 384.35041 | M15: =(BS!M25-BS!L25)-(BS!M13-BS!L13)-(BS!M12-BS!L12) -> -1130.004 | N15: =(BS!N25-BS!M25)-(BS!N13-BS!M13)-(BS!N12-BS!M12) -> -1673.587 | O15: =(BS!O25-BS!N25)-(BS!O13-BS!N13)-(BS!O12-BS!N12) -> -2248.2218 | P15: =(BS!P25-BS!O25)-(BS!P13-BS!O13)-(BS!P12-BS!O12) -> -1461.6466
C16: Net Change in Working Capital | E16: $M | G16: =SUM(G8:G15) -> 821 | H16: =SUM(H8:H15) -> -3170 | I16: =SUM(I8:I15) -> -8197 | J16: =SUM(J8:J15) -> 403 | K16: =SUM(K8:K15) -> 1919 | L16: =SUM(L8:L15) -> -2979.6941 | M16: =SUM(M8:M15) -> -4216.249 | N16: =SUM(N8:N15) -> -6533.157 | ... P16: =SUM(P8:P15) -> -7749.6163
C17: CASH FLOW FROM OPERATIONS | E17: $M | G17: =SUM(G5:G7)+G16 -> 11497 | H17: =SUM(H5:H7)+H16 -> 14724 | I17: =SUM(I5:I7)+I16 -> 13256 | J17: =SUM(J5:J7)+J16 -> 14923 | K17: =SUM(K5:K7)+K16 -> 14747 | L17: =SUM(L5:L7)+L16 -> 13312.099 | M17: =SUM(M5:M7)+M16 -> 14775.126 | N17: =SUM(N5:N7)+N16 -> 16204.071 | ... P17: =SUM(P5:P7)+P16 -> 22785.372
A19: CASH FLOW FROM INVESTING ACTIVITIES
C20: [-] Capital Expenditure | E20: $M | G20: ='Asset Schedule'!G6 -> 6482 | H20: ='Asset Schedule'!H6 -> 7158 | I20: ='Asset Schedule'!I6 -> 8899 | J20: ='Asset Schedule'!J6 -> 11342 | K20: ='Asset Schedule'!K6 -> 8527 | L20: ='Asset Schedule'!L6 -> 10184.433 | M20: ='Asset Schedule'!M6 -> 10749.187 | N20: ='Asset Schedule'!N6 -> 11623.012 | ... P20: ='Asset Schedule'!P6 -> 12912.657
C21: CASH FLOW FROM INVESTING | E21: $M | G21: -7868 | H21: -11973 | I21: -15584 | J21: -18787 | K21: -15478 | L21: =-L20 -> -10184.433 | M21: =-M20 -> -10749.187 | N21: =-N20 -> -11623.012 | O21: =-O20 -> -12342.281 | P21: =-P20 -> -12912.657
A23: CASH FLOW FROM FINANCING ACTIVITIES
C24: [+/-] Net Borrowings / (Repayments) | E24: $M | G24: ='Loans & Other Income'!G6 -> -5284 | H24: ='Loans & Other Income'!H6 -> -3364 | I24: ='Loans & Other Income'!I6 -> 2580 | J24: ='Loans & Other Income'!J6 -> 3244 | K24: ='Loans & Other Income'!K6 -> 40 | L24: ='Loans & Other Income'!L6 -> 0 | M24: ='Loans & Other Income'!M6 -> 0 | N24: ='Loans & Other Income'!N6 -> 0 | ... P24: ='Loans & Other Income'!P6 -> 0
C25: [+/-] Other Financing Activities, FX Effect & Restricted Cash Reclass, net (hist. only) | E25: $M | G25: -153 | H25: -710 | I25: -107 | J25: 361 | K25: 1065 | L25: 0 | M25: 0 | N25: 0 | O25: 0 | P25: 0
C26: [-] Dividends Paid | E26: $M | G26: ='Equity Schedule'!G7 -> 0 | H26: ='Equity Schedule'!H7 -> 0 | I26: ='Equity Schedule'!I7 -> 0 | J26: ='Equity Schedule'!J7 -> 0 | K26: ='Equity Schedule'!K7 -> 0 | L26: ='Equity Schedule'!L7 -> 0 | M26: ='Equity Schedule'!M7 -> 0 | N26: ='Equity Schedule'!N7 -> 0 | ... P26: ='Equity Schedule'!P7 -> 0
C28: CASH FLOW FROM FINANCING | E28: $M | G28: =G24+G25-G26 -> -5437 | H28: =H24+H25-H26 -> -4074 | I28: =I24+I25-I26 -> 2473 | J28: =J24+J25-J26 -> 3605 | K28: =K24+K25-K26 -> 1105 | L28: =L24+L25-L26 -> 0 | M28: =M24+M25-M26 -> 0 | N28: =N24+N25-N26 -> 0 | ... P28: =P24+P25-P26 -> 0
C30: Net Change in Cash | E30: $M | G30: =G17+G21+G28 -> -1808 | H30: =H17+H21+H28 -> -1323 | I30: =I17+I21+I28 -> 145 | J30: =J17+J21+J28 -> -259 | K30: =K17+K21+K28 -> 374 | L30: =L17+L21+L28 -> 3127.6661 | M30: =M17+M21+M28 -> 4025.939 | N30: =N17+N21+N28 -> 4581.0592 | ... P30: =P17+P21+P28 -> 9872.7145
C31: [+] Opening Cash & Cash Equivalents | E31: $M | G31: 19384 | H31: =G32 -> 17576 | I31: =H32 -> 16253 | J31: =I32 -> 16398 | K31: =J32 -> 16139 | L31: =K32 -> 16513 | M31: =L32 -> 19640.666 | N31: =M32 -> 23666.605 | O31: =N32 -> 28247.664 | P31: =O32 -> 35881.154
C32: Closing Cash & Cash Equivalents | E32: $M | G32: =G31+G30 -> 17576 | H32: =H31+H30 -> 16253 | I32: =I31+I30 -> 16398 | J32: =J31+J30 -> 16139 | K32: =K31+K30 -> 16513 | L32: =L31+L30 -> 19640.666 | M32: =M31+M30 -> 23666.605 | N32: =N31+N30 -> 28247.664 | ... P32: =P31+P30 -> 45753.868
C34: Cash Check (Closing Cash − BS Cash) | G34: =IF(ABS(G32-BS!G5)<0.5,"PASS","FAIL") -> PASS | H34: =IF(ABS(H32-BS!H5)<0.5,"PASS","FAIL") -> PASS | I34: =IF(ABS(I32-BS!I5)<0.5,"PASS","FAIL") -> PASS | J34: =IF(ABS(J32-BS!J5)<0.5,"PASS","FAIL") -> PASS | K34: =IF(ABS(K32-BS!K5)<0.5,"PASS","FAIL") -> PASS | L34: =IF(ABS(L32-BS!L5)<0.5,"PASS","FAIL") -> PASS | M34: =IF(ABS(M32-BS!M5)<0.5,"PASS","FAIL") -> PASS | N34: =IF(ABS(N32-BS!N5)<0.5,"PASS","FAIL") -> PASS | ... P34: =IF(ABS(P32-BS!P5)<0.5,"PASS","FAIL") -> PASS

Sheet Ratio Analysis
A1: TESLA, INC. | E1: ◄ Cover | G1: RATIO ANALYSIS
A2: Ratios are dimensionless unless stated otherwise
E3: Unit | G3: FY21A | H3: FY22A | I3: FY23A | J3: FY24A | K3: FY25A | L3: FY26E | M3: FY27E | N3: FY28E | O3: FY29E | P3: FY30E
A4: PROFITABILITY MARGINS
C5: EBITDA Margin | G5: =IS!G29/IS!G8 -> 0.17527823 | H5: =IS!H29/IS!H8 -> 0.21363335 | I5: =IS!I29/IS!I8 -> 0.14010106 | J5: =IS!J29/IS!J8 -> 0.12738254 | K5: =IS!K29/IS!K8 -> 0.11075959 | L5: =IS!L29/IS!L8 -> 0.13387434 | M5: =IS!M29/IS!M8 -> 0.14440301 | N5: =IS!N29/IS!N8 -> 0.15853357 | ... P5: =IS!P29/IS!P8 -> 0.17997
C6: EBIT Margin | G6: =IS!G25/IS!G8 -> 0.12119354 | H6: =IS!H25/IS!H8 -> 0.16763644 | I6: =IS!I25/IS!I8 -> 0.0918748 | J6: =IS!J25/IS!J8 -> 0.072433207 | K6: =IS!K25/IS!K8 -> 0.045925738 | L6: =IS!L25/IS!L8 -> 0.06802782 | M6: =IS!M25/IS!M8 -> 0.082012769 | N6: =IS!N25/IS!N8 -> 0.10115043 | ... P6: =IS!P25/IS!P8 -> 0.1274056
C7: PBT Margin | G7: =IS!G37/IS!G8 -> 0.11784925 | H7: =IS!H37/IS!H8 -> 0.16840981 | I7: =IS!I37/IS!I8 -> 0.1030556 | J7: =IS!J37/IS!J8 -> 0.092025796 | K7: =IS!K37/IS!K8 -> 0.055659253 | L7: =IS!L37/IS!L8 -> 0.071211945 | M7: =IS!M37/IS!M8 -> 0.086122647 | N7: =IS!N37/IS!N8 -> 0.1061541 | ... P7: =IS!P37/IS!P8 -> 0.13370296
C8: Net Income (PAT) Margin | G8: =IS!G43/IS!G8 -> 0.10486223 | H8: =IS!H43/IS!H8 -> 0.15451376 | I8: =IS!I43/IS!I8 -> 0.15473324 | J8: =IS!J43/IS!J8 -> 0.073221415 | K8: =IS!K43/IS!K8 -> 0.040652979 | L8: =IS!L43/IS!L8 -> 0.054121078 | M8: =IS!M43/IS!M8 -> 0.065453212 | N8: =IS!N43/IS!N8 -> 0.080677116 | ... P8: =IS!P43/IS!P8 -> 0.10161425
A10: GROWTH RATES (YoY)
C11: Revenue Growth | H11: =IS!H8/IS!G8-1 -> 0.51351653 | I11: =IS!I8/IS!H8-1 -> 0.18795267 | J11: =IS!J8/IS!I8-1 -> 0.0094757835 | K11: =IS!K8/IS!J8-1 -> -0.029306992 | L11: =IS!L8/IS!K8-1 -> 0.074001398 | M11: =IS!M8/IS!L8-1 -> 0.11100279 | N11: =IS!N8/IS!M8-1 -> 0.14136398 | O11: =IS!O8/IS!N8-1 -> 0.12434689 | P11: =IS!P8/IS!O8-1 -> 0.11160154
C12: EBITDA Growth | H12: =IS!H29/IS!G29-1 -> 0.84471062 | I12: =IS!I29/IS!H29-1 -> -0.22093892 | J12: =IS!J29/IS!I29-1 -> -0.082165511 | K12: =IS!K29/IS!J29-1 -> -0.15597878 | L12: =IS!L29/IS!K29-1 -> 0.29813794 | M12: =IS!M29/IS!L29-1 -> 0.19837858 | N12: =IS!N29/IS!M29-1 -> 0.25305223 | O12: =IS!O29/IS!N29-1 -> 0.21245904 | P12: =IS!P29/IS!O29-1 -> 0.1702031
C13: EBIT Growth | H13: =IS!H25/IS!G25-1 -> 1.0935153 | I13: =IS!I25/IS!H25-1 -> -0.34893087 | J13: =IS!J25/IS!I25-1 -> -0.20413902 | K13: =IS!K25/IS!J25-1 -> -0.38453929 | L13: =IS!L25/IS!K25-1 -> 0.59087206 | M13: =IS!M25/IS!L25-1 -> 0.3393993 | N13: =IS!N25/IS!M25-1 -> 0.40770098 | O13: =IS!O25/IS!N25-1 -> 0.30291946 | P13: =IS!P25/IS!O25-1 -> 0.20823853
C14: PBT Growth | H14: =IS!H37/IS!G37-1 -> 1.1628567 | I14: =IS!I37/IS!H37-1 -> -0.27305197 | J14: =IS!J37/IS!I37-1 -> -0.098566129 | K14: =IS!K37/IS!J37-1 -> -0.41290323 | L14: =IS!L37/IS!K37-1 -> 0.37410626 | M14: =IS!M37/IS!L37-1 -> 0.34362994 | N14: =IS!N37/IS!M37-1 -> 0.40683631 | O14: =IS!O37/IS!N37-1 -> 0.29337579 | P14: =IS!P37/IS!O37-1 -> 0.21710764
C15: Net Income Growth | H15: =IS!H43/IS!G43-1 -> 1.2301559 | I15: =IS!I43/IS!H43-1 -> 0.1896401 | J15: =IS!J43/IS!I43-1 -> -0.52230533 | K15: =IS!K43/IS!J43-1 -> -0.46106529 | L15: =IS!L43/IS!K43-1 -> 0.42981192 | M15: =IS!M43/IS!L43-1 -> 0.34362994 | N15: =IS!N43/IS!M43-1 -> 0.40683631 | O15: =IS!O43/IS!N43-1 -> 0.29337579 | P15: =IS!P43/IS!O43-1 -> 0.21710764
A17: COST STRUCTURE (% OF REVENUE)
C18: Cost of Revenue / Sales | G18: =IS!G14/IS!G8 -> 0.74720844 | H18: =IS!H14/IS!H8 -> 0.74401561 | I18: =IS!I14/IS!I8 -> 0.81751108 | J18: =IS!J14/IS!J8 -> 0.82137373 | K18: =IS!K14/IS!K8 -> 0.81973489 | L18: =IS!L14/IS!L8 -> 0.80197218 | M18: =IS!M14/IS!M8 -> 0.78998723 | N18: =IS!N14/IS!N8 -> 0.77884957 | ... P18: =IS!P14/IS!P8 -> 0.7625944
C19: R&D / Sales | G19: =IS!G20/IS!G8 -> 0.04817643 | H19: =IS!H20/IS!H8 -> 0.037747661 | I19: =IS!I20/IS!I8 -> 0.041013506 | J19: =IS!J20/IS!J8 -> 0.046473539 | K19: =IS!K20/IS!K8 -> 0.067607327 | L19: =IS!L20/IS!L8 -> 0.07 | M19: =IS!M20/IS!M8 -> 0.07 | N19: =IS!N20/IS!N8 -> 0.065 | ... P19: =IS!P20/IS!P8 -> 0.06
C20: SG&A / Sales | G20: =IS!G21/IS!G8 -> 0.08392323 | H20: =IS!H21/IS!H8 -> 0.048439763 | I20: =IS!I21/IS!I8 -> 0.049600612 | J20: =IS!J21/IS!J8 -> 0.052717781 | K20: =IS!K21/IS!K8 -> 0.061522562 | L20: =IS!L21/IS!L8 -> 0.06 | M20: =IS!M21/IS!M8 -> 0.058 | N20: =IS!N21/IS!N8 -> 0.055 | ... P20: =IS!P21/IS!P8 -> 0.05
A22: LIQUIDITY RATIOS
C23: Current Ratio | G23: =BS!G9/BS!G21 -> 1.3752855 | H23: =BS!H9/BS!H21 -> 1.5319555 | I23: =BS!I9/BS!I21 -> 1.725894 | J23: =BS!J9/BS!J21 -> 2.0249124 | K23: =BS!K9/BS!K21 -> 2.1644069 | L23: =BS!L9/BS!L21 -> 2.3414545 | M23: =BS!M9/BS!M21 -> 2.4329859 | N23: =BS!N9/BS!N21 -> 2.5670821 | ... P23: =BS!P9/BS!P21 -> 2.9269336
C24: Quick Ratio | G24: =(BS!G9-BS!G7)/BS!G21 -> 1.0831261 | H24: =(BS!H9-BS!H7)/BS!H21 -> 1.0512561 | I24: =(BS!I9-BS!I7)/BS!I21 -> 1.2519132 | J24: =(BS!J9-BS!J7)/BS!J21 -> 1.6079595 | K24: =(BS!K9-BS!K7)/BS!K21 -> 1.7736646 | L24: =(BS!L9-BS!L7)/BS!L21 -> 1.9606342 | M24: =(BS!M9-BS!M7)/BS!M21 -> 2.0672976 | N24: =(BS!N9-BS!N7)/BS!N21 -> 2.2123052 | ... P24: =(BS!P9-BS!P7)/BS!P21 -> 2.5817357
A26: RETURN RATIOS
C27: ROE (Return on Closing Equity) | G27: =IS!G43/BS!G33 -> 0.18197646 | H27: =IS!H43/BS!H33 -> 0.27670426 | I27: =IS!I43/BS!I33 -> 0.23630596 | J27: =IS!J43/BS!J33 -> 0.097165057 | K27: =IS!K43/BS!K33 -> 0.046521451 | L27: =IS!L43/BS!L33 -> 0.059620155 | M27: =IS!M43/BS!M33 -> 0.070950362 | N27: =IS!N43/BS!N33 -> 0.087036043 | ... P27: =IS!P43/BS!P33 -> 0.10202826
C28: ROAE (Return on Average Equity) | H28: =IS!H43/AVERAGE(BS!G33,BS!H33) -> 0.32905469 | I28: =IS!I43/AVERAGE(BS!H33,BS!I33) -> 0.27511575 | J28: =IS!J43/AVERAGE(BS!I33,BS!J33) -> 0.10443555 | K28: =IS!K43/AVERAGE(BS!J33,BS!K33) -> 0.049270843 | L28: =IS!L43/AVERAGE(BS!K33,BS!L33) -> 0.062879993 | M28: =IS!M43/AVERAGE(BS!L33,BS!M33) -> 0.075251345 | N28: =IS!N43/AVERAGE(BS!M33,BS!N33) -> 0.092988774 | O28: =IS!O43/AVERAGE(BS!N33,BS!O33) -> 0.10429632 | P28: =IS!P43/AVERAGE(BS!O33,BS!P33) -> 0.10954119
A30: LEVERAGE RATIOS
C31: Debt / Equity | G31: ='Loans & Other Income'!G8/BS!G33 -> 0.22034499 | H31: ='Loans & Other Income'!H8/BS!H33 -> 0.06812636 | I31: ='Loans & Other Income'!I8/BS!I33 -> 0.082535073 | J31: ='Loans & Other Income'!J8/BS!J33 -> 0.11156391 | K31: ='Loans & Other Income'!K8/BS!K33 -> 0.10108007 | L31: ='Loans & Other Income'!L8/BS!L33 -> 0.09059964 | M31: ='Loans & Other Income'!M8/BS!M33 -> 0.080243214 | N31: ='Loans & Other Income'!N8/BS!N33 -> 0.06996958 | ... P31: ='Loans & Other Income'!P8/BS!P33 -> 0.052104701
C32: Debt / EBITDA | G32: ='Loans & Other Income'!G8/IS!G29 -> 0.7244011 | H32: ='Loans & Other Income'!H8/IS!H29 -> 0.17807275 | I32: ='Loans & Other Income'!I8/IS!I29 -> 0.38575011 | J32: ='Loans & Other Income'!J8/IS!J29 -> 0.65999679 | K32: ='Loans & Other Income'!K8/IS!K29 -> 0.79748643 | L32: ='Loans & Other Income'!L8/IS!L29 -> 0.61433104 | M32: ='Loans & Other Income'!M8/IS!M29 -> 0.5126352 | N32: ='Loans & Other Income'!N8/IS!N29 -> 0.4091092 | ... P32: ='Loans & Other Income'!P8/IS!P29 -> 0.288344
C33: Interest Coverage (EBIT / Interest Exp.) | G33: =IS!G25/IS!G34 -> 17.58221 | H33: =IS!H25/IS!H34 -> 71.497382 | I33: =IS!I25/IS!I34 -> 56.99359 | J33: =IS!J25/IS!J34 -> 20.217143 | K33: =IS!K25/IS!K34 -> 12.884615 | L33: =IS!L25/IS!L34 -> 16.543094 | M33: =IS!M25/IS!M34 -> 22.157809 | N33: =IS!N25/IS!N34 -> 31.191569 | ... P33: =IS!P25/IS!P34 -> 49.102937
H38: CHART SOURCE DATA — PROFITABILITY MARGIN TREND (live links; A and E split so the chart breaks cleanly at FY2025A)
H39: Series | I39: =G3 -> FY21A | J39: =H3 -> FY22A | K39: =I3 -> FY23A | L39: =J3 -> FY24A | M39: =K3 -> FY25A | N39: =L3 -> FY26E | O39: =M3 -> FY27E | P39: =N3 -> FY28E | ... R39: =P3 -> FY30E
H40: Gross Margin | I40: =IS!G17 -> 0.25279156 | J40: =IS!H17 -> 0.25598439 | K40: =IS!I17 -> 0.18248892 | L40: =IS!J17 -> 0.17862627 | M40: =IS!K17 -> 0.18026511 | N40: =NA() -> #N/A | O40: =NA() -> #N/A | P40: =NA() -> #N/A | Q40: =NA() -> #N/A | R40: =NA() -> #N/A
H41: EBITDA Margin | I41: =IS!G30 -> 0.17527823 | J41: =IS!H30 -> 0.21363335 | K41: =IS!I30 -> 0.14010106 | L41: =IS!J30 -> 0.12738254 | M41: =IS!K30 -> 0.11075959 | N41: =NA() -> #N/A | O41: =NA() -> #N/A | P41: =NA() -> #N/A | Q41: =NA() -> #N/A | R41: =NA() -> #N/A
H42: EBIT Margin | I42: =IS!G26 -> 0.12119354 | J42: =IS!H26 -> 0.16763644 | K42: =IS!I26 -> 0.0918748 | L42: =IS!J26 -> 0.072433207 | M42: =IS!K26 -> 0.045925738 | N42: =NA() -> #N/A | O42: =NA() -> #N/A | P42: =NA() -> #N/A | Q42: =NA() -> #N/A | R42: =NA() -> #N/A
H43: Net Margin | I43: =IS!G44 -> 0.10486223 | J43: =IS!H44 -> 0.15451376 | K43: =IS!I44 -> 0.15473324 | L43: =IS!J44 -> 0.073221415 | M43: =IS!K44 -> 0.040652979 | N43: =NA() -> #N/A | O43: =NA() -> #N/A | P43: =NA() -> #N/A | Q43: =NA() -> #N/A | R43: =NA() -> #N/A
H44: Gross Margin (Forecast) | I44: =NA() -> #N/A | J44: =NA() -> #N/A | K44: =NA() -> #N/A | L44: =NA() -> #N/A | M44: =IS!K17 -> 0.18026511 | N44: =IS!L17 -> 0.19802782 | O44: =IS!M17 -> 0.21001277 | P44: =IS!N17 -> 0.22115043 | Q44: =IS!O17 -> 0.23021548 | R44: =IS!P17 -> 0.2374056
H45: EBITDA Margin (Forecast) | I45: =NA() -> #N/A | J45: =NA() -> #N/A | K45: =NA() -> #N/A | L45: =NA() -> #N/A | M45: =IS!K30 -> 0.11075959 | N45: =IS!L30 -> 0.13387434 | O45: =IS!M30 -> 0.14440301 | P45: =IS!N30 -> 0.15853357 | Q45: =IS!O30 -> 0.17095744 | R45: =IS!P30 -> 0.17997
H46: EBIT Margin (Forecast) | I46: =NA() -> #N/A | J46: =NA() -> #N/A | K46: =NA() -> #N/A | L46: =NA() -> #N/A | M46: =IS!K26 -> 0.045925738 | N46: =IS!L26 -> 0.06802782 | O46: =IS!M26 -> 0.082012769 | P46: =IS!N26 -> 0.10115043 | Q46: =IS!O26 -> 0.11721548 | R46: =IS!P26 -> 0.1274056
H47: Net Margin (Forecast) | I47: =NA() -> #N/A | J47: =NA() -> #N/A | K47: =NA() -> #N/A | L47: =NA() -> #N/A | M47: =IS!K44 -> 0.040652979 | N47: =IS!L44 -> 0.054121078 | O47: =IS!M44 -> 0.065453212 | P47: =IS!N44 -> 0.080677116 | Q47: =IS!O44 -> 0.092805725 | R47: =IS!P44 -> 0.10161425
H48: FY2025A appears in both the actual and the forecast series so the lines join; every other out-of-period cell returns #N/A, which Excel does not plot (no false drop to zero).

Sheet Comparable Companies
A1: TESLA, INC. | E1: ◄ Cover | G1: COMPARABLE COMPANY ANALYSIS
A2: USD $ millions except share price, per-share and multiple data | MARKET DATA AS OF: SEPTEMBER 3, 2026 CLOSE | Convention: TTM (trailing twelve months, ended Jun 30, 2026) for BOTH peers and Tesla -- see period-consistency note below
A3: PEER GROUP SELECTION & RATIONALE
A4: Tesla combines large-scale EV/automotive manufacturing, an EV-battery-technology cost base, and a fast-growing energy storage business -- there is no single publicly traded company with an identical mix. The peer group below was built, not assumed: pure-play EV manufacturers provide the closest business-model match; two large-scale global automakers are included only as scale/margin reference points for Tesla's now-mature automotive segment, not because they "make vehicles."
B5: BYD Company Ltd. (BYDDY) | C5: The closest true business-model analog to Tesla: the world's largest EV manufacturer by volume AND a vertically integrated battery/energy-storage manufacturer (LFP cells, Blade Battery, grid storage) -- the same auto+battery+energy combination Tesla has.
B6: Rivian Automotive (RIVN) | C6: US-listed pure-play EV manufacturer (trucks/SUVs) at a similar stage of scaling manufacturing; useful growth-stage EV comp, though pre-profitability.
B7: Lucid Group (LCID) | C7: US-listed pure-play luxury EV manufacturer with in-house battery/powertrain technology; direct US EV-technology comp, though at an earlier revenue scale than Tesla.
B8: NIO Inc. (NIO) | C8: Chinese EV manufacturer that also operates its own battery-swap energy infrastructure network -- a genuine (if smaller) analog to Tesla's combined vehicle + energy-service model.
B9: Li Auto Inc. (LI) | C9: Chinese EV/EREV manufacturer, one of the few China EV makers with a track record of full-year profitability; included for margin/scale contrast within the China EV cohort.
B10: General Motors (GM) | C10: Global-scale automaker included ONLY as a scale and margin reference for Tesla's mature automotive segment (revenue base and manufacturing scale of a similar order of magnitude); GM's EV unit economics and BEV mix are explicitly not the comparison basis. Note: GM's Enterprise Value includes GM Financial's captive auto-lending debt, which mechanically inflates its EV-based multiples relative to an auto-manufacturing-only peer -- read GM's EV/Revenue and EV/EBITDA with that in mind.
B11: Ford Motor Company (F) | C11: Included on the same scale/margin reference basis as GM -- a large-cap global automaker of comparable revenue scale -- not for EV-mix comparability. Same captive-finance EV caveat as GM (Ford Credit).
A13: Deliberately EXCLUDED: Toyota, Volkswagen, Stellantis, Hyundai and other large diversified global OEMs (EV is a small fraction of their revenue/earnings mix, making a blended multiple uninformative for Tesla); XPeng and Zeekr (excluded only to keep the China-EV cohort to two names alongside NIO/Li Auto and avoid double-weighting one geography); pure battery-cell manufacturers such as CATL and Panasonic Energy (they sell to automakers rather than being vertically integrated vehicle OEMs, a different business model from Tesla's).
A15: PEER TRADING DATA & MULTIPLES (TTM ended ~Jun 30, 2026; priced at Sep 3, 2026 close)
B16: Company | C16: Ticker | D16: Share Price | E16: Market Cap | F16: Enterprise Value | G16: Revenue | H16: EBITDA | I16: EBIT | J16: Net Income | K16: Book Value | L16: EV/Rev | M16: EV/EBITDA | N16: EV/EBIT | O16: P/E | P16: P/B | Q16: EBITDA margin | R16: EBIT margin
B17: BYD Company Ltd. | C17: BYDDY | D17: 11.01 | E17: 110450 | F17: 111890 | G17: 114460 | H17: 17752 | I17: 5898 | J17: 4310 | K17: 40240 | L17: =IF(G17<=0,"NM",F17/G17) -> 0.97754674 | M17: =IF(NOT(ISNUMBER(H17)),"NM",IF(H17<=0,"NM",F17/H17)) -> 6.3029518 | N17: =IF(I17<=0,"NM",F17/I17) -> 18.970838 | O17: =IF(J17<=0,"NM",E17/J17) -> 25.62645 | P17: =IF(K17<=0,"NM",E17/K17) -> 2.7447813 | Q17: =IF(H17<=0,"NM",H17/G17) -> 0.15509348 | R17: =IF(I17<=0,"NM",I17/G17) -> 0.051528918
B18: Rivian Automotive | C18: RIVN | D18: 15.91 | E18: 23040 | F18: 23080 | G18: 5883 | H18: -2714 | I18: -3533 | J18: -3233 | K18: 5130 | L18: =IF(G18<=0,"NM",F18/G18) -> 3.9231685 | M18: =IF(NOT(ISNUMBER(H18)),"NM",IF(H18<=0,"NM",F18/H18)) -> NM | N18: =IF(I18<=0,"NM",F18/I18) -> NM | O18: =IF(J18<=0,"NM",E18/J18) -> NM | P18: =IF(K18<=0,"NM",E18/K18) -> 4.4912281 | Q18: =IF(H18<=0,"NM",H18/G18) -> NM | R18: =IF(I18<=0,"NM",I18/G18) -> NM
B19: Lucid Group | C19: LCID | D19: 4.6 | E19: 1810 | F19: 4710 | G19: 1547 | H19: -3588 | I19: -4069 | J19: -4605 | K19: 1848 | L19: =IF(G19<=0,"NM",F19/G19) -> 3.0446025 | M19: =IF(NOT(ISNUMBER(H19)),"NM",IF(H19<=0,"NM",F19/H19)) -> NM | N19: =IF(I19<=0,"NM",F19/I19) -> NM | O19: =IF(J19<=0,"NM",E19/J19) -> NM | P19: =IF(K19<=0,"NM",E19/K19) -> 0.97943723 | Q19: =IF(H19<=0,"NM",H19/G19) -> NM | R19: =IF(I19<=0,"NM",I19/G19) -> NM
B20: NIO Inc. | C20: NIO | D20: 3.86 | E20: 9660 | F20: 7590 | G20: 16800 | H20: 502 | I20: -561 | J20: -700 | K20: 2135 | L20: =IF(G20<=0,"NM",F20/G20) -> 0.45178571 | M20: =IF(NOT(ISNUMBER(H20)),"NM",IF(H20<=0,"NM",F20/H20)) -> 15.119522 | N20: =IF(I20<=0,"NM",F20/I20) -> NM | O20: =IF(J20<=0,"NM",E20/J20) -> NM | P20: =IF(K20<=0,"NM",E20/K20) -> 4.5245902 | Q20: =IF(H20<=0,"NM",H20/G20) -> 0.029880952 | R20: =IF(I20<=0,"NM",I20/G20) -> NM
B21: Li Auto Inc. | C21: LI | D21: 12.06 | E21: 11830 | F21: 1390 | G21: 15430 | H21: -329 | I21: -1012 | J21: -679 | K21: 9710 | L21: =IF(G21<=0,"NM",F21/G21) -> 0.090084251 | M21: =IF(NOT(ISNUMBER(H21)),"NM",IF(H21<=0,"NM",F21/H21)) -> NM | N21: =IF(I21<=0,"NM",F21/I21) -> NM | O21: =IF(J21<=0,"NM",E21/J21) -> NM | P21: =IF(K21<=0,"NM",E21/K21) -> 1.2183316 | Q21: =IF(H21<=0,"NM",H21/G21) -> NM | R21: =IF(I21<=0,"NM",I21/G21) -> NM
B22: General Motors | C22: GM | D22: 87.22 | E22: 76530 | F22: 180580 | G22: 185528 | H22: 16462 | I22: 10284 | J22: 1857 | K22: 63640 | L22: =IF(G22<=0,"NM",F22/G22) -> 0.97333017 | M22: =IF(NOT(ISNUMBER(H22)),"NM",IF(H22<=0,"NM",F22/H22)) -> 10.969506 | N22: =IF(I22<=0,"NM",F22/I22) -> 17.559315 | O22: =IF(J22<=0,"NM",E22/J22) -> 41.211632 | P22: =IF(K22<=0,"NM",E22/K22) -> 1.2025456 | Q22: =IF(H22<=0,"NM",H22/G22) -> 0.088730542 | R22: =IF(I22<=0,"NM",I22/G22) -> 0.055430986
B23: Ford Motor Company | C23: F | D23: 14.41 | E23: 57460 | F23: 198640 | G23: 187973 | H23: 7643 | I23: 1609 | J23: -7396 | K23: 35760 | L23: =IF(G23<=0,"NM",F23/G23) -> 1.0567475 | M23: =IF(NOT(ISNUMBER(H23)),"NM",IF(H23<=0,"NM",F23/H23)) -> 25.989795 | N23: =IF(I23<=0,"NM",F23/I23) -> 123.45556 | O23: =IF(J23<=0,"NM",E23/J23) -> NM | P23: =IF(K23<=0,"NM",E23/K23) -> 1.6068233 | Q23: =IF(H23<=0,"NM",H23/G23) -> 0.040660095 | R23: =IF(I23<=0,"NM",I23/G23) -> 0.00855974
B24: ▌ Rows 17–21 — growth / EV-oriented pure-play EV peers (BYDDY, RIVN, LCID, NIO, LI): the business-model comparison set. ▌ Rows 22–23 — traditional automotive scale references (GM, F): included for revenue-scale and margin context only, and their EV multiples are inflated by captive-finance debt. Percentile statistics span all seven peers, as in the original methodology. EBITDA and EBIT margins are derived from the sourced peer financials; revenue growth and forward (NTM) multiples are not shown because comparable-period prior-year revenue and consensus estimates were not independently sourced for this workbook.
B25: PEER STATISTICS (excludes Tesla)
B26: Minimum | L26: =IFERROR(MIN(L17:L23),"NM") -> 0.090084251 | M26: =IFERROR(MIN(M17:M23),"NM") -> 6.3029518 | N26: =IFERROR(MIN(N17:N23),"NM") -> 17.559315 | O26: =IFERROR(MIN(O17:O23),"NM") -> 25.62645 | P26: =IFERROR(MIN(P17:P23),"NM") -> 0.97943723 | Q26: =IFERROR(MIN(Q17:Q23),"NM") -> 0.029880952 | R26: =IFERROR(MIN(R17:R23),"NM") -> 0.00855974
B27: 25th Percentile | L27: =IFERROR(QUARTILE(L17:L23,1),"NM") -> 0.71255794 | M27: =IFERROR(QUARTILE(M17:M23,1),"NM") -> 9.8028671 | N27: =IFERROR(QUARTILE(N17:N23,1),"NM") -> 18.265077 | O27: =IFERROR(QUARTILE(O17:O23,1),"NM") -> 29.522746 | P27: =IFERROR(QUARTILE(P17:P23,1),"NM") -> 1.2104386 | Q27: =IFERROR(QUARTILE(Q17:Q23,1),"NM") -> 0.037965309 | R27: =IFERROR(QUARTILE(R17:R23,1),"NM") -> 0.030044329
B28: Median | L28: =IFERROR(MEDIAN(L17:L23),"NM") -> 0.97754674 | M28: =IFERROR(MEDIAN(M17:M23),"NM") -> 13.044514 | N28: =IFERROR(MEDIAN(N17:N23),"NM") -> 18.970838 | O28: =IFERROR(MEDIAN(O17:O23),"NM") -> 33.419041 | P28: =IFERROR(MEDIAN(P17:P23),"NM") -> 1.6068233 | Q28: =IFERROR(MEDIAN(Q17:Q23),"NM") -> 0.064695318 | R28: =IFERROR(MEDIAN(R17:R23),"NM") -> 0.051528918
B29: 75th Percentile | L29: =IFERROR(QUARTILE(L17:L23,3),"NM") -> 2.050675 | M29: =IFERROR(QUARTILE(M17:M23,3),"NM") -> 17.83709 | N29: =IFERROR(QUARTILE(N17:N23,3),"NM") -> 71.2132 | O29: =IFERROR(QUARTILE(O17:O23,3),"NM") -> 37.315336 | P29: =IFERROR(QUARTILE(P17:P23,3),"NM") -> 3.6180047 | Q29: =IFERROR(QUARTILE(Q17:Q23,3),"NM") -> 0.10532128 | R29: =IFERROR(QUARTILE(R17:R23,3),"NM") -> 0.053479952
B30: Maximum | L30: =IFERROR(MAX(L17:L23),"NM") -> 3.9231685 | M30: =IFERROR(MAX(M17:M23),"NM") -> 25.989795 | N30: =IFERROR(MAX(N17:N23),"NM") -> 123.45556 | O30: =IFERROR(MAX(O17:O23),"NM") -> 41.211632 | P30: =IFERROR(MAX(P17:P23),"NM") -> 4.5245902 | Q30: =IFERROR(MAX(Q17:Q23),"NM") -> 0.15509348 | R30: =IFERROR(MAX(R17:R23),"NM") -> 0.055430986
A32: TESLA, INC. (TARGET) -- TTM basis, ended Jun 30, 2026 (period-consistent with peers)
B33: Company | C33: Ticker | D33: Share Price | E33: Market Cap | F33: Enterprise Value | G33: Revenue | H33: EBITDA | I33: EBIT | J33: Net Income | K33: Book Value | L33: EV/Rev | M33: EV/EBITDA | N33: EV/EBIT | O33: P/E | P33: P/B | Q33: EBITDA margin | R33: EBIT margin
B34: Tesla, Inc. | C34: TSLA | D34: =Assumptions!$G$56 -> 376.37 | E34: =D34*D35 -> 1486661.5 | F34: =E34+D37+D38-D36 -> 1453140.5 | G34: 103619 | H34: 10760 | I34: 4372 | J34: 3806 | K34: 86858 | L34: =F34/G34 -> 14.023881 | M34: =F34/H34 -> 135.05023 | N34: =F34/I34 -> 332.37431 | O34: =E34/J34 -> 390.60996 | P34: =E34/K34 -> 17.116 | Q34: =IF(H34<=0,"NM",H34/G34) -> 0.10384196 | R34: =IF(I34<=0,"NM",I34/G34) -> 0.042193034
B35: Current Common Shares Outstanding (millions) | D35: 3950
B36: [+] Cash & Short-Term Investments (Q2 2026, 10-Q) | D36: 43524
B37: [-] Total Debt & Finance Leases (Q2 2026 10-Q: $1,418M current + $7,924M non-current) | D37: 9342
B38: [-] Noncontrolling Interests (Q2 2026, 10-Q) | D38: 661
A40: TESLA IMPLIED VALUATION FROM COMPARABLES (TTM basis, Sep 3, 2026)
B41: Method | E41: Multiple | G41: Tesla Metric (TTM) | J41: Implied EV / Equity Value | M41: Implied Share Price
B42: 1. EV / REVENUE
B43: Peer 25th Pctl EV/Revenue | E43: =L27 -> 0.71255794 | G43: =G34 -> 103619 | J43: =E43*G43 -> 73834.541 | M43: Implied Share Price | N43: Source: Tesla TTM Revenue (sourced above)
B44: [+] Cash & Short-Term Investments (TTM) | J44: =D36 -> 43524
B45: [-] Total Debt (TTM) | J45: =D37 -> 9342
B46: [-] Noncontrolling Interests (TTM) | J46: =D38 -> 661
B47: Implied Equity Value | J47: =J43+J44-J45-J46 -> 107355.54 | M47: =J47/J48 -> 27.178618
B48: ÷ Current Common Shares Outstanding | J48: =D35 -> 3950
B50: Peer Median EV/Revenue | E50: =L28 -> 0.97754674 | G50: =G34 -> 103619 | J50: =E50*G50 -> 101292.42 | M50: Implied Share Price | N50: Source: Tesla TTM Revenue (sourced above)
B51: [+] Cash & Short-Term Investments (TTM) | J51: =D36 -> 43524
B52: [-] Total Debt (TTM) | J52: =D37 -> 9342
B53: [-] Noncontrolling Interests (TTM) | J53: =D38 -> 661
B54: Implied Equity Value | J54: =J50+J51-J52-J53 -> 134813.42 | M54: =J54/J55 -> 34.129979
B55: ÷ Current Common Shares Outstanding | J55: =D35 -> 3950
B57: Peer 75th Pctl EV/Revenue | E57: =L29 -> 2.050675 | G57: =G34 -> 103619 | J57: =E57*G57 -> 212488.89 | M57: Implied Share Price | N57: Source: Tesla TTM Revenue (sourced above)
B58: [+] Cash & Short-Term Investments (TTM) | J58: =D36 -> 43524
B59: [-] Total Debt (TTM) | J59: =D37 -> 9342
B60: [-] Noncontrolling Interests (TTM) | J60: =D38 -> 661
B61: Implied Equity Value | J61: =J57+J58-J59-J60 -> 246009.89 | M61: =J61/J62 -> 62.280985
B62: ÷ Current Common Shares Outstanding | J62: =D35 -> 3950
B64: 2. EV / EBITDA
B65: Peer 25th Pctl EV/EBITDA | E65: =M27 -> 9.8028671 | G65: =H34 -> 10760 | J65: =E65*G65 -> 105478.85 | M65: Implied Share Price | N65: Source: Tesla TTM EBITDA (sourced above)
B66: [+] Cash & Short-Term Investments (TTM) | J66: =D36 -> 43524
B67: [-] Total Debt (TTM) | J67: =D37 -> 9342
B68: [-] Noncontrolling Interests (TTM) | J68: =D38 -> 661
B69: Implied Equity Value | J69: =J65+J66-J67-J68 -> 138999.85 | M69: =J69/J70 -> 35.189835
B70: ÷ Current Common Shares Outstanding | J70: =D35 -> 3950
B72: Peer Median EV/EBITDA | E72: =M28 -> 13.044514 | G72: =H34 -> 10760 | J72: =E72*G72 -> 140358.97 | M72: Implied Share Price | N72: Source: Tesla TTM EBITDA (sourced above)
B73: [+] Cash & Short-Term Investments (TTM) | J73: =D36 -> 43524
B74: [-] Total Debt (TTM) | J74: =D37 -> 9342
B75: [-] Noncontrolling Interests (TTM) | J75: =D38 -> 661
B76: Implied Equity Value | J76: =J72+J73-J74-J75 -> 173879.97 | M76: =J76/J77 -> 44.020245
B77: ÷ Current Common Shares Outstanding | J77: =D35 -> 3950
B79: Peer 75th Pctl EV/EBITDA | E79: =M29 -> 17.83709 | G79: =H34 -> 10760 | J79: =E79*G79 -> 191927.09 | M79: Implied Share Price | N79: Source: Tesla TTM EBITDA (sourced above)
B80: [+] Cash & Short-Term Investments (TTM) | J80: =D36 -> 43524
B81: [-] Total Debt (TTM) | J81: =D37 -> 9342
B82: [-] Noncontrolling Interests (TTM) | J82: =D38 -> 661
B83: Implied Equity Value | J83: =J79+J80-J81-J82 -> 225448.09 | M83: =J83/J84 -> 57.075466
B84: ÷ Current Common Shares Outstanding | J84: =D35 -> 3950
B87: 3. P / E (direct to equity value -- no EV bridge)
B88: Peer 25th Pctl P/E | E88: =O27 -> 29.522746 | G88: =J34 -> 3806 | J88: =E88*G88 -> 112363.57 | M88: Implied Share Price | N88: Source: Tesla TTM Net Income to Common (sourced above)
B89: Implied Equity Value (= P/E x Net Income, no EV bridge)
B90: ÷ Current Common Shares Outstanding | J90: =D35 -> 3950 | M90: =J88/J90 -> 28.446473
B92: Peer Median P/E | E92: =O28 -> 33.419041 | G92: =J34 -> 3806 | J92: =E92*G92 -> 127192.87 | M92: Implied Share Price | N92: Source: Tesla TTM Net Income to Common (sourced above)
B93: Implied Equity Value (= P/E x Net Income, no EV bridge)
B94: ÷ Current Common Shares Outstanding | J94: =D35 -> 3950 | M94: =J92/J94 -> 32.200726
B96: Peer 75th Pctl P/E | E96: =O29 -> 37.315336 | G96: =J34 -> 3806 | J96: =E96*G96 -> 142022.17 | M96: Implied Share Price | N96: Source: Tesla TTM Net Income to Common (sourced above)
B97: Implied Equity Value (= P/E x Net Income, no EV bridge)
B98: ÷ Current Common Shares Outstanding | J98: =D35 -> 3950 | M98: =J96/J98 -> 35.95498
A100: COMBINED COMPARABLE COMPANY IMPLIED VALUATION RANGE
B101: Basis | E101: EV/Revenue-implied | H101: EV/EBITDA-implied | K101: P/E-implied | M101: Combined (avg. of 3)
B102: LOW (25th percentile) | E102: =M47 -> 27.178618 | H102: =M69 -> 35.189835 | K102: =M90 -> 28.446473 | M102: =AVERAGE(E102,H102,K102) -> 30.271642
B103: BASE (median) | E103: =M54 -> 34.129979 | H103: =M76 -> 44.020245 | K103: =M94 -> 32.200726 | M103: =AVERAGE(E103,H103,K103) -> 36.78365
B104: HIGH (75th percentile) | E104: =M61 -> 62.280985 | H104: =M83 -> 57.075466 | K104: =M98 -> 35.95498 | M104: =AVERAGE(E104,H104,K104) -> 51.770477

Sheet Precedent Transactions
A1: TESLA, INC. | E1: ◄ Cover | G1: PRECEDENT TRANSACTION ANALYSIS
A2: USD $ millions. Transaction values and dates sourced from official company announcements / press releases (cited per row). This methodology is explicitly a SECONDARY, qualitative cross-check for Tesla -- see the limitation note below.
A4: TRANSACTIONS
B5: Target | C5: Acquirer | D5: Announced | E5: Transaction Value ($M) | F5: Target LTM Revenue | G5: Target LTM EBITDA | H5: EV/Revenue | I5: EV/EBITDA | J5: Rationale / Relevance to Tesla
B6: Zoox, Inc. | C6: Amazon.com, Inc. | D6: Jun 26, 2020 | E6: 1200 | F6: N/A | G6: N/A | H6: =IF(OR(NOT(ISNUMBER(F6)),F6<=0),"N/A",E6/F6) -> N/A | I6: =IF(OR(NOT(ISNUMBER(G6)),G6<=0),"N/A",E6/G6) -> N/A | J6: Autonomous-vehicle / robotaxi technology developer -- directly relevant to Tesla's own Full Self-Driving and robotaxi ambitions; illustrates market-clearing prices for AV technology platforms.
B7: Cruise LLC (SoftBank Vision Fund's stake) | C7: General Motors Company | D7: Announced Nov 2021 / Closed Mar 2022 | E7: 2100 | F7: N/A | G7: N/A | H7: =IF(OR(NOT(ISNUMBER(F7)),F7<=0),"N/A",E7/F7) -> N/A | I7: =IF(OR(NOT(ISNUMBER(G7)),G7<=0),"N/A",E7/G7) -> N/A | J7: GM's purchase of SoftBank's ownership stake in its robotaxi/autonomous-mobility subsidiary Cruise -- a direct precedent for the market value assigned to an autonomous-mobility platform bundled inside a large automaker, structurally the closest analog to how the market might value Tesla's own FSD/robotaxi program.
B8: Lordstown Motors Corp. (Ohio manufacturing plant & equipment) | C8: Hon Hai Technology Group (Foxconn) | D8: May 11, 2022 | E8: 230 | F8: N/A | G8: N/A | H8: =IF(OR(NOT(ISNUMBER(F8)),F8<=0),"N/A",E8/F8) -> N/A | I8: =IF(OR(NOT(ISNUMBER(G8)),G8<=0),"N/A",E8/G8) -> N/A | J8: Sale of a purpose-built EV manufacturing plant by an early-stage EV startup -- a direct precedent for the value of dedicated EV production capacity/assets, relevant context for Tesla's own Gigafactory capital base.
B9: AKASOL AG | C9: BorgWarner Inc. | D9: Announced Dec 2021 / Completed Feb 2022 | E9: 882 | F9: N/A | G9: N/A | H9: =IF(OR(NOT(ISNUMBER(F9)),F9<=0),"N/A",E9/F9) -> N/A | I9: =IF(OR(NOT(ISNUMBER(G9)),G9<=0),"N/A",E9/G9) -> N/A | J9: Acquisition of a European commercial-vehicle EV battery-systems manufacturer. BorgWarner's announcement valued 100% of AKASOL equity at ~€727M; converted to ~US$882M using 15-Feb-2021 EUR/USD of 1.2132 for consistency with this sheet's USD $M presentation.
B10: Boston Dynamics | C10: Hyundai Motor Group (from SoftBank Group) | D10: Announced Dec 2020 / Closed Jun 2021 | E10: 1100 | F10: N/A | G10: N/A | H10: =IF(OR(NOT(ISNUMBER(F10)),F10<=0),"N/A",E10/F10) -> N/A | I10: =IF(OR(NOT(ISNUMBER(G10)),G10<=0),"N/A",E10/G10) -> N/A | J10: Acquisition of a leading advanced-robotics company by a global automaker -- the closest available precedent for how the market values a robotics platform bundled inside an automotive manufacturer, directly relevant to Tesla's own Optimus humanoid-robot program.
A11: SUMMARY STATISTICS
A12: All five transactions above show N/A for target LTM Revenue and LTM EBITDA (pre-scale / early-stage / privately-held targets with no reliably disclosed, comparable-period financials), so there are zero valid EV/Revenue or EV/EBITDA observations from which to compute Minimum / 25th Percentile / Median / 75th Percentile / Maximum. Per the assignment's own guidance, no valuation range is forced here. Precedent Transaction Analysis is NOT used to imply a Tesla valuation and is excluded from the weighted Valuation Summary on the Valuation sheet -- it is retained solely as qualitative, deal-value-in-context evidence.
D13: Minimum | E13: 25th Percentile | F13: Median | G13: 75th Percentile | H13: Maximum
B14: Deal Value ($M) | D14: =MIN(E6:E10) -> 230 | E14: 882 | F14: =MEDIAN(E6:E10) -> 1100 | G14: =QUARTILE(E6:E10,3) -> 1200 | H14: =MAX(E6:E10) -> 2100
A16: Deal-value range shown for context only (not an EV/Revenue or EV/EBITDA-based valuation range): these five deal values span roughly two orders of magnitude ($230M-$2,100M) reflecting very different target sizes and deal structures (asset sale vs. controlling-stake purchase vs. outright acquisition) -- they are not a Tesla enterprise-value range and should not be read as one.

Sheet Valuation
A1: TESLA, INC. | E1: ◄ Cover | G1: VALUATION — DCF, SENSITIVITY & SUMMARY
A2: USD millions except per-share and operating data
E3: Unit | G3: FY21A | H3: FY22A | I3: FY23A | J3: FY24A | K3: FY25A | L3: FY26E | M3: FY27E | N3: FY28E | O3: FY29E | P3: FY30E
A4: WACC | G4: INPUT SOURCE AND BASIS
C5: Risk-Free Rate (10-Yr US Treasury) | F5: =Assumptions!G58 -> 0.0477 | G5: Input — 10-year US Treasury constant-maturity yield at the valuation date. Source: see Sources & Notes.
C6: Beta (Levered) | F6: =Assumptions!G59 -> 1.85 | G6: Input — levered beta at the valuation date. Source: see Sources & Notes.
C7: Equity Risk Premium | F7: =Assumptions!G60 -> 0.0414 | G7: Input — mature-market equity risk premium at the valuation date. Source: see Sources & Notes.
C8: Cost of Equity (CAPM) | F8: =F5+F6*F7 -> 0.12429 | G8: Calculated — CAPM: risk-free rate + levered beta × equity risk premium.
C9: Pre-Tax Cost of Debt | F9: =Assumptions!G61 -> 0.05 | G9: Input — pre-tax cost of debt at the valuation date. Source: see Sources & Notes.
C10: Tax Rate (for Cost of Debt Tax Shield) | F10: =Assumptions!L49 -> 0.24 | G10: Link — normalised tax rate, Assumptions!L49.
C11: Post-Tax Cost of Debt | F11: =F9*(1-F10) -> 0.038 | G11: Calculated — pre-tax cost of debt × (1 − tax rate).
C12: Total Debt (Market Value Proxy) | F12: ='Loans & Other Income'!K8 -> 8376 | G12: Link — FY2025A closing total debt, Loans & Other Income!K8 (book value used as a market proxy).
C13: Equity Value (Market Cap = Price × Diluted Shares) | F13: =Assumptions!G57*Assumptions!G56 -> 1486661.5 | G13: Calculated — market capitalisation = Assumptions!G56 × Assumptions!G57 at the valuation date.
C14: Total Capital (Debt + Equity) | F14: =F12+F13 -> 1495037.5 | G14: Calculated — debt + equity at market values.
C15: Weight of Debt | F15: =F12/F14 -> 0.0056025351 | G15: Calculated — debt ÷ total capital.
C16: Weight of Equity | F16: =F13/F14 -> 0.99439746 | G16: Calculated — equity ÷ total capital.
C17: WACC | F17: =F15*F11+F16*F8 -> 0.12380656 | G17: Calculated — weight of debt × post-tax cost of debt + weight of equity × cost of equity.
C18: Terminal Growth Rate | F18: =Assumptions!G62 -> 0.038 | G18: Link — terminal growth rate, Assumptions!G62.
A21: FREE CASH FLOW TO THE FIRM (FCFF)
C22: EBIT | L22: =IS!L25 -> 6928.2478 | M22: =IS!M25 -> 9279.6903 | N22: =IS!N25 -> 13063.029 | O22: =IS!O25 -> 17020.075 | P22: =IS!P25 -> 20564.31
C23: [-] Tax on EBIT (at Assumptions tax rate) | L23: =L22*Assumptions!L49 -> 1662.7795 | M23: =M22*Assumptions!M49 -> 2227.1257 | N23: =N22*Assumptions!N49 -> 3135.127 | O23: =O22*Assumptions!O49 -> 4084.8179 | P23: =P22*Assumptions!P49 -> 4935.4344
C24: NOPAT = EBIT × (1 − Tax Rate) | L24: =L22-L23 -> 5265.4684 | M24: =M22-M23 -> 7052.5646 | N24: =N22-N23 -> 9927.9021 | O24: =O22-O23 -> 12935.257 | P24: =P22-P23 -> 15628.876
C25: [+] Depreciation & Amortization | L25: =IS!L28 -> 6706.095 | M25: =IS!M28 -> 7059.4141 | N25: =IS!N28 -> 7410.7222 | O25: =IS!O28 -> 7803.5101 | P25: =IS!P28 -> 8484.3257
C26: [-] Capital Expenditure | L26: ='Asset Schedule'!L6 -> 10184.433 | M26: ='Asset Schedule'!M6 -> 10749.187 | N26: ='Asset Schedule'!N6 -> 11623.012 | O26: ='Asset Schedule'!O6 -> 12342.281 | P26: ='Asset Schedule'!P6 -> 12912.657
C27: [-] Increase in Net Working Capital | L27: =(BS!L6+BS!L7+(BS!L8*($F$30/($F$29+$F$30)))-BS!L17-BS!L18-BS!L19)-(BS!K6+BS!K7+$F$30-BS!K17-BS!K18-BS!K19) -> 524.39313 | M27: =(BS!M6+BS!M7+(BS!M8*($F$30/($F$29+$F$30)))-BS!M17-BS!M18-BS!M19)-(BS!L6+BS!L7+(BS!L8*($F$30/($F$29+$F$30)))-BS!L17-BS!L18-BS!L19) -> -770.03585 | N27: =(BS!N6+BS!N7+(BS!N8*($F$30/($F$29+$F$30)))-BS!N17-BS!N18-BS!N19)-(BS!M6+BS!M7+(BS!M8*($F$30/($F$29+$F$30)))-BS!M17-BS!M18-BS!M19) -> -479.46397 | O27: =(BS!O6+BS!O7+(BS!O8*($F$30/($F$29+$F$30)))-BS!O17-BS!O18-BS!O19)-(BS!N6+BS!N7+(BS!N8*($F$30/($F$29+$F$30)))-BS!N17-BS!N18-BS!N19) -> -1034.884 | P27: =(BS!P6+BS!P7+(BS!P8*($F$30/($F$29+$F$30)))-BS!P17-BS!P18-BS!P19)-(BS!O6+BS!O7+(BS!O8*($F$30/($F$29+$F$30)))-BS!O17-BS!O18-BS!O19) -> 385.54438
C28: FREE CASH FLOW TO THE FIRM (FCFF) | L28: =L24+L25-L26-L27 -> 1262.7372 | M28: =M24+M25-M26-M27 -> 4132.8277 | N28: =N24+N25-N26-N27 -> 6195.0764 | O28: =O24+O25-O26-O27 -> 9431.3702 | P28: =P24+P25-P26-P27 -> 10815
C29: Memo: FY2025A Actual Short-Term Investments (10-K Balance Sheet, $M) - excluded from operating NWC | F29: 27546
C30: Memo: FY2025A Actual Prepaid Expenses & Other Current Assets (10-K Balance Sheet, $M) - the operating portion of BS row 13 | F30: 7615
A32: TERMINAL VALUATION
C33: FY2030E Free Cash Flow to the Firm (FCFF) | F33: =P28 -> 10815
C34: Terminal Growth Rate | F34: =F18 -> 0.038
C35: WACC | F35: =F17 -> 0.12380656
C36: Terminal FCFF = FY2030E FCFF × (1 + Terminal Growth Rate) | F36: =F33*(1+F34) -> 11225.97
C37: TERMINAL VALUE = Terminal FCFF ÷ (WACC − Terminal Growth Rate) | F37: =F36/(F35-F34) -> 130828.81
A39: DISCOUNTING
C40: Discount Period (Years) | L40: 1 | M40: =L40+1 -> 2 | N40: =M40+1 -> 3 | O40: =N40+1 -> 4 | P40: =O40+1 -> 5
C41: Discount Factor | L41: =1/(1+$F$17)^L40 -> 0.88983286 | M41: =1/(1+$F$17)^M40 -> 0.79180251 | N41: =1/(1+$F$17)^N40 -> 0.70457189 | O41: =1/(1+$F$17)^O40 -> 0.62695122 | P41: =1/(1+$F$17)^P40 -> 0.5578818
A43: ENTERPRISE VALUE
C44: PV of Forecast FCFF | L44: =L28*L41 -> 1123.625 | M44: =M28*M41 -> 3272.3834 | N44: =N28*N41 -> 4364.8767 | O44: =O28*O41 -> 5913.0091 | P44: =P28*P41 -> 6033.4916
C45: [+] PV of Terminal Value | K45: =F37*P41 -> 72987.012
C46: ENTERPRISE VALUE | K46: =SUM(L44:P44,K45) -> 93694.398
C47: Terminal Value as % of Enterprise Value (memo) | K47: =K45/K46 -> 0.77899014
A48: ENTERPRISE VALUE TO EQUITY VALUE BRIDGE
C49: [+] Cash & Short-Term Investments (FY2025A) | K49: 44059
C50: [-] Total Debt (FY2025A) | K50: ='Loans & Other Income'!K8 -> 8376
C51: [-] Noncontrolling Interests (FY2025A) | K51: =BS!K32 -> 728
C52: EQUITY VALUE | K52: =K46+K49-K50-K51 -> 128649.4
A54: IMPLIED VALUE PER SHARE
C55: Common Shares Outstanding (Current) | K55: =Assumptions!G57 -> 3950
C56: Implied Value per Share | K56: =K52/K55 -> 32.569468
C57: Current Share Price (valuation date) | K57: =Assumptions!G56 -> 376.37
C58: Implied Upside / (Downside) | K58: =K56/K57-1 -> -0.91346423
C59: Single market-price source: Assumptions!G56 ($376.37, 3 September 2026 close). It drives the WACC market-value weights, the Comparable Companies market capitalisation, the valuation summary and the football field.
A60: SENSITIVITY ANALYSIS
A61: WACC × Terminal Growth Rate sensitivity — identical WACC and TGR ranges in both tables; base case (WACC = F17, TGR = F18) highlighted in Tesla red.
C62: ON ENTERPRISE VALUE ($M)
J63: WACC ↓ | L63: TERMINAL GROWTH RATE →
K64: =K46 -> 93694.398 | L64: =$F$18-0.01 -> 0.028 | M64: =$F$18-0.005 -> 0.033 | N64: =$F$18 -> 0.038 | O64: =$F$18+0.005 -> 0.043 | P64: =$F$18+0.01 -> 0.048
C65: READING THE SENSITIVITY | K65: =$F$17-0.02 -> 0.10380656 | L65: =(L$28/(1+$K65)^L$40+M$28/(1+$K65)^M$40+N$28/(1+$K65)^N$40+O$28/(1+$K65)^O$40+P$28/(1+$K65)^P$40+(P$28*(1+L$64)/($K65-L$64))/(1+$K65)^P$40) -> 111601.26 | M65: =(L$28/(1+$K65)^L$40+M$28/(1+$K65)^M$40+N$28/(1+$K65)^N$40+O$28/(1+$K65)^O$40+P$28/(1+$K65)^P$40+(P$28*(1+M$64)/($K65-M$64))/(1+$K65)^P$40) -> 118387.74 | N65: =(L$28/(1+$K65)^L$40+M$28/(1+$K65)^M$40+N$28/(1+$K65)^N$40+O$28/(1+$K65)^O$40+P$28/(1+$K65)^P$40+(P$28*(1+N$64)/($K65-N$64))/(1+$K65)^P$40) -> 126205.49 | O65: =(L$28/(1+$K65)^L$40+M$28/(1+$K65)^M$40+N$28/(1+$K65)^N$40+O$28/(1+$K65)^O$40+P$28/(1+$K65)^P$40+(P$28*(1+O$64)/($K65-O$64))/(1+$K65)^P$40) -> 135308.92 | P65: =(L$28/(1+$K65)^L$40+M$28/(1+$K65)^M$40+N$28/(1+$K65)^N$40+O$28/(1+$K65)^O$40+P$28/(1+$K65)^P$40+(P$28*(1+P$64)/($K65-P$64))/(1+$K65)^P$40) -> 146043.6
C66: Base case — WACC × terminal growth | F66: =K56 -> 32.569468 | K66: =$F$17-0.01 -> 0.11380656 | L66: =(L$28/(1+$K66)^L$40+M$28/(1+$K66)^M$40+N$28/(1+$K66)^N$40+O$28/(1+$K66)^O$40+P$28/(1+$K66)^P$40+(P$28*(1+L$64)/($K66-L$64))/(1+$K66)^P$40) -> 96973.667 | M66: =(L$28/(1+$K66)^L$40+M$28/(1+$K66)^M$40+N$28/(1+$K66)^N$40+O$28/(1+$K66)^O$40+P$28/(1+$K66)^P$40+(P$28*(1+M$64)/($K66-M$64))/(1+$K66)^P$40) -> 102041.13 | N66: =(L$28/(1+$K66)^L$40+M$28/(1+$K66)^M$40+N$28/(1+$K66)^N$40+O$28/(1+$K66)^O$40+P$28/(1+$K66)^P$40+(P$28*(1+N$64)/($K66-N$64))/(1+$K66)^P$40) -> 107777.06 | O66: =(L$28/(1+$K66)^L$40+M$28/(1+$K66)^M$40+N$28/(1+$K66)^N$40+O$28/(1+$K66)^O$40+P$28/(1+$K66)^P$40+(P$28*(1+O$64)/($K66-O$64))/(1+$K66)^P$40) -> 114323.08 | P66: =(L$28/(1+$K66)^L$40+M$28/(1+$K66)^M$40+N$28/(1+$K66)^N$40+O$28/(1+$K66)^O$40+P$28/(1+$K66)^P$40+(P$28*(1+P$64)/($K66-P$64))/(1+$K66)^P$40) -> 121863.83
C67: Low end of the sensitivity range | F67: =MIN(L74:P78) -> 26.184574 | K67: =$F$17 -> 0.12380656 | L67: =(L$28/(1+$K67)^L$40+M$28/(1+$K67)^M$40+N$28/(1+$K67)^N$40+O$28/(1+$K67)^O$40+P$28/(1+$K67)^P$40+(P$28*(1+L$64)/($K67-L$64))/(1+$K67)^P$40) -> 85446.476 | M67: =(L$28/(1+$K67)^L$40+M$28/(1+$K67)^M$40+N$28/(1+$K67)^N$40+O$28/(1+$K67)^O$40+P$28/(1+$K67)^P$40+(P$28*(1+M$64)/($K67-M$64))/(1+$K67)^P$40) -> 89343.363 | N67: =(L$28/(1+$K67)^L$40+M$28/(1+$K67)^M$40+N$28/(1+$K67)^N$40+O$28/(1+$K67)^O$40+P$28/(1+$K67)^P$40+(P$28*(1+N$64)/($K67-N$64))/(1+$K67)^P$40) -> 93694.398 | O67: =(L$28/(1+$K67)^L$40+M$28/(1+$K67)^M$40+N$28/(1+$K67)^N$40+O$28/(1+$K67)^O$40+P$28/(1+$K67)^P$40+(P$28*(1+O$64)/($K67-O$64))/(1+$K67)^P$40) -> 98583.884 | P67: =(L$28/(1+$K67)^L$40+M$28/(1+$K67)^M$40+N$28/(1+$K67)^N$40+O$28/(1+$K67)^O$40+P$28/(1+$K67)^P$40+(P$28*(1+P$64)/($K67-P$64))/(1+$K67)^P$40) -> 104118.36
C68: High end of the sensitivity range | F68: =MAX(L74:P78) -> 45.82243 | K68: =$F$17+0.01 -> 0.13380656 | L68: =(L$28/(1+$K68)^L$40+M$28/(1+$K68)^M$40+N$28/(1+$K68)^N$40+O$28/(1+$K68)^O$40+P$28/(1+$K68)^P$40+(P$28*(1+L$64)/($K68-L$64))/(1+$K68)^P$40) -> 76138.791 | M68: =(L$28/(1+$K68)^L$40+M$28/(1+$K68)^M$40+N$28/(1+$K68)^N$40+O$28/(1+$K68)^O$40+P$28/(1+$K68)^P$40+(P$28*(1+M$64)/($K68-M$64))/(1+$K68)^P$40) -> 79206.677 | N68: =(L$28/(1+$K68)^L$40+M$28/(1+$K68)^M$40+N$28/(1+$K68)^N$40+O$28/(1+$K68)^O$40+P$28/(1+$K68)^P$40+(P$28*(1+N$64)/($K68-N$64))/(1+$K68)^P$40) -> 82594.781 | O68: =(L$28/(1+$K68)^L$40+M$28/(1+$K68)^M$40+N$28/(1+$K68)^N$40+O$28/(1+$K68)^O$40+P$28/(1+$K68)^P$40+(P$28*(1+O$64)/($K68-O$64))/(1+$K68)^P$40) -> 86355.996 | P68: =(L$28/(1+$K68)^L$40+M$28/(1+$K68)^M$40+N$28/(1+$K68)^N$40+O$28/(1+$K68)^O$40+P$28/(1+$K68)^P$40+(P$28*(1+P$64)/($K68-P$64))/(1+$K68)^P$40) -> 90555.548
C69: High end vs. current market price | F69: =MAX(L74:P78)/G87-1 -> -0.87825164 | K69: =$F$17+0.02 -> 0.14380656 | L69: =(L$28/(1+$K69)^L$40+M$28/(1+$K69)^M$40+N$28/(1+$K69)^N$40+O$28/(1+$K69)^O$40+P$28/(1+$K69)^P$40+(P$28*(1+L$64)/($K69-L$64))/(1+$K69)^P$40) -> 68474.068 | M69: =(L$28/(1+$K69)^L$40+M$28/(1+$K69)^M$40+N$28/(1+$K69)^N$40+O$28/(1+$K69)^O$40+P$28/(1+$K69)^P$40+(P$28*(1+M$64)/($K69-M$64))/(1+$K69)^P$40) -> 70936.065 | N69: =(L$28/(1+$K69)^L$40+M$28/(1+$K69)^M$40+N$28/(1+$K69)^N$40+O$28/(1+$K69)^O$40+P$28/(1+$K69)^P$40+(P$28*(1+N$64)/($K69-N$64))/(1+$K69)^P$40) -> 73630.751 | O69: =(L$28/(1+$K69)^L$40+M$28/(1+$K69)^M$40+N$28/(1+$K69)^N$40+O$28/(1+$K69)^O$40+P$28/(1+$K69)^P$40+(P$28*(1+O$64)/($K69-O$64))/(1+$K69)^P$40) -> 76592.75 | P69: =(L$28/(1+$K69)^L$40+M$28/(1+$K69)^M$40+N$28/(1+$K69)^N$40+O$28/(1+$K69)^O$40+P$28/(1+$K69)^P$40+(P$28*(1+P$64)/($K69-P$64))/(1+$K69)^P$40) -> 79863.913
C71: ON SHARE PRICE ($/share)
J72: WACC ↓ | L72: TERMINAL GROWTH RATE →
C73: READING THE DIRECTION | K73: =K56 -> 32.569468 | L73: =L64 -> 0.028 | M73: =M64 -> 0.033 | N73: =N64 -> 0.038 | O73: =O64 -> 0.043 | P73: =P64 -> 0.048
C74: Higher WACC | F74: ↓ lower present value of every cash flow | K74: =K65 -> 0.10380656 | L74: =(L65+$K$49-$K$50-$K$51)/$K$55 -> 37.102851 | M74: =(M65+$K$49-$K$50-$K$51)/$K$55 -> 38.820946 | N74: =(N65+$K$49-$K$50-$K$51)/$K$55 -> 40.800125 | O74: =(O65+$K$49-$K$50-$K$51)/$K$55 -> 43.10479 | P74: =(P65+$K$49-$K$50-$K$51)/$K$55 -> 45.82243
C75: Higher terminal growth | F75: ↑ higher terminal value, which is 73% of EV | K75: =K66 -> 0.11380656 | L75: =(L66+$K$49-$K$50-$K$51)/$K$55 -> 33.399663 | M75: =(M66+$K$49-$K$50-$K$51)/$K$55 -> 34.682564 | N75: =(N66+$K$49-$K$50-$K$51)/$K$55 -> 36.134699 | O75: =(O66+$K$49-$K$50-$K$51)/$K$55 -> 37.791919 | P75: =(P66+$K$49-$K$50-$K$51)/$K$55 -> 39.70097
K76: =K67 -> 0.12380656 | L76: =(L67+$K$49-$K$50-$K$51)/$K$55 -> 30.481386 | M76: =(M67+$K$49-$K$50-$K$51)/$K$55 -> 31.46794 | N76: =(N67+$K$49-$K$50-$K$51)/$K$55 -> 32.569468 | O76: =(O67+$K$49-$K$50-$K$51)/$K$55 -> 33.807312 | P76: =(P67+$K$49-$K$50-$K$51)/$K$55 -> 35.208447
C77: Across the whole WACC × terminal-growth grid the implied share price stays far below the market price, so the valuation conclusion does not depend on any single discount-rate or terminal-growth choice. | K77: =K68 -> 0.13380656 | L77: =(L68+$K$49-$K$50-$K$51)/$K$55 -> 28.12501 | M77: =(M68+$K$49-$K$50-$K$51)/$K$55 -> 28.90169 | N77: =(N68+$K$49-$K$50-$K$51)/$K$55 -> 29.759438 | O77: =(O68+$K$49-$K$50-$K$51)/$K$55 -> 30.711645 | P77: =(P68+$K$49-$K$50-$K$51)/$K$55 -> 31.774822
K78: =K69 -> 0.14380656 | L78: =(L69+$K$49-$K$50-$K$51)/$K$55 -> 26.184574 | M78: =(M69+$K$49-$K$50-$K$51)/$K$55 -> 26.807865 | N78: =(N69+$K$49-$K$50-$K$51)/$K$55 -> 27.490064 | O78: =(O69+$K$49-$K$50-$K$51)/$K$55 -> 28.239937 | P78: =(P69+$K$49-$K$50-$K$51)/$K$55 -> 29.068079
A81: VALUATION SUMMARY
B83: Method | E83: Low | G83: Base / Mid | I83: High | K83: Implied Share Price Range
B84: 1. Discounted Cash Flow (DCF) | E84: =MIN(L74:P78) -> 26.184574 | G84: =K56 -> 32.569468 | I84: =MAX(L74:P78) -> 45.82243 | K84: =TEXT(E84,"$0.00")&" - "&TEXT(I84,"$0.00") -> $26.18 - $45.82
B85: 2. Comparable Company Analysis | E85: ='Comparable Companies'!M102 -> 30.271642 | G85: ='Comparable Companies'!M103 -> 36.78365 | I85: ='Comparable Companies'!M104 -> 51.770477 | K85: =TEXT(E85,"$0.00")&" - "&TEXT(I85,"$0.00") -> $30.27 - $51.77
B86: 3. Precedent Transaction Analysis | E86: N/A | G86: N/A | I86: N/A | K86: Secondary cross-check — limited direct comparability
B87: 4. Current Tesla Market Price | E87: ='Comparable Companies'!D34 -> 376.37 | G87: ='Comparable Companies'!D34 -> 376.37 | I87: ='Comparable Companies'!D34 -> 376.37 | K87: =TEXT(G87,"$0.00") -> $376.37
B89: FOOTBALL-FIELD CHART SOURCE — live links, feeds the Model Summary chart (do not overwrite)
B90: Method | C90: Base (invisible) | D90: Low → Base | E90: Base marker | F90: Base → High | H90: Marker half-width | I90: 0.4
B91: DCF | C91: =E84 -> 26.184574 | D91: =MAX(0,G84-E84-$I$90) -> 5.9848936 | E91: =$I$90*2 -> 0.8 | F91: =MAX(0,I84-G84-$I$90) -> 12.852962
B92: Comparable Companies | C92: =E85 -> 30.271642 | D92: =MAX(0,G85-E85-$I$90) -> 6.1120078 | E92: =$I$90*2 -> 0.8 | F92: =MAX(0,I85-G85-$I$90) -> 14.586827
B93: Current Market Price | C93: 0 | D93: =G87 -> 376.37 | E93: 0 | F93: 0
B94: Bars are drawn on a 0–60 $/share axis so the DCF and comparable ranges keep full resolution; the market-price bar therefore runs off the plot area and is labelled as an off-scale reference.
A96: SUPPLEMENTARY CROSS-CHECKS — NOT THE PRIMARY VALUATION METHODOLOGY
C97: Both cross-checks below are diagnostics. The Gordon Growth DCF above remains the primary methodology and no averaging of the two is performed.
C98: A. EXIT-MULTIPLE TERMINAL VALUE CROSS-CHECK
C99: Exit multiple applied to FY2030E EBITDA | E99: Peer 25th pctl | G99: Peer median | I99: Peer 75th pctl
C100: FY2030E EBITDA | E100: =IS!$P$29 -> 29048.636 | G100: =IS!$P$29 -> 29048.636 | I100: =IS!$P$29 -> 29048.636
C101: Peer EV / EBITDA multiple | E101: ='Comparable Companies'!M27 -> 9.8028671 | G101: ='Comparable Companies'!M28 -> 13.044514 | I101: ='Comparable Companies'!M29 -> 17.83709
C102: Terminal enterprise value | E102: =E100*E101 -> 284759.92 | G102: =G100*G101 -> 378925.33 | I102: =I100*I101 -> 518143.13
C103: × Discount factor, FY2030E | E103: =$P$41 -> 0.5578818 | G103: =$P$41 -> 0.5578818 | I103: =$P$41 -> 0.5578818
C104: PV of terminal value | E104: =E102*E103 -> 158862.37 | G104: =G102*G103 -> 211395.54 | I104: =I102*I103 -> 289062.62
C105: [+] PV of explicit FCFF, FY2026E–FY2030E | E105: =SUM($L$44:$P$44) -> 20707.386 | G105: =SUM($L$44:$P$44) -> 20707.386 | I105: =SUM($L$44:$P$44) -> 20707.386
C106: ENTERPRISE VALUE | E106: =E104+E105 -> 179569.76 | G106: =G104+G105 -> 232102.93 | I106: =I104+I105 -> 309770.01
C107: EQUITY VALUE | E107: =E106+$K$49-$K$50-$K$51 -> 214524.76 | G107: =G106+$K$49-$K$50-$K$51 -> 267057.93 | I107: =I106+$K$49-$K$50-$K$51 -> 344725.01
C108: IMPLIED VALUE PER SHARE | E108: =E107/$K$55 -> 54.310066 | G108: =G107/$K$55 -> 67.609602 | I108: =I107/$K$55 -> 87.272154
C109: Memo — Gordon Growth implied value per share (primary methodology) | G109: =$K$56 -> 32.569468
C110: Memo — perpetuity growth rate embedded in the peer-median exit multiple | G110: =(G102*$F$17-$P$28)/(G102+$P$28) -> 0.092621774
C111: ="The peer-median exit multiple implies a perpetuity growth rate of "&TEXT(G110,"0.0%")&" — far above the "&TEXT($F$18,"0.0%")&_xlfn._LONGTEXT(" terminal growth rate used in the primary DCF and above any defensible long-run nominal growth rate. A trading multiple capitalises current market expectations, so applying one at the end of the forecast re-imports those expectations into the terminal val","ue. That is precisely why Gordon Growth is retained as the primary method and the two results are reported separately rather than averaged.") -> The peer-median exit multiple implies a perpetuity growth rate of 9.3% — far above the 3.8% terminal growth rate used in the primary DCF and above any defensible long-run nominal growth rate. A trading multiple capitalises current market expectations, so applying one at the end of the forecast re-imports those expectations into the terminal value. That is precisely why Gordon Growth is retained as the primary method and the two results are reported separately rather than averaged.
C113: B. BETA AND CAPITAL-STRUCTURE CROSS-CHECK
...

Sheet Scenario Analysis
A1: TESLA, INC. | E1: ◄ Cover | G1: SCENARIO ANALYSIS — BEAR / BASE / BULL
A2: USD millions except per-share and operating data · One integrated model: the case selected on Assumptions drives the live statements; the three build-outs below are calculated in parallel from the same driver grids
A4: SCENARIO OUTPUT SUMMARY
C5: Metric | E5: Unit | G5: ="Bear"&IF(Assumptions!$L$2=1," ◄ SELECTED","") -> Bear | I5: ="Base"&IF(Assumptions!$L$2=2," ◄ SELECTED","") -> Base ◄ SELECTED | K5: ="Bull"&IF(Assumptions!$L$2=3," ◄ SELECTED","") -> Bull
C6: FY2030E Revenue | E6: $M | G6: =P32 -> 113105.54 | I6: =P70 -> 161408.21 | K6: =P108 -> 206513.16
C7: FY2025A–FY2030E Revenue CAGR | E7: % | G7: =(P32/K32)^(1/5)-1 -> 0.035882209 | I7: =(P70/K70)^(1/5)-1 -> 0.11224055 | K7: =(P108/K108)^(1/5)-1 -> 0.1684312
C8: FY2030E EBITDA | E8: $M | G8: =P44 -> 14722.576 | I8: =P82 -> 29048.636 | K8: =P120 -> 44126.508
C9: FY2030E EBITDA Margin | E9: % | G9: =P44/P32 -> 0.1301667 | I9: =P82/P70 -> 0.17997 | K9: =P120/P108 -> 0.21367407
C10: FY2030E EBIT | E10: $M | G10: =P39 -> 6807.7837 | I10: =P77 -> 20564.31 | K10: =P115 -> 35125.317
C11: FY2030E EBIT Margin | E11: % | G11: =P39/P32 -> 0.060189657 | I11: =P77/P70 -> 0.1274056 | K11: =P115/P108 -> 0.17008755
C12: FY2030E Net Income | E12: $M | G12: =P50 -> 5946.4147 | I12: =P88 -> 16401.375 | K12: =P126 -> 27467.74
C13: FY2030E Free Cash Flow to the Firm | E13: $M | G13: =P48 -> 2369.8931 | I13: =P86 -> 10815 | K13: =P124 -> 20083.529
C14: Enterprise Value | E14: $M | G14: =K57 -> 16863.276 | I14: =K95 -> 93694.398 | K14: =K133 -> 176169.41
C15: Equity Value | E15: $M | G15: =K58 -> 51818.276 | I15: =K96 -> 128649.4 | K15: =K134 -> 211124.41
C16: DCF Implied Value / Share | E16: $/share | G16: =K59 -> 13.118551 | I16: =K97 -> 32.569468 | K16: =K135 -> 53.449218
C17: Upside / (Downside) vs Market Price | E17: % | G17: =K59/Assumptions!$G$56-1 -> -0.96514454 | I17: =K97/Assumptions!$G$56-1 -> -0.91346423 | K17: =K135/Assumptions!$G$56-1 -> -0.85798757
C19: Base column reconciles to the live model | I19: =IF(Assumptions!$L$2<>2,"set selector to 2 to test",IF(ABS(I16-Valuation!K56)<0.01,"PASS","FAIL")) -> PASS
C20: The Base column is calculated independently of the selector, so it can be reconciled against the live three-statement model whenever the selector is set to Base. Net interest is common to all three cases (debt is held flat, so interest expense is identical); interest income follows the live financing schedule, which is why Net Income — and only Net Income — carries a small case-independent element. Revenue, EBITDA, EBIT, FCFF and every valuation output are fully case-specific.
A23: BEAR CASE — OPERATING BUILD, FCFF AND DCF
K24: ='Revenue Build-up'!K3 -> FY25A | L24: ='Revenue Build-up'!L3 -> FY26E | M24: ='Revenue Build-up'!M3 -> FY27E | N24: ='Revenue Build-up'!N3 -> FY28E | O24: ='Revenue Build-up'!O3 -> FY29E | P24: ='Revenue Build-up'!P3 -> FY30E
C25: Vehicle Deliveries | E25: units | K25: ='Revenue Build-up'!K5 -> 1636129 | L25: =K25*(1+Assumptions!L68) -> 1636129 | M25: =L25*(1+Assumptions!M68) -> 1685212.9 | N25: =M25*(1+Assumptions!N68) -> 1769473.5 | O25: =N25*(1+Assumptions!O68) -> 1857947.2 | P25: =O25*(1+Assumptions!P68) -> 1932265.1
C26: Automotive Revenue per Delivery | E26: $/unit | K26: ='Revenue Build-up'!K6 -> 41276.085 | L26: =K26*(1+Assumptions!L71) -> 38799.52 | M26: =L26*(1+Assumptions!M71) -> 37247.539 | N26: =M26*(1+Assumptions!N71) -> 36502.588 | O26: =N26*(1+Assumptions!O71) -> 36502.588 | P26: =O26*(1+Assumptions!P71) -> 36502.588
C27: Automotive Sales & Leasing Revenue | E27: $M | L27: =L25*L26/1000000 -> 63481.02 | M27: =M25*M26/1000000 -> 62770.033 | N27: =N25*N26/1000000 -> 64590.364 | O27: =O25*O26/1000000 -> 67819.882 | P27: =P25*P26/1000000 -> 70532.677
C28: [+] Automotive Regulatory Credits | E28: $M | K28: ='Revenue Build-up'!K8 -> 1993 | L28: =K28*(1+Assumptions!L74) -> 1195.8 | M28: =L28*(1+Assumptions!M74) -> 777.27 | N28: =M28*(1+Assumptions!N74) -> 582.9525 | O28: =N28*(1+Assumptions!O74) -> 466.362 | P28: =O28*(1+Assumptions!P74) -> 373.0896
C29: Total Automotive Revenue | E29: $M | L29: =L27+L28 -> 64676.82 | M29: =M27+M28 -> 63547.303 | N29: =N27+N28 -> 65173.316 | O29: =O27+O28 -> 68286.244 | P29: =P27+P28 -> 70905.767
C30: Energy Generation & Storage Revenue | E30: $M | K30: ='Revenue Build-up'!K12 -> 12771 | L30: =K30*(1+Assumptions!L80) -> 15325.2 | M30: =L30*(1+Assumptions!M80) -> 17623.98 | N30: =M30*(1+Assumptions!N80) -> 19738.858 | O30: =N30*(1+Assumptions!O80) -> 21712.743 | P30: =O30*(1+Assumptions!P80) -> 23449.763
C31: Services & Other Revenue | E31: $M | K31: ='Revenue Build-up'!K15 -> 12530 | L31: =K31*(1+Assumptions!L86) -> 13783 | M31: =L31*(1+Assumptions!M86) -> 15023.47 | N31: =M31*(1+Assumptions!N86) -> 16225.348 | O31: =N31*(1+Assumptions!O86) -> 17523.375 | P31: =O31*(1+Assumptions!P86) -> 18750.012
C32: TOTAL REVENUE | E32: $M | K32: ='Revenue Build-up'!K18 -> 94827 | L32: =L29+L30+L31 -> 93785.02 | M32: =M29+M30+M31 -> 96194.753 | N32: =N29+N30+N31 -> 101137.52 | O32: =O29+O30+O31 -> 107522.36 | P32: =P29+P30+P31 -> 113105.54
C33: Automotive Gross Profit | E33: $M | L33: =L29*Assumptions!L77 -> 10671.675 | M33: =M29*Assumptions!M77 -> 10803.041 | N33: =N29*Assumptions!N77 -> 11405.33 | O33: =O29*Assumptions!O77 -> 12291.524 | P33: =P29*Assumptions!P77 -> 13117.567
C34: Energy Gross Profit | E34: $M | L34: =L30*Assumptions!L83 -> 3984.552 | M34: =M30*Assumptions!M83 -> 4582.2348 | N34: =N30*Assumptions!N83 -> 5329.4916 | O34: =O30*Assumptions!O83 -> 5862.4407 | P34: =P30*Assumptions!P83 -> 6331.436
C35: Services Gross Profit | E35: $M | L35: =L31*Assumptions!L89 -> 1240.47 | M35: =M31*Assumptions!M89 -> 1427.2297 | N35: =N31*Assumptions!N89 -> 1622.5348 | O35: =O31*Assumptions!O89 -> 1839.9544 | P35: =P31*Assumptions!P89 -> 2062.5013
C36: GROSS PROFIT | E36: $M | L36: =SUM(L33:L35) -> 15896.697 | M36: =SUM(M33:M35) -> 16812.506 | N36: =SUM(N33:N35) -> 18357.357 | O36: =SUM(O33:O35) -> 19993.919 | P36: =SUM(P33:P35) -> 21511.504
C37: [-] Research & Development | E37: $M | L37: =L32*Assumptions!L92 -> 7033.8765 | M37: =M32*Assumptions!M92 -> 7214.6064 | N37: =N32*Assumptions!N92 -> 7585.3141 | O37: =O32*Assumptions!O92 -> 7741.6101 | P37: =P32*Assumptions!P92 -> 7917.3879
C38: [-] Selling, General & Administrative | E38: $M | L38: =L32*Assumptions!L95 -> 6096.0263 | M38: =M32*Assumptions!M95 -> 6156.4642 | N38: =N32*Assumptions!N95 -> 6371.6638 | O38: =O32*Assumptions!O95 -> 6666.3865 | P38: =P32*Assumptions!P95 -> 6786.3325
C39: EBIT (Operating Income) | E39: $M | L39: =L36-L37-L38 -> 2766.7945 | M39: =M36-M37-M38 -> 3441.4353 | N39: =N36-N37-N38 -> 4400.3787 | O39: =O36-O37-O38 -> 5585.9224 | P39: =P36-P37-P38 -> 6807.7837
C40: Opening Net PP&E | E40: $M | L40: =K43 -> 40643 | M40: =L43 -> 44253.257 | N40: =M43 -> 47273.185 | O40: =N43 -> 50059.594 | P40: =O43 -> 52765.279
C41: [-] Depreciation & Amortisation | E41: $M | L41: =L40*Assumptions!L42 -> 6706.095 | M41: =M40*Assumptions!M42 -> 7080.5212 | N41: =N40*Assumptions!N42 -> 7327.3437 | O41: =O40*Assumptions!O42 -> 7508.939 | P41: =P40*Assumptions!P42 -> 7914.7918
C42: [+] Capital Expenditure | E42: $M | L42: =L32*Assumptions!L98 -> 10316.352 | M42: =M32*Assumptions!M98 -> 10100.449 | N42: =N32*Assumptions!N98 -> 10113.752 | O42: =O32*Assumptions!O98 -> 10214.624 | P42: =P32*Assumptions!P98 -> 10179.499
C43: Closing Net PP&E | E43: $M | K43: ='Asset Schedule'!K9 -> 40643 | L43: =L40-L41+L42 -> 44253.257 | M43: =M40-M41+M42 -> 47273.185 | N43: =N40-N41+N42 -> 50059.594 | O43: =O40-O41+O42 -> 52765.279 | P43: =P40-P41+P42 -> 55029.986
C44: EBITDA | E44: $M | L44: =L39+L41 -> 9472.8895 | M44: =M39+M41 -> 10521.956 | N44: =N39+N41 -> 11727.722 | O44: =O39+O41 -> 13094.861 | P44: =P39+P41 -> 14722.576
C45: Net Working Capital (DCF definition) | E45: $M | K45: =BS!K6+BS!K7+Valuation!$F$30-BS!K17-BS!K18-BS!K19 -> -5491 | L45: =L32/365*Assumptions!L29+(L32-L36)/365*Assumptions!L30+L32*Assumptions!L32*(Valuation!$F$30/(Valuation!$F$29+Valuation!$F$30))-(L32-L36)/365*Assumptions!L31-L32*Assumptions!L33-L32*Assumptions!L34 -> -4624.8893 | M45: =M32/365*Assumptions!M29+(M32-M36)/365*Assumptions!M30+M32*Assumptions!M32*(Valuation!$F$30/(Valuation!$F$29+Valuation!$F$30))-(M32-M36)/365*Assumptions!M31-M32*Assumptions!M33-M32*Assumptions!M34 -> -4960.6293 | N45: =N32/365*Assumptions!N29+(N32-N36)/365*Assumptions!N30+N32*Assumptions!N32*(Valuation!$F$30/(Valuation!$F$29+Valuation!$F$30))-(N32-N36)/365*Assumptions!N31-N32*Assumptions!N33-N32*Assumptions!N34 -> -4977.8876 | O45: =O32/365*Assumptions!O29+(O32-O36)/365*Assumptions!O30+O32*Assumptions!O32*(Valuation!$F$30/(Valuation!$F$29+Valuation!$F$30))-(O32-O36)/365*Assumptions!O31-O32*Assumptions!O33-O32*Assumptions!O34 -> -5525.7977 | P45: =P32/365*Assumptions!P29+(P32-P36)/365*Assumptions!P30+P32*Assumptions!P32*(Valuation!$F$30/(Valuation!$F$29+Valuation!$F$30))-(P32-P36)/365*Assumptions!P31-P32*Assumptions!P33-P32*Assumptions!P34 -> -4986.482
C46: [-] Increase in Net Working Capital | E46: $M | L46: =L45-K45 -> 866.11071 | M46: =M45-L45 -> -335.74005 | N46: =N45-M45 -> -17.258224 | O46: =O45-N45 -> -547.91016 | P46: =P45-O45 -> 539.31572
C47: NOPAT = EBIT × (1 − Tax Rate) | E47: $M | L47: =L39*(1-Assumptions!L49) -> 2102.7638 | M47: =M39*(1-Assumptions!M49) -> 2615.4908 | N47: =N39*(1-Assumptions!N49) -> 3344.2878 | O47: =O39*(1-Assumptions!O49) -> 4245.301 | P47: =P39*(1-Assumptions!P49) -> 5173.9156
C48: FREE CASH FLOW TO THE FIRM (FCFF) | E48: $M | L48: =L47+L41-L42-L46 -> -2373.6041 | M48: =M47+M41-M42-M46 -> -68.697001 | N48: =N47+N41-N42-N46 -> 575.13759 | O48: =O47+O41-O42-O46 -> 2087.5258 | P48: =P47+P41-P42-P46 -> 2369.8931
C49: [+/-] Net Interest (common to all cases) | E49: $M | L49: ='Loans & Other Income'!L16-'Loans & Other Income'!L11 -> 324.285 | M49: ='Loans & Other Income'!M16-'Loans & Other Income'!M11 -> 465.02997 | N49: ='Loans & Other Income'!N16-'Loans & Other Income'!N11 -> 646.19723 | O49: ='Loans & Other Income'!O16-'Loans & Other Income'!O11 -> 711.10657 | P49: ='Loans & Other Income'!P16-'Loans & Other Income'!P11 -> 1016.4462
C50: NET INCOME | E50: $M | L50: =(L39+L49)*(1-Assumptions!L49) -> 2349.2204 | M50: =(M39+M49)*(1-Assumptions!M49) -> 2968.9136 | N50: =(N39+N49)*(1-Assumptions!N49) -> 3835.3977 | O50: =(O39+O49)*(1-Assumptions!O49) -> 4785.742 | P50: =(P39+P49)*(1-Assumptions!P49) -> 5946.4147
C51: Discount Factor | L51: =Valuation!L41 -> 0.88983286 | M51: =Valuation!M41 -> 0.79180251 | N51: =Valuation!N41 -> 0.70457189 | O51: =Valuation!O41 -> 0.62695122 | P51: =Valuation!P41 -> 0.5578818
C52: PV of FCFF | E52: $M | L52: =L48*L51 -> -2112.1109 | M52: =M48*M51 -> -54.394458 | N52: =N48*N51 -> 405.22578 | O52: =O48*O51 -> 1308.7768 | P52: =P48*P51 -> 1322.1202
C54: Sum of PV of Explicit FCFF (FY2026E–FY2030E) | K54: =SUM(L52:P52) -> 869.61745
C55: Terminal Value = FY2030E FCFF × (1 + g) ÷ (WACC − g) | K55: =P48*(1+Valuation!$F$18)/(Valuation!$F$17-Valuation!$F$18) -> 28668.543
C56: PV of Terminal Value | K56: =K55*P51 -> 15993.658
C57: ENTERPRISE VALUE | K57: =K54+K56 -> 16863.276
C58: EQUITY VALUE = EV + Cash − Debt − NCI | K58: =K57+Valuation!$K$49-Valuation!$K$50-Valuation!$K$51 -> 51818.276
C59: DCF IMPLIED VALUE PER SHARE | K59: =K58/Valuation!$K$55 -> 13.118551
A61: BASE CASE — OPERATING BUILD, FCFF AND DCF
K62: ='Revenue Build-up'!K3 -> FY25A | L62: ='Revenue Build-up'!L3 -> FY26E | M62: ='Revenue Build-up'!M3 -> FY27E | N62: ='Revenue Build-up'!N3 -> FY28E | O62: ='Revenue Build-up'!O3 -> FY29E | P62: ='Revenue Build-up'!P3 -> FY30E
C63: Vehicle Deliveries | E63: units | K63: ='Revenue Build-up'!K5 -> 1636129 | L63: =K63*(1+Assumptions!L69) -> 1734296.7 | M63: =L63*(1+Assumptions!M69) -> 1907726.4 | N63: =M63*(1+Assumptions!N69) -> 2136653.6 | O63: =N63*(1+Assumptions!O69) -> 2350318.9 | P63: =O63*(1+Assumptions!P69) -> 2538344.5
C64: Automotive Revenue per Delivery | E64: $/unit | K64: ='Revenue Build-up'!K6 -> 41276.085 | L64: =K64*(1+Assumptions!L72) -> 40037.803 | M64: =L64*(1+Assumptions!M72) -> 39237.047 | N64: =M64*(1+Assumptions!N72) -> 39629.417 | O64: =N64*(1+Assumptions!O72) -> 40025.711 | P64: =O64*(1+Assumptions!P72) -> 40826.225
C65: Automotive Sales & Leasing Revenue | E65: $M | L65: =L63*L64/1000000 -> 69437.431 | M65: =M63*M64/1000000 -> 74853.55 | N65: =N63*N64/1000000 -> 84674.336 | O65: =O63*O64/1000000 -> 94073.187 | P65: =P63*P64/1000000 -> 103631.02
C66: [+] Automotive Regulatory Credits | E66: $M | K66: ='Revenue Build-up'!K8 -> 1993 | L66: =K66*(1+Assumptions!L75) -> 1395.1 | M66: =L66*(1+Assumptions!M75) -> 1116.08 | N66: =M66*(1+Assumptions!N75) -> 1004.472 | O66: =N66*(1+Assumptions!O75) -> 954.2484 | P66: =O66*(1+Assumptions!P75) -> 906.53598
C67: Total Automotive Revenue | E67: $M | L67: =L65+L66 -> 70832.531 | M67: =M65+M66 -> 75969.63 | N67: =N65+N66 -> 85678.808 | O67: =O65+O66 -> 95027.436 | P67: =P65+P66 -> 104537.56
C68: Energy Generation & Storage Revenue | E68: $M | K68: ='Revenue Build-up'!K12 -> 12771 | L68: =K68*(1+Assumptions!L81) -> 16602.3 | M68: =L68*(1+Assumptions!M81) -> 20752.875 | N68: =M68*(1+Assumptions!N81) -> 24903.45 | O68: =N68*(1+Assumptions!O81) -> 29386.071 | P68: =O68*(1+Assumptions!P81) -> 33793.982
C69: Services & Other Revenue | E69: $M | K69: ='Revenue Build-up'!K15 -> 12530 | L69: =K69*(1+Assumptions!L87) -> 14409.5 | M69: =L69*(1+Assumptions!M87) -> 16426.83 | N69: =M69*(1+Assumptions!N87) -> 18562.318 | O69: =N69*(1+Assumptions!O87) -> 20789.796 | P69: =O69*(1+Assumptions!P87) -> 23076.674
C70: TOTAL REVENUE | E70: $M | K70: ='Revenue Build-up'!K18 -> 94827 | L70: =L67+L68+L69 -> 101844.33 | M70: =M67+M68+M69 -> 113149.34 | N70: =N67+N68+N69 -> 129144.58 | O70: =O67+O68+O69 -> 145203.3 | P70: =P67+P68+P69 -> 161408.21
C71: Automotive Gross Profit | E71: $M | L71: =L67*Assumptions!L78 -> 13458.181 | M71: =M67*Assumptions!M78 -> 15193.926 | N71: =N67*Assumptions!N78 -> 17992.55 | O71: =O67*Assumptions!O78 -> 20906.036 | P71: =P67*Assumptions!P78 -> 24043.639
C72: Energy Gross Profit | E72: $M | L72: =L68*Assumptions!L84 -> 4980.69 | M72: =M68*Assumptions!M84 -> 6433.3912 | N72: =N68*Assumptions!N84 -> 7969.104 | O72: =O68*Assumptions!O84 -> 9403.5427 | P72: =P68*Assumptions!P84 -> 10814.074
C73: Services Gross Profit | E73: $M | L73: =L69*Assumptions!L90 -> 1729.14 | M73: =M69*Assumptions!M90 -> 2135.4879 | N73: =N69*Assumptions!N90 -> 2598.7245 | O73: =O69*Assumptions!O90 -> 3118.4694 | P73: =P69*Assumptions!P90 -> 3461.501
C74: GROSS PROFIT | E74: $M | L74: =SUM(L71:L73) -> 20168.011 | M74: =SUM(M71:M73) -> 23762.805 | N74: =SUM(N71:N73) -> 28560.378 | O74: =SUM(O71:O73) -> 33428.048 | P74: =SUM(P71:P73) -> 38319.214
C75: [-] Research & Development | E75: $M | L75: =L70*Assumptions!L93 -> 7129.1031 | M75: =M70*Assumptions!M93 -> 7920.4535 | N75: =N70*Assumptions!N93 -> 8394.3974 | O75: =O70*Assumptions!O93 -> 8712.1982 | P75: =P70*Assumptions!P93 -> 9684.4929
C76: [-] Selling, General & Administrative | E76: $M | L76: =L70*Assumptions!L96 -> 6110.6598 | M76: =M70*Assumptions!M96 -> 6562.6614 | N76: =N70*Assumptions!N96 -> 7102.9517 | O76: =O70*Assumptions!O96 -> 7695.775 | P76: =P70*Assumptions!P96 -> 8070.4107
C77: EBIT (Operating Income) | E77: $M | L77: =L74-L75-L76 -> 6928.2478 | M77: =M74-M75-M76 -> 9279.6903 | N77: =N74-N75-N76 -> 13063.029 | O77: =O74-O75-O76 -> 17020.075 | P77: =P74-P75-P76 -> 20564.31
C78: Opening Net PP&E | E78: $M | L78: =K81 -> 40643 | M78: =L81 -> 44121.338 | N78: =M81 -> 47811.111 | O78: =N81 -> 52023.4 | P78: =O81 -> 56562.171
C79: [-] Depreciation & Amortisation | E79: $M | L79: =L78*Assumptions!L42 -> 6706.095 | M79: =M78*Assumptions!M42 -> 7059.4141 | N79: =N78*Assumptions!N42 -> 7410.7222 | O79: =O78*Assumptions!O42 -> 7803.5101 | P79: =P78*Assumptions!P42 -> 8484.3257
C80: [+] Capital Expenditure | E80: $M | L80: =L70*Assumptions!L99 -> 10184.433 | M80: =M70*Assumptions!M99 -> 10749.187 | N80: =N70*Assumptions!N99 -> 11623.012 | O80: =O70*Assumptions!O99 -> 12342.281 | P80: =P70*Assumptions!P99 -> 12912.657
C81: Closing Net PP&E | E81: $M | K81: ='Asset Schedule'!K9 -> 40643 | L81: =L78-L79+L80 -> 44121.338 | M81: =M78-M79+M80 -> 47811.111 | N81: =N78-N79+N80 -> 52023.4 | O81: =O78-O79+O80 -> 56562.171 | P81: =P78-P79+P80 -> 60990.503
C82: EBITDA | E82: $M | L82: =L77+L79 -> 13634.343 | M82: =M77+M79 -> 16339.104 | N82: =N77+N79 -> 20473.751 | O82: =O77+O79 -> 24823.585 | P82: =P77+P79 -> 29048.636
C83: Net Working Capital (DCF definition) | E83: $M | K83: =BS!K6+BS!K7+Valuation!$F$30-BS!K17-BS!K18-BS!K19 -> -5491 | L83: =L70/365*Assumptions!L29+(L70-L74)/365*Assumptions!L30+L70*Assumptions!L32*(Valuation!$F$30/(Valuation!$F$29+Valuation!$F$30))-(L70-L74)/365*Assumptions!L31-L70*Assumptions!L33-L70*Assumptions!L34 -> -4966.6069 | M83: =M70/365*Assumptions!M29+(M70-M74)/365*Assumptions!M30+M70*Assumptions!M32*(Valuation!$F$30/(Valuation!$F$29+Valuation!$F$30))-(M70-M74)/365*Assumptions!M31-M70*Assumptions!M33-M70*Assumptions!M34 -> -5736.6427 | N83: =N70/365*Assumptions!N29+(N70-N74)/365*Assumptions!N30+N70*Assumptions!N32*(Valuation!$F$30/(Valuation!$F$29+Valuation!$F$30))-(N70-N74)/365*Assumptions!N31-N70*Assumptions!N33-N70*Assumptions!N34 -> -6216.1067 | O83: =O70/365*Assumptions!O29+(O70-O74)/365*Assumptions!O30+O70*Assumptions!O32*(Valuation!$F$30/(Valuation!$F$29+Valuation!$F$30))-(O70-O74)/365*Assumptions!O31-O70*Assumptions!O33-O70*Assumptions!O34 -> -7250.9907 | P83: =P70/365*Assumptions!P29+(P70-P74)/365*Assumptions!P30+P70*Assumptions!P32*(Valuation!$F$30/(Valuation!$F$29+Valuation!$F$30))-(P70-P74)/365*Assumptions!P31-P70*Assumptions!P33-P70*Assumptions!P34 -> -6865.4463
C84: [-] Increase in Net Working Capital | E84: $M | L84: =L83-K83 -> 524.39313 | M84: =M83-L83 -> -770.03585 | N84: =N83-M83 -> -479.46397 | O84: =O83-N83 -> -1034.884 | P84: =P83-O83 -> 385.54438
C85: NOPAT = EBIT × (1 − Tax Rate) | E85: $M | L85: =L77*(1-Assumptions!L49) -> 5265.4684 | M85: =M77*(1-Assumptions!M49) -> 7052.5646 | N85: =N77*(1-Assumptions!N49) -> 9927.9021 | O85: =O77*(1-Assumptions!O49) -> 12935.257 | P85: =P77*(1-Assumptions!P49) -> 15628.876
C86: FREE CASH FLOW TO THE FIRM (FCFF) | E86: $M | L86: =L85+L79-L80-L84 -> 1262.7372 | M86: =M85+M79-M80-M84 -> 4132.8277 | N86: =N85+N79-N80-N84 -> 6195.0764 | O86: =O85+O79-O80-O84 -> 9431.3702 | P86: =P85+P79-P80-P84 -> 10815
C87: [+/-] Net Interest (common to all cases) | E87: $M | L87: ='Loans & Other Income'!L16-'Loans & Other Income'!L11 -> 324.285 | M87: ='Loans & Other Income'!M16-'Loans & Other Income'!M11 -> 465.02997 | N87: ='Loans & Other Income'!N16-'Loans & Other Income'!N11 -> 646.19723 | O87: ='Loans & Other Income'!O16-'Loans & Other Income'!O11 -> 711.10657 | P87: ='Loans & Other Income'!P16-'Loans & Other Income'!P11 -> 1016.4462
C88: NET INCOME | E88: $M | L88: =(L77+L87)*(1-Assumptions!L49) -> 5511.925 | M88: =(M77+M87)*(1-Assumptions!M49) -> 7405.9874 | N88: =(N77+N87)*(1-Assumptions!N49) -> 10419.012 | O88: =(O77+O87)*(1-Assumptions!O49) -> 13475.698 | P88: =(P77+P87)*(1-Assumptions!P49) -> 16401.375
C89: Discount Factor | L89: =Valuation!L41 -> 0.88983286 | M89: =Valuation!M41 -> 0.79180251 | N89: =Valuation!N41 -> 0.70457189 | O89: =Valuation!O41 -> 0.62695122 | P89: =Valuation!P41 -> 0.5578818
C90: PV of FCFF | E90: $M | L90: =L86*L89 -> 1123.625 | M90: =M86*M89 -> 3272.3834 | N90: =N86*N89 -> 4364.8767 | O90: =O86*O89 -> 5913.0091 | P90: =P86*P89 -> 6033.4916
C92: Sum of PV of Explicit FCFF (FY2026E–FY2030E) | K92: =SUM(L90:P90) -> 20707.386
C93: Terminal Value = FY2030E FCFF × (1 + g) ÷ (WACC − g) | K93: =P86*(1+Valuation!$F$18)/(Valuation!$F$17-Valuation!$F$18) -> 130828.81
C94: PV of Terminal Value | K94: =K93*P89 -> 72987.012
C95: ENTERPRISE VALUE | K95: =K92+K94 -> 93694.398
C96: EQUITY VALUE = EV + Cash − Debt − NCI | K96: =K95+Valuation!$K$49-Valuation!$K$50-Valuation!$K$51 -> 128649.4
C97: DCF IMPLIED VALUE PER SHARE | K97: =K96/Valuation!$K$55 -> 32.569468
A99: BULL CASE — OPERATING BUILD, FCFF AND DCF
K100: ='Revenue Build-up'!K3 -> FY25A | L100: ='Revenue Build-up'!L3 -> FY26E | M100: ='Revenue Build-up'!M3 -> FY27E | N100: ='Revenue Build-up'!N3 -> FY28E | O100: ='Revenue Build-up'!O3 -> FY29E | P100: ='Revenue Build-up'!P3 -> FY30E
C101: Vehicle Deliveries | E101: units | K101: ='Revenue Build-up'!K5 -> 1636129 | L101: =K101*(1+Assumptions!L70) -> 1799741.9 | M101: =L101*(1+Assumptions!M70) -> 2069703.2 | N101: =M101*(1+Assumptions!N70) -> 2421552.7 | O101: =N101*(1+Assumptions!O70) -> 2760570.1 | P101: =O101*(1+Assumptions!P70) -> 3091838.5
C102: Automotive Revenue per Delivery | E102: $/unit | K102: ='Revenue Build-up'!K6 -> 41276.085 | L102: =K102*(1+Assumptions!L73) -> 40863.324 | M102: =L102*(1+Assumptions!M73) -> 40863.324 | N102: =M102*(1+Assumptions!N73) -> 41680.591 | O102: =N102*(1+Assumptions!O73) -> 42514.203 | P102: =O102*(1+Assumptions!P73) -> 43789.629
C103: Automotive Sales & Leasing Revenue | E103: $M | L103: =L101*L102/1000000 -> 73543.437 | M103: =M101*M102/1000000 -> 84574.953 | N103: =N101*N102/1000000 -> 100931.75 | O103: =O101*O102/1000000 -> 117363.44 | P103: =P101*P102/1000000 -> 135390.46
C104: [+] Automotive Regulatory Credits | E104: $M | K104: ='Revenue Build-up'!K8 -> 1993 | L104: =K104*(1+Assumptions!L76) -> 1494.75 | M104: =L104*(1+Assumptions!M76) -> 1270.5375 | N104: =M104*(1+Assumptions!N76) -> 1207.0106 | O104: =N104*(1+Assumptions!O76) -> 1207.0106 | P104: =O104*(1+Assumptions!P76) -> 1207.0106
C105: Total Automotive Revenue | E105: $M | L105: =L103+L104 -> 75038.187 | M105: =M103+M104 -> 85845.49 | N105: =N103+N104 -> 102138.76 | O105: =O103+O104 -> 118570.45 | P105: =P103+P104 -> 136597.47
C106: Energy Generation & Storage Revenue | E106: $M | K106: ='Revenue Build-up'!K12 -> 12771 | L106: =K106*(1+Assumptions!L82) -> 17623.98 | M106: =L106*(1+Assumptions!M82) -> 23263.654 | N106: =M106*(1+Assumptions!N82) -> 29544.84 | O106: =N106*(1+Assumptions!O82) -> 36340.153 | P106: =O106*(1+Assumptions!P82) -> 43608.184
C107: Services & Other Revenue | E107: $M | K107: ='Revenue Build-up'!K15 -> 12530 | L107: =K107*(1+Assumptions!L88) -> 14785.4 | M107: =L107*(1+Assumptions!M88) -> 17298.918 | N107: =M107*(1+Assumptions!N88) -> 20066.745 | O107: =N107*(1+Assumptions!O88) -> 23076.757 | P107: =O107*(1+Assumptions!P88) -> 26307.503
C108: TOTAL REVENUE | E108: $M | K108: ='Revenue Build-up'!K18 -> 94827 | L108: =L105+L106+L107 -> 107447.57 | M108: =M105+M106+M107 -> 126408.06 | N108: =N105+N106+N107 -> 151750.34 | O108: =O105+O106+O107 -> 177987.36 | P108: =P105+P106+P107 -> 206513.16
...

Sheet Reverse DCF
A1: TESLA, INC. | E1: ◄ Cover | G1: REVERSE DCF — MARKET-IMPLIED EXPECTATIONS
A2: USD millions except per-share data · This sheet is NOT a forecast. It starts from the market price and asks what operating performance would be required to justify it.
A4: MARKET-IMPLIED ENTERPRISE VALUE
C5: Valuation date | E5: date | F5: =Assumptions!$G$63 -> 46268
C6: Market price per share | E6: $/share | F6: =Assumptions!$G$56 -> 376.37
C7: Common Shares Outstanding (Current) | E7: millions | F7: =Assumptions!$G$57 -> 3950
C8: Market capitalisation (equity value) | E8: $M | F8: =F6*F7 -> 1486661.5
C9: [+] Total debt | E9: $M | F9: =Valuation!$K$50 -> 8376
C10: [+] Noncontrolling interests | E10: $M | F10: =Valuation!$K$51 -> 728
C11: [-] Cash & short-term investments | E11: $M | F11: =Valuation!$K$49 -> 44059
C12: MARKET-IMPLIED ENTERPRISE VALUE | E12: $M | F12: =F8+F9+F10-F11 -> 1451706.5
A14: FUNDAMENTAL BASE CASE — FOR CONTRAST
C15: Fundamental enterprise value (DCF, selected case) | E15: $M | F15: =Valuation!$K$46 -> 93694.398
C16: Fundamental equity value | E16: $M | F16: =Valuation!$K$52 -> 128649.4
C17: Fundamental implied value per share | E17: $/share | F17: =Valuation!$K$56 -> 32.569468
C18: Market-implied EV ÷ fundamental EV | E18: x | F18: =F12/F15 -> 15.494059
C19: The expectations gap above is what the rest of this sheet decomposes.
A21: INDEPENDENT PARAMETERISED DCF — INPUTS
C22: Deliberately independent of the forecast sheets: the build below is driven only by FY2025A actuals and the parameters in this block, so it can be moved without touching the operating model. Conversion assumptions are set at the model's own long-run levels and are stated as explicit inputs rather than inherited.
C23: Parameter | E23: Unit | F23: Value
C24: FY2025A revenue (actual) | E24: $M | F24: =IS!$K$8 -> 94827
C25: FY2025A EBIT margin (actual) | E25: % | F25: =IS!$K$26 -> 0.045925738
C26: Revenue CAGR, FY2025A–FY2030E | E26: % | F26: 0.112
C27: FY2030E EBIT margin | E27: % | F27: 0.127
C28: Tax rate | E28: % | F28: 0.24
C29: D&A as % of revenue | E29: % | F29: 0.053
C30: CapEx as % of revenue | E30: % | F30: 0.08
C31: Increase in NWC as % of revenue increase | E31: % | F31: 0.024
C32: WACC | E32: % | F32: =Valuation!$F$17 -> 0.12380656
C33: Terminal growth rate | E33: % | F33: =Valuation!$F$18 -> 0.038
A35: PARAMETERISED FIVE-YEAR BUILD
H36: ='Revenue Build-up'!L3 -> FY26E | I36: ='Revenue Build-up'!M3 -> FY27E | J36: ='Revenue Build-up'!N3 -> FY28E | K36: ='Revenue Build-up'!O3 -> FY29E | L36: ='Revenue Build-up'!P3 -> FY30E
C37: Year index (t) | H37: =1 -> 1 | I37: =2 -> 2 | J37: =3 -> 3 | K37: =4 -> 4 | L37: =5 -> 5
C38: Revenue | H38: =$F$24*(1+$F$26)^H37 -> 105447.62 | I38: =$F$24*(1+$F$26)^I37 -> 117257.76 | J38: =$F$24*(1+$F$26)^J37 -> 130390.63 | K38: =$F$24*(1+$F$26)^K37 -> 144994.38 | L38: =$F$24*(1+$F$26)^L37 -> 161233.75
C39: EBIT margin (linear ramp to the target) | H39: =$F$25+($F$27-$F$25)*H37/5 -> 0.062140591 | I39: =$F$25+($F$27-$F$25)*I37/5 -> 0.078355443 | J39: =$F$25+($F$27-$F$25)*J37/5 -> 0.094570295 | K39: =$F$25+($F$27-$F$25)*K37/5 -> 0.11078515 | L39: =$F$25+($F$27-$F$25)*L37/5 -> 0.127
C40: EBIT | H40: =H38*H39 -> 6552.5776 | I40: =I38*I39 -> 9187.7836 | J40: =J38*J39 -> 12331.08 | K40: =K38*K39 -> 16063.223 | L40: =L38*L39 -> 20476.686
C41: NOPAT = EBIT × (1 − tax) | H41: =H40*(1-$F$28) -> 4979.959 | I41: =I40*(1-$F$28) -> 6982.7155 | J41: =J40*(1-$F$28) -> 9371.6209 | K41: =K40*(1-$F$28) -> 12208.05 | L41: =L40*(1-$F$28) -> 15562.281
C42: [+] Depreciation & amortisation | H42: =H38*$F$29 -> 5588.7241 | I42: =I38*$F$29 -> 6214.6612 | J42: =J38*$F$29 -> 6910.7032 | K42: =K38*$F$29 -> 7684.702 | L42: =L38*$F$29 -> 8545.3886
C43: [-] Capital expenditure | H43: =H38*$F$30 -> 8435.8099 | I43: =I38*$F$30 -> 9380.6206 | J43: =J38*$F$30 -> 10431.25 | K43: =K38*$F$30 -> 11599.55 | L43: =L38*$F$30 -> 12898.7
C44: [-] Increase in net working capital | H44: =(H38-$F$24)*$F$31 -> 254.89498 | I44: =(I38-H38)*$F$31 -> 283.44321 | J44: =(J38-I38)*$F$31 -> 315.18885 | K44: =(K38-J38)*$F$31 -> 350.49 | L44: =(L38-K38)*$F$31 -> 389.74489
C45: FREE CASH FLOW TO THE FIRM | H45: =H41+H42-H43-H44 -> 1877.9782 | I45: =I41+I42-I43-I44 -> 3533.3128 | J45: =J41+J42-J43-J44 -> 5535.8851 | K45: =K41+K42-K43-K44 -> 7942.7117 | L45: =L41+L42-L43-L44 -> 10819.225
C46: Discount factor | H46: =1/(1+$F$32)^H37 -> 0.88983286 | I46: =1/(1+$F$32)^I37 -> 0.79180251 | J46: =1/(1+$F$32)^J37 -> 0.70457189 | K46: =1/(1+$F$32)^K37 -> 0.62695122 | L46: =1/(1+$F$32)^L37 -> 0.5578818
C47: PV of FCFF | H47: =H45*H46 -> 1671.0867 | I47: =I45*I46 -> 2797.686 | J47: =J45*J46 -> 3900.429 | K47: =K45*K46 -> 4979.6928 | L47: =L45*L46 -> 6035.8488
C49: Sum of PV of explicit FCFF | E49: $M | F49: =SUM(H47:L47) -> 19384.743
C50: Terminal value = FY2030E FCFF × (1 + g) ÷ (WACC − g) | E50: $M | F50: =L45*(1+$F$33)/($F$32-$F$33) -> 130879.93
C51: [+] PV of terminal value | E51: $M | F51: =F50*L46 -> 73015.528
C52: ENTERPRISE VALUE at these parameters | E52: $M | F52: =F49+F51 -> 92400.271
C53: Equity value | E53: $M | F53: =F52+Valuation!$K$49-Valuation!$K$50-Valuation!$K$51 -> 127355.27
C54: IMPLIED VALUE PER SHARE at these parameters | E54: $/share | F54: =F53/Assumptions!$G$57 -> 32.241841
C55: Implied value ÷ market price − 1 | E55: % | F55: =F54/$F$6-1 -> -0.91433472
C56: ="Calibration memo: at Base Case parameters this independent build returns "&TEXT($F$54,"$0.00")&" against "&TEXT($F$17,"$0.00")&" from the full three-statement DCF ("&TEXT($F$54/$F$17-1,"0.0%")&"). The difference is the simplified conversion ratios — it confirms the parameterisation is calibrated to the operating model without being driven by it." -> Calibration memo: at Base Case parameters this independent build returns $32.24 against $32.57 from the full three-statement DCF (-1.0%). The difference is the simplified conversion ratios — it confirms the parameterisation is calibrated to the operating model without being driven by it.
A57: REQUIRED PERFORMANCE TO JUSTIFY THE MARKET PRICE
C58: Scaling factor required on the whole FCFF path | E58: x | F58: =$F$12/$F$52 -> 15.711063
C59: Required FY2030E free cash flow to the firm | E59: $M | F59: =L45*F58 -> 169981.53
C60: Base Case FY2030E free cash flow to the firm | E60: $M | F60: ='Scenario Analysis'!I13 -> 10815
C61: Required FY2030E FCFF ÷ Base Case | E61: x | F61: =F59/F60 -> 15.717201
C62: Required FY2030E EBIT (same conversion economics) | E62: $M | F62: =L40*F58 -> 321710.51
C63: → implied FY2030E revenue if the EBIT margin stays at the input level | E63: $M | F63: =F62/$F$27 -> 2533153.6
C64: → implied FY2030E EBIT margin if revenue only reaches the Bull Case | E64: % | F64: =F62/'Scenario Analysis'!K6 -> 1.5578209
C65: Enterprise value is linear in the cash-flow path, so scaling the whole path by the factor in row 58 scales enterprise value by the same factor. That makes the requirement directly readable rather than solved by trial and error.
A67: SENSITIVITY — REVENUE CAGR × FY2030E EBIT MARGIN
C68: Each cell re-runs the full five-year parameterised DCF for that pair of assumptions, holding WACC, terminal growth and the conversion assumptions constant. Cells that would land within ±10% of the market price are highlighted — if none is highlighted, no combination in the grid justifies the market price.
G69: CAGR ↓ | I69: FY2030E EBIT MARGIN →
H70: =$F$54 -> 32.241841 | I70: =$F$27 -> 0.127 | J70: 0.16 | K70: 0.2 | L70: 0.24 | M70: 0.28 | N70: 0.32
H71: =$F$26 -> 0.112 | I71: =(SUMPRODUCT((($F$24*(1+$H71)^{1,2,3,4,5})*(($F$25+(I$70-$F$25)*{1,2,3,4,5}/5)*(1-$F$28)+$F$29-$F$30)-(($F$24*(1+$H71)^{1,2,3,4,5})-($F$24*(1+$H71)^({1,2,3,4,5}-1)))*$F$31)/(1+$F$32)^{1,2,3,4,5})+($F$24*(1+$H71)^5*(I$70*(1-$F$28)+$F$29-$F$30)-($F$24*(1+$H71)^5-$F$24*(1+$H71)^4)*$F$31)*(1+$F$33)/($F$32-$F$33)/(1+$F$32)^5+Valuation!$K$49-Valuation!$K$50-Valuation!$K$51)/Assumptions!$G$57 -> 32.241841 | J71: =(SUMPRODUCT((($F$24*(1+$H71)^{1,2,3,4,5})*(($F$25+(J$70-$F$25)*{1,2,3,4,5}/5)*(1-$F$28)+$F$29-$F$30)-(($F$24*(1+$H71)^{1,2,3,4,5})-($F$24*(1+$H71)^({1,2,3,4,5}-1)))*$F$31)/(1+$F$32)^{1,2,3,4,5})+($F$24*(1+$H71)^5*(J$70*(1-$F$28)+$F$29-$F$30)-($F$24*(1+$H71)^5-$F$24*(1+$H71)^4)*$F$31)*(1+$F$33)/($F$32-$F$33)/(1+$F$32)^5+Valuation!$K$49-Valuation!$K$50-Valuation!$K$51)/Assumptions!$G$57 -> 40.8885 | K71: =(SUMPRODUCT((($F$24*(1+$H71)^{1,2,3,4,5})*(($F$25+(K$70-$F$25)*{1,2,3,4,5}/5)*(1-$F$28)+$F$29-$F$30)-(($F$24*(1+$H71)^{1,2,3,4,5})-($F$24*(1+$H71)^({1,2,3,4,5}-1)))*$F$31)/(1+$F$32)^{1,2,3,4,5})+($F$24*(1+$H71)^5*(K$70*(1-$F$28)+$F$29-$F$30)-($F$24*(1+$H71)^5-$F$24*(1+$H71)^4)*$F$31)*(1+$F$33)/($F$32-$F$33)/(1+$F$32)^5+Valuation!$K$49-Valuation!$K$50-Valuation!$K$51)/Assumptions!$G$57 -> 51.369299 | L71: =(SUMPRODUCT((($F$24*(1+$H71)^{1,2,3,4,5})*(($F$25+(L$70-$F$25)*{1,2,3,4,5}/5)*(1-$F$28)+$F$29-$F$30)-(($F$24*(1+$H71)^{1,2,3,4,5})-($F$24*(1+$H71)^({1,2,3,4,5}-1)))*$F$31)/(1+$F$32)^{1,2,3,4,5})+($F$24*(1+$H71)^5*(L$70*(1-$F$28)+$F$29-$F$30)-($F$24*(1+$H71)^5-$F$24*(1+$H71)^4)*$F$31)*(1+$F$33)/($F$32-$F$33)/(1+$F$32)^5+Valuation!$K$49-Valuation!$K$50-Valuation!$K$51)/Assumptions!$G$57 -> 61.850098 | M71: =(SUMPRODUCT((($F$24*(1+$H71)^{1,2,3,4,5})*(($F$25+(M$70-$F$25)*{1,2,3,4,5}/5)*(1-$F$28)+$F$29-$F$30)-(($F$24*(1+$H71)^{1,2,3,4,5})-($F$24*(1+$H71)^({1,2,3,4,5}-1)))*$F$31)/(1+$F$32)^{1,2,3,4,5})+($F$24*(1+$H71)^5*(M$70*(1-$F$28)+$F$29-$F$30)-($F$24*(1+$H71)^5-$F$24*(1+$H71)^4)*$F$31)*(1+$F$33)/($F$32-$F$33)/(1+$F$32)^5+Valuation!$K$49-Valuation!$K$50-Valuation!$K$51)/Assumptions!$G$57 -> 72.330896 | N71: =(SUMPRODUCT((($F$24*(1+$H71)^{1,2,3,4,5})*(($F$25+(N$70-$F$25)*{1,2,3,4,5}/5)*(1-$F$28)+$F$29-$F$30)-(($F$24*(1+$H71)^{1,2,3,4,5})-($F$24*(1+$H71)^({1,2,3,4,5}-1)))*$F$31)/(1+$F$32)^{1,2,3,4,5})+($F$24*(1+$H71)^5*(N$70*(1-$F$28)+$F$29-$F$30)-($F$24*(1+$H71)^5-$F$24*(1+$H71)^4)*$F$31)*(1+$F$33)/($F$32-$F$33)/(1+$F$32)^5+Valuation!$K$49-Valuation!$K$50-Valuation!$K$51)/Assumptions!$G$57 -> 82.811695
H72: 0.15 | I72: =(SUMPRODUCT((($F$24*(1+$H72)^{1,2,3,4,5})*(($F$25+(I$70-$F$25)*{1,2,3,4,5}/5)*(1-$F$28)+$F$29-$F$30)-(($F$24*(1+$H72)^{1,2,3,4,5})-($F$24*(1+$H72)^({1,2,3,4,5}-1)))*$F$31)/(1+$F$32)^{1,2,3,4,5})+($F$24*(1+$H72)^5*(I$70*(1-$F$28)+$F$29-$F$30)-($F$24*(1+$H72)^5-$F$24*(1+$H72)^4)*$F$31)*(1+$F$33)/($F$32-$F$33)/(1+$F$32)^5+Valuation!$K$49-Valuation!$K$50-Valuation!$K$51)/Assumptions!$G$57 -> 35.928761 | J72: =(SUMPRODUCT((($F$24*(1+$H72)^{1,2,3,4,5})*(($F$25+(J$70-$F$25)*{1,2,3,4,5}/5)*(1-$F$28)+$F$29-$F$30)-(($F$24*(1+$H72)^{1,2,3,4,5})-($F$24*(1+$H72)^({1,2,3,4,5}-1)))*$F$31)/(1+$F$32)^{1,2,3,4,5})+($F$24*(1+$H72)^5*(J$70*(1-$F$28)+$F$29-$F$30)-($F$24*(1+$H72)^5-$F$24*(1+$H72)^4)*$F$31)*(1+$F$33)/($F$32-$F$33)/(1+$F$32)^5+Valuation!$K$49-Valuation!$K$50-Valuation!$K$51)/Assumptions!$G$57 -> 46.067867 | K72: =(SUMPRODUCT((($F$24*(1+$H72)^{1,2,3,4,5})*(($F$25+(K$70-$F$25)*{1,2,3,4,5}/5)*(1-$F$28)+$F$29-$F$30)-(($F$24*(1+$H72)^{1,2,3,4,5})-($F$24*(1+$H72)^({1,2,3,4,5}-1)))*$F$31)/(1+$F$32)^{1,2,3,4,5})+($F$24*(1+$H72)^5*(K$70*(1-$F$28)+$F$29-$F$30)-($F$24*(1+$H72)^5-$F$24*(1+$H72)^4)*$F$31)*(1+$F$33)/($F$32-$F$33)/(1+$F$32)^5+Valuation!$K$49-Valuation!$K$50-Valuation!$K$51)/Assumptions!$G$57 -> 58.357692 | L72: =(SUMPRODUCT((($F$24*(1+$H72)^{1,2,3,4,5})*(($F$25+(L$70-$F$25)*{1,2,3,4,5}/5)*(1-$F$28)+$F$29-$F$30)-(($F$24*(1+$H72)^{1,2,3,4,5})-($F$24*(1+$H72)^({1,2,3,4,5}-1)))*$F$31)/(1+$F$32)^{1,2,3,4,5})+($F$24*(1+$H72)^5*(L$70*(1-$F$28)+$F$29-$F$30)-($F$24*(1+$H72)^5-$F$24*(1+$H72)^4)*$F$31)*(1+$F$33)/($F$32-$F$33)/(1+$F$32)^5+Valuation!$K$49-Valuation!$K$50-Valuation!$K$51)/Assumptions!$G$57 -> 70.647517 | M72: =(SUMPRODUCT((($F$24*(1+$H72)^{1,2,3,4,5})*(($F$25+(M$70-$F$25)*{1,2,3,4,5}/5)*(1-$F$28)+$F$29-$F$30)-(($F$24*(1+$H72)^{1,2,3,4,5})-($F$24*(1+$H72)^({1,2,3,4,5}-1)))*$F$31)/(1+$F$32)^{1,2,3,4,5})+($F$24*(1+$H72)^5*(M$70*(1-$F$28)+$F$29-$F$30)-($F$24*(1+$H72)^5-$F$24*(1+$H72)^4)*$F$31)*(1+$F$33)/($F$32-$F$33)/(1+$F$32)^5+Valuation!$K$49-Valuation!$K$50-Valuation!$K$51)/Assumptions!$G$57 -> 82.937342 | N72: =(SUMPRODUCT((($F$24*(1+$H72)^{1,2,3,4,5})*(($F$25+(N$70-$F$25)*{1,2,3,4,5}/5)*(1-$F$28)+$F$29-$F$30)-(($F$24*(1+$H72)^{1,2,3,4,5})-($F$24*(1+$H72)^({1,2,3,4,5}-1)))*$F$31)/(1+$F$32)^{1,2,3,4,5})+($F$24*(1+$H72)^5*(N$70*(1-$F$28)+$F$29-$F$30)-($F$24*(1+$H72)^5-$F$24*(1+$H72)^4)*$F$31)*(1+$F$33)/($F$32-$F$33)/(1+$F$32)^5+Valuation!$K$49-Valuation!$K$50-Valuation!$K$51)/Assumptions!$G$57 -> 95.227167
H73: 0.2 | I73: =(SUMPRODUCT((($F$24*(1+$H73)^{1,2,3,4,5})*(($F$25+(I$70-$F$25)*{1,2,3,4,5}/5)*(1-$F$28)+$F$29-$F$30)-(($F$24*(1+$H73)^{1,2,3,4,5})-($F$24*(1+$H73)^({1,2,3,4,5}-1)))*$F$31)/(1+$F$32)^{1,2,3,4,5})+($F$24*(1+$H73)^5*(I$70*(1-$F$28)+$F$29-$F$30)-($F$24*(1+$H73)^5-$F$24*(1+$H73)^4)*$F$31)*(1+$F$33)/($F$32-$F$33)/(1+$F$32)^5+Valuation!$K$49-Valuation!$K$50-Valuation!$K$51)/Assumptions!$G$57 -> 41.499269 | J73: =(SUMPRODUCT((($F$24*(1+$H73)^{1,2,3,4,5})*(($F$25+(J$70-$F$25)*{1,2,3,4,5}/5)*(1-$F$28)+$F$29-$F$30)-(($F$24*(1+$H73)^{1,2,3,4,5})-($F$24*(1+$H73)^({1,2,3,4,5}-1)))*$F$31)/(1+$F$32)^{1,2,3,4,5})+($F$24*(1+$H73)^5*(J$70*(1-$F$28)+$F$29-$F$30)-($F$24*(1+$H73)^5-$F$24*(1+$H73)^4)*$F$31)*(1+$F$33)/($F$32-$F$33)/(1+$F$32)^5+Valuation!$K$49-Valuation!$K$50-Valuation!$K$51)/Assumptions!$G$57 -> 53.915146 | K73: =(SUMPRODUCT((($F$24*(1+$H73)^{1,2,3,4,5})*(($F$25+(K$70-$F$25)*{1,2,3,4,5}/5)*(1-$F$28)+$F$29-$F$30)-(($F$24*(1+$H73)^{1,2,3,4,5})-($F$24*(1+$H73)^({1,2,3,4,5}-1)))*$F$31)/(1+$F$32)^{1,2,3,4,5})+($F$24*(1+$H73)^5*(K$70*(1-$F$28)+$F$29-$F$30)-($F$24*(1+$H73)^5-$F$24*(1+$H73)^4)*$F$31)*(1+$F$33)/($F$32-$F$33)/(1+$F$32)^5+Valuation!$K$49-Valuation!$K$50-Valuation!$K$51)/Assumptions!$G$57 -> 68.964693 | L73: =(SUMPRODUCT((($F$24*(1+$H73)^{1,2,3,4,5})*(($F$25+(L$70-$F$25)*{1,2,3,4,5}/5)*(1-$F$28)+$F$29-$F$30)-(($F$24*(1+$H73)^{1,2,3,4,5})-($F$24*(1+$H73)^({1,2,3,4,5}-1)))*$F$31)/(1+$F$32)^{1,2,3,4,5})+($F$24*(1+$H73)^5*(L$70*(1-$F$28)+$F$29-$F$30)-($F$24*(1+$H73)^5-$F$24*(1+$H73)^4)*$F$31)*(1+$F$33)/($F$32-$F$33)/(1+$F$32)^5+Valuation!$K$49-Valuation!$K$50-Valuation!$K$51)/Assumptions!$G$57 -> 84.014241 | M73: =(SUMPRODUCT((($F$24*(1+$H73)^{1,2,3,4,5})*(($F$25+(M$70-$F$25)*{1,2,3,4,5}/5)*(1-$F$28)+$F$29-$F$30)-(($F$24*(1+$H73)^{1,2,3,4,5})-($F$24*(1+$H73)^({1,2,3,4,5}-1)))*$F$31)/(1+$F$32)^{1,2,3,4,5})+($F$24*(1+$H73)^5*(M$70*(1-$F$28)+$F$29-$F$30)-($F$24*(1+$H73)^5-$F$24*(1+$H73)^4)*$F$31)*(1+$F$33)/($F$32-$F$33)/(1+$F$32)^5+Valuation!$K$49-Valuation!$K$50-Valuation!$K$51)/Assumptions!$G$57 -> 99.063788 | N73: =(SUMPRODUCT((($F$24*(1+$H73)^{1,2,3,4,5})*(($F$25+(N$70-$F$25)*{1,2,3,4,5}/5)*(1-$F$28)+$F$29-$F$30)-(($F$24*(1+$H73)^{1,2,3,4,5})-($F$24*(1+$H73)^({1,2,3,4,5}-1)))*$F$31)/(1+$F$32)^{1,2,3,4,5})+($F$24*(1+$H73)^5*(N$70*(1-$F$28)+$F$29-$F$30)-($F$24*(1+$H73)^5-$F$24*(1+$H73)^4)*$F$31)*(1+$F$33)/($F$32-$F$33)/(1+$F$32)^5+Valuation!$K$49-Valuation!$K$50-Valuation!$K$51)/Assumptions!$G$57 -> 114.11334
H74: 0.25 | I74: =(SUMPRODUCT((($F$24*(1+$H74)^{1,2,3,4,5})*(($F$25+(I$70-$F$25)*{1,2,3,4,5}/5)*(1-$F$28)+$F$29-$F$30)-(($F$24*(1+$H74)^{1,2,3,4,5})-($F$24*(1+$H74)^({1,2,3,4,5}-1)))*$F$31)/(1+$F$32)^{1,2,3,4,5})+($F$24*(1+$H74)^5*(I$70*(1-$F$28)+$F$29-$F$30)-($F$24*(1+$H74)^5-$F$24*(1+$H74)^4)*$F$31)*(1+$F$33)/($F$32-$F$33)/(1+$F$32)^5+Valuation!$K$49-Valuation!$K$50-Valuation!$K$51)/Assumptions!$G$57 -> 47.979447 | J74: =(SUMPRODUCT((($F$24*(1+$H74)^{1,2,3,4,5})*(($F$25+(J$70-$F$25)*{1,2,3,4,5}/5)*(1-$F$28)+$F$29-$F$30)-(($F$24*(1+$H74)^{1,2,3,4,5})-($F$24*(1+$H74)^({1,2,3,4,5}-1)))*$F$31)/(1+$F$32)^{1,2,3,4,5})+($F$24*(1+$H74)^5*(J$70*(1-$F$28)+$F$29-$F$30)-($F$24*(1+$H74)^5-$F$24*(1+$H74)^4)*$F$31)*(1+$F$33)/($F$32-$F$33)/(1+$F$32)^5+Valuation!$K$49-Valuation!$K$50-Valuation!$K$51)/Assumptions!$G$57 -> 63.071102 | K74: =(SUMPRODUCT((($F$24*(1+$H74)^{1,2,3,4,5})*(($F$25+(K$70-$F$25)*{1,2,3,4,5}/5)*(1-$F$28)+$F$29-$F$30)-(($F$24*(1+$H74)^{1,2,3,4,5})-($F$24*(1+$H74)^({1,2,3,4,5}-1)))*$F$31)/(1+$F$32)^{1,2,3,4,5})+($F$24*(1+$H74)^5*(K$70*(1-$F$28)+$F$29-$F$30)-($F$24*(1+$H74)^5-$F$24*(1+$H74)^4)*$F$31)*(1+$F$33)/($F$32-$F$33)/(1+$F$32)^5+Valuation!$K$49-Valuation!$K$50-Valuation!$K$51)/Assumptions!$G$57 -> 81.364016 | L74: =(SUMPRODUCT((($F$24*(1+$H74)^{1,2,3,4,5})*(($F$25+(L$70-$F$25)*{1,2,3,4,5}/5)*(1-$F$28)+$F$29-$F$30)-(($F$24*(1+$H74)^{1,2,3,4,5})-($F$24*(1+$H74)^({1,2,3,4,5}-1)))*$F$31)/(1+$F$32)^{1,2,3,4,5})+($F$24*(1+$H74)^5*(L$70*(1-$F$28)+$F$29-$F$30)-($F$24*(1+$H74)^5-$F$24*(1+$H74)^4)*$F$31)*(1+$F$33)/($F$32-$F$33)/(1+$F$32)^5+Valuation!$K$49-Valuation!$K$50-Valuation!$K$51)/Assumptions!$G$57 -> 99.656931 | M74: =(SUMPRODUCT((($F$24*(1+$H74)^{1,2,3,4,5})*(($F$25+(M$70-$F$25)*{1,2,3,4,5}/5)*(1-$F$28)+$F$29-$F$30)-(($F$24*(1+$H74)^{1,2,3,4,5})-($F$24*(1+$H74)^({1,2,3,4,5}-1)))*$F$31)/(1+$F$32)^{1,2,3,4,5})+($F$24*(1+$H74)^5*(M$70*(1-$F$28)+$F$29-$F$30)-($F$24*(1+$H74)^5-$F$24*(1+$H74)^4)*$F$31)*(1+$F$33)/($F$32-$F$33)/(1+$F$32)^5+Valuation!$K$49-Valuation!$K$50-Valuation!$K$51)/Assumptions!$G$57 -> 117.94985 | N74: =(SUMPRODUCT((($F$24*(1+$H74)^{1,2,3,4,5})*(($F$25+(N$70-$F$25)*{1,2,3,4,5}/5)*(1-$F$28)+$F$29-$F$30)-(($F$24*(1+$H74)^{1,2,3,4,5})-($F$24*(1+$H74)^({1,2,3,4,5}-1)))*$F$31)/(1+$F$32)^{1,2,3,4,5})+($F$24*(1+$H74)^5*(N$70*(1-$F$28)+$F$29-$F$30)-($F$24*(1+$H74)^5-$F$24*(1+$H74)^4)*$F$31)*(1+$F$33)/($F$32-$F$33)/(1+$F$32)^5+Valuation!$K$49-Valuation!$K$50-Valuation!$K$51)/Assumptions!$G$57 -> 136.24276
H75: 0.3 | I75: =(SUMPRODUCT((($F$24*(1+$H75)^{1,2,3,4,5})*(($F$25+(I$70-$F$25)*{1,2,3,4,5}/5)*(1-$F$28)+$F$29-$F$30)-(($F$24*(1+$H75)^{1,2,3,4,5})-($F$24*(1+$H75)^({1,2,3,4,5}-1)))*$F$31)/(1+$F$32)^{1,2,3,4,5})+($F$24*(1+$H75)^5*(I$70*(1-$F$28)+$F$29-$F$30)-($F$24*(1+$H75)^5-$F$24*(1+$H75)^4)*$F$31)*(1+$F$33)/($F$32-$F$33)/(1+$F$32)^5+Valuation!$K$49-Valuation!$K$50-Valuation!$K$51)/Assumptions!$G$57 -> 55.477038 | J75: =(SUMPRODUCT((($F$24*(1+$H75)^{1,2,3,4,5})*(($F$25+(J$70-$F$25)*{1,2,3,4,5}/5)*(1-$F$28)+$F$29-$F$30)-(($F$24*(1+$H75)^{1,2,3,4,5})-($F$24*(1+$H75)^({1,2,3,4,5}-1)))*$F$31)/(1+$F$32)^{1,2,3,4,5})+($F$24*(1+$H75)^5*(J$70*(1-$F$28)+$F$29-$F$30)-($F$24*(1+$H75)^5-$F$24*(1+$H75)^4)*$F$31)*(1+$F$33)/($F$32-$F$33)/(1+$F$32)^5+Valuation!$K$49-Valuation!$K$50-Valuation!$K$51)/Assumptions!$G$57 -> 73.694311 | K75: =(SUMPRODUCT((($F$24*(1+$H75)^{1,2,3,4,5})*(($F$25+(K$70-$F$25)*{1,2,3,4,5}/5)*(1-$F$28)+$F$29-$F$30)-(($F$24*(1+$H75)^{1,2,3,4,5})-($F$24*(1+$H75)^({1,2,3,4,5}-1)))*$F$31)/(1+$F$32)^{1,2,3,4,5})+($F$24*(1+$H75)^5*(K$70*(1-$F$28)+$F$29-$F$30)-($F$24*(1+$H75)^5-$F$24*(1+$H75)^4)*$F$31)*(1+$F$33)/($F$32-$F$33)/(1+$F$32)^5+Valuation!$K$49-Valuation!$K$50-Valuation!$K$51)/Assumptions!$G$57 -> 95.775855 | L75: =(SUMPRODUCT((($F$24*(1+$H75)^{1,2,3,4,5})*(($F$25+(L$70-$F$25)*{1,2,3,4,5}/5)*(1-$F$28)+$F$29-$F$30)-(($F$24*(1+$H75)^{1,2,3,4,5})-($F$24*(1+$H75)^({1,2,3,4,5}-1)))*$F$31)/(1+$F$32)^{1,2,3,4,5})+($F$24*(1+$H75)^5*(L$70*(1-$F$28)+$F$29-$F$30)-($F$24*(1+$H75)^5-$F$24*(1+$H75)^4)*$F$31)*(1+$F$33)/($F$32-$F$33)/(1+$F$32)^5+Valuation!$K$49-Valuation!$K$50-Valuation!$K$51)/Assumptions!$G$57 -> 117.8574 | M75: =(SUMPRODUCT((($F$24*(1+$H75)^{1,2,3,4,5})*(($F$25+(M$70-$F$25)*{1,2,3,4,5}/5)*(1-$F$28)+$F$29-$F$30)-(($F$24*(1+$H75)^{1,2,3,4,5})-($F$24*(1+$H75)^({1,2,3,4,5}-1)))*$F$31)/(1+$F$32)^{1,2,3,4,5})+($F$24*(1+$H75)^5*(M$70*(1-$F$28)+$F$29-$F$30)-($F$24*(1+$H75)^5-$F$24*(1+$H75)^4)*$F$31)*(1+$F$33)/($F$32-$F$33)/(1+$F$32)^5+Valuation!$K$49-Valuation!$K$50-Valuation!$K$51)/Assumptions!$G$57 -> 139.93894 | N75: =(SUMPRODUCT((($F$24*(1+$H75)^{1,2,3,4,5})*(($F$25+(N$70-$F$25)*{1,2,3,4,5}/5)*(1-$F$28)+$F$29-$F$30)-(($F$24*(1+$H75)^{1,2,3,4,5})-($F$24*(1+$H75)^({1,2,3,4,5}-1)))*$F$31)/(1+$F$32)^{1,2,3,4,5})+($F$24*(1+$H75)^5*(N$70*(1-$F$28)+$F$29-$F$30)-($F$24*(1+$H75)^5-$F$24*(1+$H75)^4)*$F$31)*(1+$F$33)/($F$32-$F$33)/(1+$F$32)^5+Valuation!$K$49-Valuation!$K$50-Valuation!$K$51)/Assumptions!$G$57 -> 162.02048
H76: 0.35 | I76: =(SUMPRODUCT((($F$24*(1+$H76)^{1,2,3,4,5})*(($F$25+(I$70-$F$25)*{1,2,3,4,5}/5)*(1-$F$28)+$F$29-$F$30)-(($F$24*(1+$H76)^{1,2,3,4,5})-($F$24*(1+$H76)^({1,2,3,4,5}-1)))*$F$31)/(1+$F$32)^{1,2,3,4,5})+($F$24*(1+$H76)^5*(I$70*(1-$F$28)+$F$29-$F$30)-($F$24*(1+$H76)^5-$F$24*(1+$H76)^4)*$F$31)*(1+$F$33)/($F$32-$F$33)/(1+$F$32)^5+Valuation!$K$49-Valuation!$K$50-Valuation!$K$51)/Assumptions!$G$57 -> 64.107979 | J76: =(SUMPRODUCT((($F$24*(1+$H76)^{1,2,3,4,5})*(($F$25+(J$70-$F$25)*{1,2,3,4,5}/5)*(1-$F$28)+$F$29-$F$30)-(($F$24*(1+$H76)^{1,2,3,4,5})-($F$24*(1+$H76)^({1,2,3,4,5}-1)))*$F$31)/(1+$F$32)^{1,2,3,4,5})+($F$24*(1+$H76)^5*(J$70*(1-$F$28)+$F$29-$F$30)-($F$24*(1+$H76)^5-$F$24*(1+$H76)^4)*$F$31)*(1+$F$33)/($F$32-$F$33)/(1+$F$32)^5+Valuation!$K$49-Valuation!$K$50-Valuation!$K$51)/Assumptions!$G$57 -> 85.955714 | K76: =(SUMPRODUCT((($F$24*(1+$H76)^{1,2,3,4,5})*(($F$25+(K$70-$F$25)*{1,2,3,4,5}/5)*(1-$F$28)+$F$29-$F$30)-(($F$24*(1+$H76)^{1,2,3,4,5})-($F$24*(1+$H76)^({1,2,3,4,5}-1)))*$F$31)/(1+$F$32)^{1,2,3,4,5})+($F$24*(1+$H76)^5*(K$70*(1-$F$28)+$F$29-$F$30)-($F$24*(1+$H76)^5-$F$24*(1+$H76)^4)*$F$31)*(1+$F$33)/($F$32-$F$33)/(1+$F$32)^5+Valuation!$K$49-Valuation!$K$50-Valuation!$K$51)/Assumptions!$G$57 -> 112.43782 | L76: =(SUMPRODUCT((($F$24*(1+$H76)^{1,2,3,4,5})*(($F$25+(L$70-$F$25)*{1,2,3,4,5}/5)*(1-$F$28)+$F$29-$F$30)-(($F$24*(1+$H76)^{1,2,3,4,5})-($F$24*(1+$H76)^({1,2,3,4,5}-1)))*$F$31)/(1+$F$32)^{1,2,3,4,5})+($F$24*(1+$H76)^5*(L$70*(1-$F$28)+$F$29-$F$30)-($F$24*(1+$H76)^5-$F$24*(1+$H76)^4)*$F$31)*(1+$F$33)/($F$32-$F$33)/(1+$F$32)^5+Valuation!$K$49-Valuation!$K$50-Valuation!$K$51)/Assumptions!$G$57 -> 138.91992 | M76: =(SUMPRODUCT((($F$24*(1+$H76)^{1,2,3,4,5})*(($F$25+(M$70-$F$25)*{1,2,3,4,5}/5)*(1-$F$28)+$F$29-$F$30)-(($F$24*(1+$H76)^{1,2,3,4,5})-($F$24*(1+$H76)^({1,2,3,4,5}-1)))*$F$31)/(1+$F$32)^{1,2,3,4,5})+($F$24*(1+$H76)^5*(M$70*(1-$F$28)+$F$29-$F$30)-($F$24*(1+$H76)^5-$F$24*(1+$H76)^4)*$F$31)*(1+$F$33)/($F$32-$F$33)/(1+$F$32)^5+Valuation!$K$49-Valuation!$K$50-Valuation!$K$51)/Assumptions!$G$57 -> 165.40202 | N76: =(SUMPRODUCT((($F$24*(1+$H76)^{1,2,3,4,5})*(($F$25+(N$70-$F$25)*{1,2,3,4,5}/5)*(1-$F$28)+$F$29-$F$30)-(($F$24*(1+$H76)^{1,2,3,4,5})-($F$24*(1+$H76)^({1,2,3,4,5}-1)))*$F$31)/(1+$F$32)^{1,2,3,4,5})+($F$24*(1+$H76)^5*(N$70*(1-$F$28)+$F$29-$F$30)-($F$24*(1+$H76)^5-$F$24*(1+$H76)^4)*$F$31)*(1+$F$33)/($F$32-$F$33)/(1+$F$32)^5+Valuation!$K$49-Valuation!$K$50-Valuation!$K$51)/Assumptions!$G$57 -> 191.88412
C77: Base-case parameter pair outlined in Tesla red.
C78: PREMIUM / (DISCOUNT) VERSUS THE MARKET PRICE
H79: =$F$55 -> -0.91433472 | I79: =I70 -> 0.127 | J79: =J70 -> 0.16 | K79: =K70 -> 0.2 | L79: =L70 -> 0.24 | M79: =M70 -> 0.28 | N79: =N70 -> 0.32
H80: =H71 -> 0.112 | I80: =I71/$F$6-1 -> -0.91433472 | J80: =J71/$F$6-1 -> -0.8913609 | K80: =K71/$F$6-1 -> -0.86351383 | L80: =L71/$F$6-1 -> -0.83566677 | M80: =M71/$F$6-1 -> -0.80781971 | N80: =N71/$F$6-1 -> -0.77997265
H81: =H72 -> 0.15 | I81: =I72/$F$6-1 -> -0.90453872 | J81: =J72/$F$6-1 -> -0.87759953 | K81: =K72/$F$6-1 -> -0.84494595 | L81: =L72/$F$6-1 -> -0.81229238 | M81: =M72/$F$6-1 -> -0.77963881 | N81: =N72/$F$6-1 -> -0.74698523
H82: =H73 -> 0.2 | I82: =I73/$F$6-1 -> -0.88973811 | J82: =J73/$F$6-1 -> -0.85674962 | K82: =K73/$F$6-1 -> -0.81676358 | L82: =L73/$F$6-1 -> -0.77677753 | M82: =M73/$F$6-1 -> -0.73679149 | N82: =N73/$F$6-1 -> -0.69680544
H83: =H74 -> 0.25 | I83: =I74/$F$6-1 -> -0.87252053 | J83: =J74/$F$6-1 -> -0.83242261 | K83: =K74/$F$6-1 -> -0.78381907 | L83: =L74/$F$6-1 -> -0.73521553 | M83: =M74/$F$6-1 -> -0.68661199 | N83: =N74/$F$6-1 -> -0.63800845
H84: =H75 -> 0.3 | I84: =I75/$F$6-1 -> -0.85259973 | J84: =J75/$F$6-1 -> -0.80419717 | K84: =K75/$F$6-1 -> -0.74552739 | L84: =L75/$F$6-1 -> -0.68685762 | M84: =M75/$F$6-1 -> -0.62818784 | N84: =N75/$F$6-1 -> -0.56951807
H85: =H76 -> 0.35 | I85: =I76/$F$6-1 -> -0.82966767 | J85: =J76/$F$6-1 -> -0.77161911 | K85: =K76/$F$6-1 -> -0.70125723 | L85: =L76/$F$6-1 -> -0.63089534 | M85: =M76/$F$6-1 -> -0.56053346 | N85: =N76/$F$6-1 -> -0.49017157
A87: CROSS-CHECK — IMPLIED VALUE AT LOWER DISCOUNT RATES
C88: Base-case parameters throughout; only the discount rate changes. This tests whether the valuation gap could be a discount-rate artefact. Terminal growth is held at the model rate, so every column still satisfies WACC > g.
C89: WACC applied | H89: 0.12 | I89: 0.1 | J89: 0.08 | K89: 0.06 | L89: 0.05
C90: Implied value per share at Base Case parameters | H90: =(SUMPRODUCT((($F$24*(1+$F$26)^{1,2,3,4,5})*(($F$25+($F$27-$F$25)*{1,2,3,4,5}/5)*(1-$F$28)+$F$29-$F$30)-(($F$24*(1+$F$26)^{1,2,3,4,5})-($F$24*(1+$F$26)^({1,2,3,4,5}-1)))*$F$31)/(1+H$89)^{1,2,3,4,5})+($F$24*(1+$F$26)^5*($F$27*(1-$F$28)+$F$29-$F$30)-($F$24*(1+$F$26)^5-$F$24*(1+$F$26)^4)*$F$31)*(1+$F$33)/(H$89-$F$33)/(1+H$89)^5+Valuation!$K$49-Valuation!$K$50-Valuation!$K$51)/Assumptions!$G$57 -> 33.490621 | I90: =(SUMPRODUCT((($F$24*(1+$F$26)^{1,2,3,4,5})*(($F$25+($F$27-$F$25)*{1,2,3,4,5}/5)*(1-$F$28)+$F$29-$F$30)-(($F$24*(1+$F$26)^{1,2,3,4,5})-($F$24*(1+$F$26)^({1,2,3,4,5}-1)))*$F$31)/(1+I$89)^{1,2,3,4,5})+($F$24*(1+$F$26)^5*($F$27*(1-$F$28)+$F$29-$F$30)-($F$24*(1+$F$26)^5-$F$24*(1+$F$26)^4)*$F$31)*(1+$F$33)/(I$89-$F$33)/(1+I$89)^5+Valuation!$K$49-Valuation!$K$50-Valuation!$K$51)/Assumptions!$G$57 -> 42.62148 | J90: =(SUMPRODUCT((($F$24*(1+$F$26)^{1,2,3,4,5})*(($F$25+($F$27-$F$25)*{1,2,3,4,5}/5)*(1-$F$28)+$F$29-$F$30)-(($F$24*(1+$F$26)^{1,2,3,4,5})-($F$24*(1+$F$26)^({1,2,3,4,5}-1)))*$F$31)/(1+J$89)^{1,2,3,4,5})+($F$24*(1+$F$26)^5*($F$27*(1-$F$28)+$F$29-$F$30)-($F$24*(1+$F$26)^5-$F$24*(1+$F$26)^4)*$F$31)*(1+$F$33)/(J$89-$F$33)/(1+J$89)^5+Valuation!$K$49-Valuation!$K$50-Valuation!$K$51)/Assumptions!$G$57 -> 60.582263 | K90: =(SUMPRODUCT((($F$24*(1+$F$26)^{1,2,3,4,5})*(($F$25+($F$27-$F$25)*{1,2,3,4,5}/5)*(1-$F$28)+$F$29-$F$30)-(($F$24*(1+$F$26)^{1,2,3,4,5})-($F$24*(1+$F$26)^({1,2,3,4,5}-1)))*$F$31)/(1+K$89)^{1,2,3,4,5})+($F$24*(1+$F$26)^5*($F$27*(1-$F$28)+$F$29-$F$30)-($F$24*(1+$F$26)^5-$F$24*(1+$F$26)^4)*$F$31)*(1+$F$33)/(K$89-$F$33)/(1+K$89)^5+Valuation!$K$49-Valuation!$K$50-Valuation!$K$51)/Assumptions!$G$57 -> 111.48073 | L90: =(SUMPRODUCT((($F$24*(1+$F$26)^{1,2,3,4,5})*(($F$25+($F$27-$F$25)*{1,2,3,4,5}/5)*(1-$F$28)+$F$29-$F$30)-(($F$24*(1+$F$26)^{1,2,3,4,5})-($F$24*(1+$F$26)^({1,2,3,4,5}-1)))*$F$31)/(1+L$89)^{1,2,3,4,5})+($F$24*(1+$F$26)^5*($F$27*(1-$F$28)+$F$29-$F$30)-($F$24*(1+$F$26)^5-$F$24*(1+$F$26)^4)*$F$31)*(1+$F$33)/(L$89-$F$33)/(1+L$89)^5+Valuation!$K$49-Valuation!$K$50-Valuation!$K$51)/Assumptions!$G$57 -> 200.76335
A92: CONCLUSION
C93: ="At "&TEXT($F$6,"$0.00")&" per share the market implies an enterprise value of $"&TEXT($F$12,"#,##0")&"M, which is "&TEXT($F$18,"0.0")&"x the fundamental DCF enterprise value. Justifying it on the modelled economics would require FY2030E free cash flow of about $"&TEXT($F$59,"#,##0")&"M, roughly "&TEXT($F$61,"0.0")&"x the Base Case, on implied FY2030E revenue of about $"&TEXT($F$63,"#,##0")&"M at the modelled margin — or an EBIT margin of "&TEXT($F$64,"0.0%")&" if revenue only reached the Bull Case. Across the grid the highest implied value is "&TEXT(MAX(I71:N76),"$0.00")&" per share, "&TEXT(MAX(I71:N76)/$F$6-1,"0.0%")&" versus the market, and at a "&TEXT(L89,"0.0%")&" discount rate the Base Case still implies only "&TEXT(L90,"$0.00")&_xlfn._LONGTEXT(". The gap is therefore not a discount-rate or terminal-growth artefact: at the current price the market appears to require operating performance materially above the fundamental Base Case, or to be capitalising businesses this model does not forecast as s","eparate cash-flow streams.") -> At $376.37 per share the market implies an enterprise value of $1,451,707M, which is 15.5x the fundamental DCF enterprise value. Justifying it on the modelled economics would require FY2030E free cash flow of about $169,982M, roughly 15.7x the Base Case, on implied FY2030E revenue of about $2,533,154M at the modelled margin — or an EBIT margin of 155.8% if revenue only reached the Bull Case. Across the grid the highest implied value is $191.88 per share, -49.0% versus the market, and at a 5.0% discount rate the Base Case still implies only $200.76. The gap is therefore not a discount-rate or terminal-growth artefact: at the current price the market appears to require operating performance materially above the fundamental Base Case, or to be capitalising businesses this model does not forecast as separate cash-flow streams.

Sheet Model Checks
A1: TESLA, INC. | E1: ◄ Cover | G1: MODEL CHECKS
A2: Every check is a live formula. The four marked ▲ are mirrored on the Model Summary; the rest live here so the summary stays uncluttered.
A4: INTEGRITY CHECKS
C5: Check | E5: Result | G5: What it tests
C6: ▲ Balance Sheet Check, FY2021A–FY2030E | E6: =IF(COUNTIF(BS!$G$37:$P$37,"PASS")=10,"PASS","FAIL") -> PASS | G6: Total assets equal total liabilities and equity in all ten years, within $0.5M.
C7: ▲ Cash Check, FY2021A–FY2030E | E7: =IF(COUNTIF(Cashflow!$G$34:$P$34,"PASS")=10,"PASS","FAIL") -> PASS | G7: Closing cash on the cash flow statement ties to balance sheet cash in all ten years.
C8: Retained Earnings Check (forecast) | E8: =IF(SUMPRODUCT(--(ABS(BS!$L$31:$P$31-(BS!$K$31:$O$31+IS!$L$43:$P$43))>0.5))=0,"PASS","FAIL") -> PASS | G8: Closing retained earnings equal opening retained earnings plus net income, no dividends.
C9: Debt Schedule Check, FY2021A–FY2030E | E9: =IF(SUMPRODUCT(--(ABS(BS!$G$20:$P$20+BS!$G$23:$P$23-'Loans & Other Income'!$G$8:$P$8)>0.5))=0,"PASS","FAIL") -> PASS | G9: Current plus long-term debt on the balance sheet ties to the closing debt schedule balance.
C10: ▲ Scenario Selector Check | E10: =IF(AND(Assumptions!$L$2>=1,Assumptions!$L$2<=3,Assumptions!$L$2=INT(Assumptions!$L$2)),"PASS","FAIL") -> PASS | G10: The selector holds a whole number between 1 and 3, so CHOOSE resolves on every driver row.
C11: ▲ WACC > Terminal Growth Check | E11: =IF(Valuation!$F$17>Valuation!$F$18,"PASS","FAIL") -> PASS | G11: The Gordon Growth denominator is positive, so the terminal value is meaningful.
C12: Historical Data Completeness | E12: =IF(AND(COUNT(IS!$G$8:$K$8)=5,COUNT(BS!$G$14:$K$14)=5,COUNT('Revenue Build-up'!$G$5:$K$5)=5,COUNT(Cashflow!$G$32:$K$32)=5),"PASS","FAIL") -> PASS | G12: Five years of revenue, total assets, deliveries and closing cash are present as actuals.
C13: Forecast Formula Check | E13: =IF(SUMPRODUCT(--(ABS(IS!$L$8:$P$8-('Revenue Build-up'!$L$9:$P$9+'Revenue Build-up'!$L$12:$P$12+'Revenue Build-up'!$L$15:$P$15))>0.5))+SUMPRODUCT(--(ABS(IS!$L$25:$P$25-(IS!$L$16:$P$16-IS!$L$23:$P$23))>0.5))+SUMPRODUCT(--(ABS(Valuation!$L$28:$P$28-(Valuation!$L$24:$P$24+Valuation!$L$25:$P$25-Valuation!$L$26:$P$26-Valuation!$L$27:$P$27))>0.5))=0,"PASS","FAIL") -> PASS | G13: Forecast columns still resolve from their drivers: revenue ties to the revenue build, EBIT to gross profit less operating expenses, FCFF to its components. A hardcode pasted over any of them breaks the identity.
C14: No External Workbook Links | E14: =IF(ISERROR(_xlfn.FORMULATEXT(IS!$G$8)),"n/a — needs Excel 2013+",IF(SUMPRODUCT(--ISNUMBER(SEARCH("[",IFERROR(_xlfn.FORMULATEXT(Valuation!$C$5:$P$94),""))))+SUMPRODUCT(--ISNUMBER(SEARCH("[",IFERROR(_xlfn.FORMULATEXT(IS!$G$5:$P$48),""))))=0,"PASS","FAIL")) -> PASS | G14: No formula references another workbook. Self-validating: shows n/a rather than a false PASS in applications without FORMULATEXT. Verified as clean at build time.
C15: No Formula Errors | E15: =IF(SUMPRODUCT(--ISERROR(IS!$G$5:$P$48))+SUMPRODUCT(--ISERROR(BS!$G$5:$P$35))+SUMPRODUCT(--ISERROR(Valuation!$L$22:$P$44))=0,"PASS","FAIL") -> PASS | G15: No #REF!, #VALUE!, #DIV/0! or #NAME? in the statements or the FCFF build.
A17: OVERALL
C18: All checks passing | E18: =IF(COUNTIF(E6:E15,"FAIL")=0,"PASS","FAIL") -> PASS | G18: PASS when none of the 10 checks above returns FAIL.
C20: Tolerances: balance sheet, cash, retained earnings and debt checks use a $0.5M tolerance, which is below rounding materiality on a balance sheet of this size. The external-link and formula-error checks scan the ranges named beside them rather than the whole workbook; the chart-source block on Ratio Analysis deliberately returns #N/A outside its period and is excluded by design.

Sheet Sources & Notes
A1: TESLA, INC. | E1: ◄ Cover | G1: SOURCES & NOTES
A2: Every material external input in the workbook, with its source. Prepared for audit: a reader should be able to trace any hardcoded number back to a primary document.
A4: VERIFICATION STATUS
B5: ● Verified against the named public source at the access date shown. ▲ Not fully primary-source verified or intentionally treated as an analyst assumption; see the row note before publication.
B7: Category | C7: Metric | D7: Company | E7: Period | F7: Value | G7: Unit | H7: Source | I7: Publication Date | J7: Access Date | K7: URL / Filing Reference | L7: Notes
B8: TESLA — FINANCIALS | C8: Income statement, all lines | D8: Tesla, Inc. | E8: FY2021A–FY2025A | F8: see IS | G8: $M | H8: ● Tesla 2025 Form 10-K; prior-year comparatives in Tesla annual filings | I8: 2026 | J8: 07-Sep-2026 | K8: https://www.sec.gov/Archives/edgar/data/1318605/000162828026003952/tsla-20251231.htm | L8: Verified against Tesla's FY2025 Form 10-K and comparative annual-report disclosures. Historical model values retained.
B9: TESLA — FINANCIALS | C9: Balance sheet, all lines | D9: Tesla, Inc. | E9: FY2021A–FY2025A | F9: see BS | G9: $M | H9: ● Tesla 2025 Form 10-K; prior-year comparatives in Tesla annual filings | I9: 2026 | J9: 07-Sep-2026 | K9: https://www.sec.gov/Archives/edgar/data/1318605/000162828026003952/tsla-20251231.htm | L9: Verified against Tesla's FY2025 Form 10-K and comparative annual-report disclosures.
B10: TESLA — FINANCIALS | C10: Cash flow statement, historical lines | D10: Tesla, Inc. | E10: FY2021A–FY2025A | F10: see Cashflow | G10: $M | H10: ● Tesla 2025 Form 10-K; prior-year comparatives in Tesla annual filings | I10: 2026 | J10: 07-Sep-2026 | K10: https://www.sec.gov/Archives/edgar/data/1318605/000162828026003952/tsla-20251231.htm | L10: Verified against Tesla's consolidated cash-flow statements; historical model values retained.
B11: TESLA — FINANCIALS | C11: Segment revenue: Automotive / Energy / Services | D11: Tesla, Inc. | E11: FY2021A–FY2025A | F11: see Revenue Build-up | G11: $M | H11: ● Tesla Form 10-K revenue disclosures | I11: 2026 | J11: 07-Sep-2026 | K11: https://www.sec.gov/Archives/edgar/data/1318605/000162828026003952/tsla-20251231.htm | L11: FY2025 segment revenue verified: Automotive $69,526M; Energy $12,771M; Services & Other $12,530M.
B12: TESLA — OPERATING | C12: Vehicle deliveries | D12: Tesla, Inc. | E12: FY2021A–FY2025A | F12: see 'Revenue Build-up'!G5:K5 | G12: units | H12: ● Tesla quarterly production & delivery disclosures / annual totals | I12: 2021–2026 | J12: 07-Sep-2026 | K12: https://ir.tesla.com/ | L12: Verified annual deliveries: FY2021 936,172; FY2022 1,313,851; FY2023 1,808,581; FY2024 1,789,226; FY2025 1,636,129.
B13: TESLA — OPERATING | C13: Automotive regulatory credit revenue | D13: Tesla, Inc. | E13: FY2021A–FY2025A | F13: see 'Revenue Build-up'!G8:K8 | G13: $M | H13: ● Tesla Form 10-K, automotive revenues note | I13: 2026 | J13: 07-Sep-2026 | K13: https://www.sec.gov/Archives/edgar/data/1318605/000162828026003952/tsla-20251231.htm | L13: FY2025 regulatory-credit revenue verified at $1,993M; historical series retained.
B14: TESLA — OPERATING | C14: Energy storage deployed | D14: Tesla, Inc. | E14: FY2021A | F14: 3.99 | G14: GWh | H14: ▲ Q4 2021 quarterly update deck | I14: n/d | J14: n/d | K14: ir.tesla.com — Quarterly Disclosures | L14: Used as context only, not as a forecast driver.
B15: TESLA — OPERATING | C15: Energy storage deployed | D15: Tesla, Inc. | E15: FY2022A | F15: 6.5 | G15: GWh | H15: ▲ Q4 2022 quarterly update deck | I15: n/d | J15: n/d | K15: ir.tesla.com — Quarterly Disclosures | L15: Context only.
B16: TESLA — OPERATING | C16: Energy storage deployed | D16: Tesla, Inc. | E16: FY2023A | F16: 14.7 | G16: GWh | H16: ● Energy-Storage.News, reporting Tesla Q4 2023 update | I16: n/d | J16: 07-Sep-2026 | K16: energy-storage.news/tesla-deployed-14-7gwh-of-energy-storage-in-2023/ | L16: Context only.
B17: TESLA — OPERATING | C17: Energy storage deployed | D17: Tesla, Inc. | E17: FY2024A | F17: 31.4 | G17: GWh | H17: ● Utility Dive, reporting Tesla Q4 2024 results | I17: n/d | J17: 07-Sep-2026 | K17: utilitydive.com/news/tesla-battery-storage-powerwall-megapack-earnings/738751/ | L17: Context only.
B18: TESLA — OPERATING | C18: Energy storage deployed | D18: Tesla, Inc. | E18: FY2025A | F18: 46.7 | G18: GWh | H18: ● Renewables Now, reporting Tesla FY2025 deployments | I18: n/d | J18: 07-Sep-2026 | K18: renewablesnow.com/news/teslas-2025-energy-storage-deployments-hit-all-time-high-of-46-7-gwh-1289136/ | L18: Anchors the revenue-per-GWh cross-check on the Revenue Build-up sheet.
B19: TESLA — BALANCE SHEET | C19: Cash & short-term investments | D19: Tesla, Inc. | E19: FY2025A | F19: 44059 | G19: $M | H19: ● Tesla 2025 Form 10-K, Consolidated Balance Sheets | I19: 2026 | J19: 07-Sep-2026 | K19: https://www.sec.gov/Archives/edgar/data/1318605/000162828026003952/tsla-20251231.htm | L19: Verified FY2025 cash + short-term investments = $44,059M; used in EV-to-equity bridge.
B20: TESLA — BALANCE SHEET | C20: Debt + finance leases, current + non-current | D20: Tesla, Inc. | E20: FY2025A | F20: 8376 | G20: $M | H20: ● Tesla 2025 Form 10-K, debt and finance-lease disclosures | I20: 2026 | J20: 07-Sep-2026 | K20: https://www.sec.gov/Archives/edgar/data/1318605/000162828026003952/tsla-20251231.htm | L20: Verified $8,376M carrying value. Label is debt + finance leases (current + non-current), not an observed market value.
B21: TESLA — BALANCE SHEET | C21: Noncontrolling interests | D21: Tesla, Inc. | E21: FY2025A | F21: 728 | G21: $M | H21: ● Tesla 2025 Form 10-K, redeemable and non-redeemable NCI | I21: 2026 | J21: 07-Sep-2026 | K21: https://www.sec.gov/Archives/edgar/data/1318605/000162828026003952/tsla-20251231.htm | L21: Verified total NCI = $728M, comprising the relevant redeemable and non-redeemable interests used in the bridge.
B22: TESLA — SHARES | C22: Current common shares outstanding | D22: Tesla, Inc. | E22: Sep 2026 | F22: 3950 | G22: millions | H22: ● Tesla Q2 2026 Form 10-Q cover page | I22: 2026-07-24 | J22: 07-Sep-2026 | K22: https://www.sec.gov/Archives/edgar/data/1318605/000162828026049270/tsla-20260630.htm | L22: Verified 3,949,547,394 common shares outstanding as of 16-Jul-2026; model rounds to 3,950M. This is current common shares outstanding, not diluted weighted-average shares.
B23: MARKET DATA | C23: Share price, valuation-date close | D23: Tesla, Inc. | E23: 03-Sep-2026 | F23: 376.37 | G23: $/share | H23: ● Yahoo Finance historical market close | I23: 03-Sep-2026 | J23: 07-Sep-2026 | K23: https://finance.yahoo.com/quote/TSLA/ | L23: Verified TSLA close = $376.37 on 03-Sep-2026. Single source-of-truth remains Assumptions!G56.
B24: MARKET DATA | C24: Risk-free rate, 10-yr US Treasury | D24: US Treasury | E24: 03-Sep-2026 | F24: 4.77 | G24: % | H24: ● U.S. Treasury Daily Treasury Par Yield Curve | I24: 03-Sep-2026 | J24: 07-Sep-2026 | K24: https://home.treasury.gov/resource-center/data-chart-center/interest-rates/TextView?type=daily_treasury_yield_curve | L24: Verified 10-year U.S. Treasury yield = 4.77% on 03-Sep-2026.
B25: MARKET DATA | C25: Levered beta | D25: Tesla, Inc. | E25: 03-Sep-2026 | F25: 1.85 | G25: x | H25: ● Yahoo Finance — Beta (5Y Monthly) | I25: Sep-2026 | J25: 07-Sep-2026 | K25: https://finance.yahoo.com/quote/TSLA/ | L25: Verified current 5Y monthly beta = 1.85. Workbook still contains 1.84 pending the user's manual update; do not treat 1.84 as the verified value.
... B27: MARKET DATA | C27: Pre-tax cost of debt | D27: Tesla, Inc. | E27: Sep 2026 | F27: 5 | G27: % | H27: ▲ Analyst assumption; Tesla debt disclosures used as reasonableness check | I27: Sep-2026 | J27: 07-Sep-2026 | K27: https://www.sec.gov/Archives/edgar/data/1318605/000162828026003952/tsla-20251231.htm | L27: 5.00% is not a directly observed blended market yield. Treat as a normalized pre-tax cost-of-debt assumption unless a specific yield methodology is added.
B28: PEER DATA | C28: Share price, market cap, EV, revenue, EBITDA, EBIT, net income, book value | D28: BYDDY, RIVN, LCID, NIO, LI, GM, F | E28: TTM to 30-Jun-2026; priced 03-Sep-2026 | F28: see Comparable Companies rows 17–23 | G28: $M / $ | H28: ▲ Individual peer filings + historical market closes — company-by-company verification still required | I28: n/d | J28: 07-Sep-2026 | K28: https://www.sec.gov/edgar/searchedgar/companysearch | L28: Do not mark this row verified as a group. Each peer's TTM financials and 03-Sep-2026 market data should be tied to its own filing/provider before publication.
B29: PEER DATA | C29: Tesla TTM revenue, EBITDA, EBIT, net income, book value | D29: Tesla, Inc. | E29: TTM to 30-Jun-2026 | F29: see Comparable Companies row 34 | G29: $M | H29: ● Tesla 2025 Form 10-K + Q2 2026 Form 10-Q / TTM calculation | I29: 2026 | J29: 07-Sep-2026 | K29: https://www.sec.gov/Archives/edgar/data/1318605/000162828026049270/tsla-20260630.htm | L29: Tesla TTM metrics are derived from FY2025 plus H1 2026 less H1 2025 where applicable; Tesla remains excluded from peer percentile statistics.
B30: PRECEDENT TRANSACTIONS | C30: Zoox / Amazon | D30: Amazon.com, Inc. | E30: Announced 26-Jun-2020 | F30: 1200 | G30: $M | H30: ▲ Amazon acquisition announcement confirms transaction; purchase price not disclosed by Amazon | I30: 26-Jun-2020 | J30: 07-Sep-2026 | K30: https://www.aboutamazon.com/news/company-news/were-acquiring-zoox-to-help-bring-their-vision-of-autonomous-ride-hailing-to-reality | L30: $1.2B remains a secondary-source figure and should not be presented as primary-source verified until a named secondary source is added.
B31: PRECEDENT TRANSACTIONS | C31: Cruise stake / General Motors | D31: General Motors Company | E31: Announced Nov 2021 | F31: 2100 | G31: $M | H31: ● General Motors investor announcement / SEC disclosure | I31: 18-Mar-2022 | J31: 07-Sep-2026 | K31: https://investor.gm.com/news-releases/news-release-details/gm-announces-additional-investment-cruise | L31: Verified: GM acquired SoftBank Vision Fund 1's Cruise equity stake for $2.1B. Target LTM financials not disclosed.
B32: PRECEDENT TRANSACTIONS | C32: Lordstown Ohio plant / Foxconn | D32: Hon Hai Technology Group | E32: Announced 11-May-2022 | F32: 230 | G32: $M | H32: ● Lordstown Motors / Foxconn company announcement | I32: 11-May-2022 | J32: 07-Sep-2026 | K32: https://investor.lordstownmotors.com/news-releases/news-release-details/lordstown-motors-and-foxconn-close-asset-purchase-agreement-and | L32: Verified $230M plant purchase price; asset purchase, not a whole-company transaction.
B33: PRECEDENT TRANSACTIONS | C33: AKASOL / BorgWarner | D33: BorgWarner Inc. | E33: Announced Dec 2021 | F33: 882 | G33: $M | H33: ● BorgWarner acquisition announcement; EUR/USD conversion at announcement date | I33: 15-Feb-2021 | J33: 07-Sep-2026 | K33: https://www.borgwarner.com/newsroom/press-releases/2021/02/15/borgwarner-agrees-to-acquire-akasol-ag-seeking-to-expand-electrification-portfolio | L33: Primary source values 100% of AKASOL equity at ~€727M. Converted at 1 EUR = 1.2132 USD on 15-Feb-2021, giving ~US$882M; FX cross-check: https://www.exchange-rates.org/exchange-rate-history/eur-usd-2021
B34: PRECEDENT TRANSACTIONS | C34: Boston Dynamics / Hyundai | D34: Hyundai Motor Group | E34: Announced Dec 2020 | F34: 1100 | G34: $M | H34: ● Hyundai Motor Group acquisition announcement | I34: 11-Dec-2020 | J34: 07-Sep-2026 | K34: https://www.hyundai.com/worldwide/en/newsroom/detail/0000000577 | L34: Verified: transaction valued Boston Dynamics at $1.1B; Hyundai Motor Group to acquire an approximately 80% stake.
B35: MODEL ASSUMPTIONS | C35: All FY2026E–FY2030E operating drivers, three cases | D35: Tesla, Inc. | E35: FY2026E–FY2030E | F35: see Assumptions rows 68–100 | G35: various | H35: Author’s own estimates | I35: n/d | J35: n/d | K35: No external source | L35: Rationale for each block is set out in the callout boxes on the Assumptions sheet.
B36: MODEL ASSUMPTIONS | C36: Working capital, depreciation, tax, financing and equity ratios | D36: Tesla, Inc. | E36: FY2026E–FY2030E | F36: see Assumptions rows 29–53 | G36: various | H36: Author’s own estimates, anchored on FY2021A–FY2025A actuals | I36: n/d | J36: n/d | K36: No external source | L36: Common to all three scenario cases.
B38: Priority of sources: (1) SEC filings and Tesla Investor Relations disclosures; (2) peer filings and investor-relations disclosures; (3) reputable market-data providers, used only where a primary filing cannot supply the market input. No value in the workbook was sourced from an unattributed aggregator.
